Workbook

Sheet START
A1: DZIF Intelligence Master | v2.3
A3: Pflegequelle Excel | Geprueft am 29.10.2026 | Routine: Competitor, Funding, BD
A5: ZWECK: Quellen und Entitaeten finden, projektbezogen auswaehlen und Recherche priorisieren.
A6: KEINE Ergebnisdatenbank: Phasen, Calls, Fristen, Deals und klinische Evidenz werden live verifiziert.
A7: Reservierte Firmen bleiben in Excel. JSON enthaelt nur operative Routen und deren Abhaengigkeiten.
B9: Organisationen | C9: M01 gesamt | D9: M01 operativ | E9: Funding-Routen | F9: Quellen
B10: =COUNTA(ENTITY_MASTER!A2:A266) -> 265 | C10: =COUNTA(M01_COMPETITORS!A2:A245) -> 244 | D10: =COUNTIF(M01_COMPETITORS!Q2:Q245,"CONDITIONAL")+COUNTIF(M01_COMPETITORS!Q2:Q245,"CORE") -> 103 | E10: =COUNTA(M05_FUNDING!A2:A68) -> 67 | F10: =COUNTA(SOURCE_REGISTRY!A2:A246) -> 245
A12: Flagship-Pruefung | C12: 11 reale DZIF-Beispiele; Scope, Korrektur und verbleibende Luecken.
A13: Effizienzentscheidungen | C13: Was bleibt, was archiviert ist und welche Unsicherheiten bestehen.
A14: Offene Datenpruefung | C14: Keine Pflicht zur erneuten Vollrecherche aller Reservefirmen.
A16: Modul | D16: Katalogzeilen | E16: Routine | F16: Funktion
A17: M01 | Competitor & Asset Intelligence | D17: =COUNTA(M01_COMPETITORS!A2:A245) -> 244 | E17: AKTIV | F17: Suchprofile
A18: M02 | Clinical Trial Intelligence | D18: =COUNTA(M02_CLINICAL!A2:A6) -> 5 | E18: RESERVIERT | F18: Quellenanker
A19: M03 | Scientific & Technology Intelligence | D19: =COUNTA(M03_SCI_TECH!A2:A4) -> 3 | E19: RESERVIERT | F19: Quellenanker
A20: M04 | Regulatory Intelligence | D20: =COUNTA(M04_REGULATORY!A2:A11) -> 10 | E20: RESERVIERT | F20: Quellenanker
A21: M05 | Funding Opportunities | D21: =COUNTA(M05_FUNDING!A2:A68) -> 67 | E21: AKTIV | F21: Suchprofile
A22: M06 | BD & Partnering Intelligence | D22: =COUNTA(M06_BD_PARTNERS!A2:A79) -> 78 | E22: AKTIV | F22: Suchprofile
A23: M07 | Deal & Investment Intelligence | D23: =COUNTA(M07_DEALS!A2:A58) -> 57 | E23: RESERVIERT | F23: Suchprofile
A24: M08 | Conference & Event Intelligence | D24: =COUNTA(M08_EVENTS!A2:A8) -> 7 | E24: RESERVIERT | F24: Quellenanker
A25: M09 | Clinical & Medical Landscape | D25: =COUNTA(M09_MEDICAL!A2:A7) -> 6 | E25: RESERVIERT | F25: Quellenanker
A26: M10 | IP & Patent Intelligence | D26: =COUNTA(M10_IP_PATENT!A2:A4) -> 3 | E26: RESERVIERT | F26: Quellenanker
A27: M11 | CMC & Manufacturing Intelligence | D27: =COUNTA(M11_CMC!A2:A8) -> 7 | E27: RESERVIERT | F27: Quellenanker
A28: M12 | Policy, Market & Access Intelligence | D28: =COUNTA(M12_POLICY_ACCESS!A2:A8) -> 7 | E28: RESERVIERT | F28: Quellenanker
A31: PFLEGE | B31: IDs erhalten; nur belegte neue Angaben eintragen. Pflichtfelder nicht leer lassen. Optionale Elternbeziehung, Alias oder API-Felder duerfen leer sein.
A32: AUSWAHL | B32: own_asset_ids im Projekt-Intake angeben. Gleicher Erreger ist nicht automatisch gleicher klinischer Zweck. Rueckstellungen sind sichtbar.
A33: EXPORT | B33: Mit export_master.py neu erzeugen. DISCOVERY/PAUSED/INACTIVE und unreferenzierte Entitaeten/Quellen werden nicht in den Standardexport geladen.
A34: ARCHIV | B34: Historische Seeds, Discovery Pool und 18 ausgelagerte Blaetter liegen unveraendert im Integrations-/Auditpaket; v2.2-Original ebenfalls enthalten.
A35: ABNAHME | B35: 109 lokale technische Checks bestanden. 11 Flagships plus 13 Kontrastprofile. Keine externe Recall-Messung und kein Langdock-End-to-End-Test.
A36: RECHTE | B36: GlobalData-abgeleitete Inhalte nur im geklaerten Nutzungsrahmen. Privates GitHub-Repository allein ersetzt keine Weitergaberechte.

Sheet MODULE_CONFIG
A1: module_id | B1: module_name | C1: sheet_name | D1: module_priority | E1: routine_enabled | F1: run_cadence | G1: candidate_cap | H1: max_live_checks | I1: discovery_queries | J1: freshness_days | K1: catalog_review_months | L1: selection_basis | M1: output_focus | N1: policy_note | O1: catalog_status | P1: integration_status | Q1: default_query_id
A2: M01 | B2: Competitor & Asset Intelligence | C2: M01_COMPETITORS | D2: SEHR_HOCH | E2: YES | F2: MONTHLY | G2: 25 | H2: 12 | I2: 2 | J2: 30 | K2: 12 | L2: EVIDENCE_TIER > pathogen/indication/target > MoA/modality > stage > specific topic > base priority | M2: Asset / Wettbewerbsentwicklung | N2: Direct asset and clinical-context anchors precede general companies; no forced field quotas; all budget omissions visible. | O2: POPULATED_REFERENCE_INDEX | P2: LOCAL_SELECTOR_ONLY | Q2: M01_ENTITY
A3: M02 | B3: Clinical Trial Intelligence | C3: M02_CLINICAL | D3: SEHR_HOCH | E3: NO | F3: MONTHLY | G3: 15 | H3: 8 | I3: 2 | J3: 14 | K3: 12 | L3: SCOPE_MATCH;PROJECT_MATCH;PRIORITY;STABLE_ID | M3: Studie / Studiendelta | N3: Budget = Planungsannahme. Erst lokal filtern; Quellen nicht vollstaendig in Agentenprompt laden. Unabhaengige Discovery bleibt. Kein Persistenz-/Live-Connector-Test. | O3: POPULATED_REFERENCE_INDEX | P3: LOCAL_SELECTOR_ONLY | Q3: M02_REGISTRY
A4: M03 | B4: Scientific & Technology Intelligence | C4: M03_SCI_TECH | D4: SEHR_HOCH | E4: NO | F4: QUARTERLY | G4: 12 | H4: 6 | I4: 3 | J4: 60 | K4: 12 | L4: SCOPE_MATCH;PROJECT_MATCH;PRIORITY;STABLE_ID | M4: Publikation / Technologieentwicklung | N4: Budget = Planungsannahme. Erst lokal filtern; Quellen nicht vollstaendig in Agentenprompt laden. Unabhaengige Discovery bleibt. Kein Persistenz-/Live-Connector-Test. | O4: POPULATED_REFERENCE_INDEX | P4: LOCAL_SELECTOR_ONLY | Q4: M03_LITERATURE
A5: M04 | B5: Regulatory Intelligence | C5: M04_REGULATORY | D5: SEHR_HOCH | E5: NO | F5: QUARTERLY | G5: 10 | H5: 5 | I5: 2 | J5: 60 | K5: 12 | L5: SCOPE_MATCH;PROJECT_MATCH;PRIORITY;STABLE_ID | M5: Regulatorisches Dokument / Änderung | N5: Budget = Planungsannahme. Erst lokal filtern; Quellen nicht vollstaendig in Agentenprompt laden. Unabhaengige Discovery bleibt. Kein Persistenz-/Live-Connector-Test. | O5: POPULATED_REFERENCE_INDEX | P5: LOCAL_SELECTOR_ONLY | Q5: M04_GUIDANCE
A6: M05 | B6: Funding Opportunities | C6: M05_FUNDING | D6: SEHR_HOCH | E6: YES | F6: WEEKLY | G6: 18 | H6: 12 | I6: 2 | J6: 7 | K6: 12 | L6: SCOPE_MATCH;PROJECT_MATCH;PRIORITY;STABLE_ID | M6: Call / Förderchance | N6: Budget = Planungsannahme. Erst lokal filtern; Quellen nicht vollstaendig in Agentenprompt laden. Unabhaengige Discovery bleibt. Kein Persistenz-/Live-Connector-Test. | O6: POPULATED_REFERENCE_INDEX | P6: LOCAL_SELECTOR_ONLY | Q6: M05_SOURCE
A7: M06 | B7: BD & Partnering Intelligence | C7: M06_BD_PARTNERS | D7: SEHR_HOCH | E7: YES | F7: QUARTERLY | G7: 15 | H7: 8 | I7: 2 | J7: 45 | K7: 12 | L7: SCOPE_MATCH;PROJECT_MATCH;PRIORITY;STABLE_ID | M7: Partnerkandidat / Strategisches Signal | N7: Equity only with explicit company/spinout financing strategy; licensing, co-development and nonprofit R&D assessed separately. | O7: POPULATED_REFERENCE_INDEX | P7: LOCAL_SELECTOR_ONLY | Q7: M06_ENTITY
A8: M07 | B8: Deal & Investment Intelligence | C8: M07_DEALS | D8: HOCH | E8: NO | F8: MONTHLY | G8: 10 | H8: 5 | I8: 2 | J8: 30 | K8: 12 | L8: SCOPE_MATCH;PROJECT_MATCH;PRIORITY;STABLE_ID | M8: Transaktion / Finanzierung | N8: Optional watches only. Activation requires validated deal-event results schema and explicit approval; master contains NO transactions. | O8: POPULATED_REFERENCE_INDEX | P8: RESERVED_DEAL_EVENT_STORE_NOT_VALIDATED | Q8: M07_ENTITY
A9: M08 | B9: Conference & Event Intelligence | C9: M08_EVENTS | D9: HOCH | E9: NO | F9: MONTHLY | G9: 10 | H9: 5 | I9: 2 | J9: 30 | K9: 12 | L9: SCOPE_MATCH;PROJECT_MATCH;PRIORITY;STABLE_ID | M9: Event-Ausgabe / Deadline | N9: Budget = Planungsannahme. Erst lokal filtern; Quellen nicht vollstaendig in Agentenprompt laden. Unabhaengige Discovery bleibt. Kein Persistenz-/Live-Connector-Test. | O9: POPULATED_REFERENCE_INDEX | P9: LOCAL_SELECTOR_ONLY | Q9: M08_EVENT
A10: M09 | B10: Clinical & Medical Landscape | C10: M09_MEDICAL | D10: HOCH | E10: NO | F10: QUARTERLY | G10: 10 | H10: 5 | I10: 2 | J10: 90 | K10: 12 | L10: SCOPE_MATCH;PROJECT_MATCH;PRIORITY;STABLE_ID | M10: Leitlinien-/SoC-Update | N10: Budget = Planungsannahme. Erst lokal filtern; Quellen nicht vollstaendig in Agentenprompt laden. Unabhaengige Discovery bleibt. Kein Persistenz-/Live-Connector-Test. | O10: POPULATED_REFERENCE_INDEX | P10: LOCAL_SELECTOR_ONLY | Q10: M09_MEDICAL
A11: M10 | B11: IP & Patent Intelligence | C11: M10_IP_PATENT | D11: MITTEL_HOCH | E11: NO | F11: QUARTERLY | G11: 10 | H11: 4 | I11: 2 | J11: 90 | K11: 12 | L11: SCOPE_MATCH;PROJECT_MATCH;PRIORITY;STABLE_ID | M11: Patentfamilie / neue Anmeldung | N11: Budget = Planungsannahme. Erst lokal filtern; Quellen nicht vollstaendig in Agentenprompt laden. Unabhaengige Discovery bleibt. Kein Persistenz-/Live-Connector-Test. | O11: POPULATED_REFERENCE_INDEX | P11: LOCAL_SELECTOR_ONLY | Q11: M10_PATENT
A12: M11 | B12: CMC & Manufacturing Intelligence | C12: M11_CMC | D12: MITTEL | E12: NO | F12: QUARTERLY | G12: 10 | H12: 4 | I12: 2 | J12: 120 | K12: 12 | L12: SCOPE_MATCH;PROJECT_MATCH;PRIORITY;STABLE_ID | M12: CMC-Standard / Technologie / Lieferant | N12: Budget = Planungsannahme. Erst lokal filtern; Quellen nicht vollstaendig in Agentenprompt laden. Unabhaengige Discovery bleibt. Kein Persistenz-/Live-Connector-Test. | O12: POPULATED_REFERENCE_INDEX | P12: LOCAL_SELECTOR_ONLY | Q12: M11_CMC
A13: M12 | B13: Policy, Market & Access Intelligence | C13: M12_POLICY_ACCESS | D13: MITTEL | E13: NO | F13: QUARTERLY | G13: 10 | H13: 4 | I13: 2 | J13: 90 | K13: 12 | L13: SCOPE_MATCH;PROJECT_MATCH;PRIORITY;STABLE_ID | M13: Policy-/Access-Entwicklung | N13: Budget = Planungsannahme. Erst lokal filtern; Quellen nicht vollstaendig in Agentenprompt laden. Unabhaengige Discovery bleibt. Kein Persistenz-/Live-Connector-Test. | O13: POPULATED_REFERENCE_INDEX | P13: LOCAL_SELECTOR_ONLY | Q13: M12_POLICY

Sheet FLAGSHIP_CHECK
A1: project_id | B1: project_name | C1: scope | D1: change | E1: official_url | F1: scenario_assumption | G1: m01_profiles_before | H1: m01_profiles_after | I1: m01_planned_live_requests | J1: important_anchors | K1: remaining_gap | L1: acceptance
A2: DZIF-FLAG-HEV | B2: HEVbnAb | C2: HEV / neutralisierender Antikoerper / akute und chronische Infektion | D2: Spezifische HEV-Indikationen ergaenzt; Hecolin als Praeventionsprodukt herabgestuft. | E2: https://www.dzif.de/de/hevbnab-breit-neutralisierende-antikoerper-gegen-das-hepatitis-e-virus | F2: Academic applicant, no equity strategy; scenario phase only for routing test, not independently verified current study status. | G2: 10 | H2: 5 | I2: 7 | J2: DIRECT_COMPETITOR_DISCOVERY_OPEN | K2: Kein direkt konkurrierendes therapeutisches HEV-mAb-Programm in dieser gezielten Recherche belegt; offene akademische/klinische Suche bleibt notwendig. | L2: LOCAL_ROUTING_OBSERVED; NOT_EXTERNAL_RECALL; LANGDOCK_NOT_RUN
A3: DZIF-FLAG-EVREA | B3: EVREA-Phage | C3: E. faecium / lebende Phagen / intestinale VRE-Dekolonisierung | D3: E_FAECIUM und Dekolonisierung ergaenzt; SNIPR001 bleibt E.-coli-Kontextalternative. | E3: https://www.dzif.de/de/evrea-phage-mit-phagen-gegen-das-darmbakterium-enterococcus-faecium | F3: Academic applicant, no equity strategy; scenario phase only for routing test, not independently verified current study status. | G3: 0 | H3: 6 | I3: 8 | J3: SNIPR Biome ApS: PLANNED | K3: Kein direkter E.-faecium-Phagenkonkurrent belegt. Andere Spezies, systemische Therapie und Dekolonisierung nicht gleichsetzen. | L3: LOCAL_ROUTING_OBSERVED; NOT_EXTERNAL_RECALL; LANGDOCK_NOT_RUN
A4: DZIF-FLAG-PANTIPA | B4: PANTIPA / UHC-D9b | C4: P. aeruginosa / anti-PcrV / HAP-VAP-Therapieszenario | D4: Spezifische Anker geschuetzt; hoechstens fuenf allgemeine Firmenprofile; akademische Discovery erhalten. | E4: https://www.dzif.de/de/pantipa-monoklonale-antikoerper-gegen-pseudomonas-aeruginosa | F4: User-supplied HAP/VAP treatment scenario; public DZIF page also discusses prophylaxis. PRECLINICAL/CMC test input, not a verified current phase. | G4: 25 | H4: 9 | I4: 11 | J4: Infex Therapeutics: PLANNED; AstraZeneca: PLANNED; Armata Pharmaceuticals: PLANNED | K4: NCFB/CF ist nicht akute HAP/VAP. Aktuelle Phase, Aktivitaet, Differenzierung und Versorgungskontext live pruefen. | L4: LOCAL_ROUTING_OBSERVED; NOT_EXTERNAL_RECALL; LANGDOCK_NOT_RUN
A5: DZIF-FLAG-H052 | B5: H052 / alpha-toxin small molecules | C5: S. aureus / alpha-Toxin-Inhibition / Small Molecule / Pneumonie | D5: AR-301 als Target-/Indikationsalternative ergaenzt; IBT-Niedersachsen als Forschungsroute. | E5: https://www.dzif.de/de/niedermolekulare-inhibitoren-des-alpha-toxins-von-staphylococcus-aureus-gegen-schwere | F5: Academic applicant, no equity strategy; scenario phase only for routing test, not independently verified current study status. | G5: 25 | H5: 6 | I5: 5 | J5: Aridis Pharmaceuticals Inc: PLANNED | K5: Aktuelle Fortfuehrung/Rechte und Studienergebnisse von AR-301 unabhaengig pruefen; anderer Wirkstofftyp. | L5: LOCAL_ROUTING_OBSERVED; NOT_EXTERNAL_RECALL; LANGDOCK_NOT_RUN
A6: DZIF-FLAG-BTZ043 | B6: BTZ-043 | C6: M. tuberculosis / DprE1 / Small Molecule / Kombinationstherapie | D6: Otsuka mit offizieller Pipeline und Quabodepistat-Anker nachqualifiziert. | E6: https://www.dzif.de/de/neuer-wirkstoff-btz-043-gegen-tuberkulose | F6: Academic applicant, no equity strategy; scenario phase only for routing test, not independently verified current study status. | G6: 20 | H6: 7 | I6: 9 | J6: Otsuka Pharmaceutical Co Ltd: PLANNED; TB Alliance: PLANNED | K6: Kombinationsregime und aktuelle Studienaktivitaet nicht im Master gepflegt. Weitere DprE1-/Regimenprogramme live recherchieren. | L6: LOCAL_ROUTING_OBSERVED; NOT_EXTERNAL_RECALL; LANGDOCK_NOT_RUN
A7: DZIF-FLAG-HY133 | B7: HY-133 | C7: S. aureus / Endolysin-Protein / nasale Dekolonisierung | D7: ENDOLYSIN getrennt von PHAGE; HYpharm/HY-133 im eigenen Projekt nicht als Konkurrenz. | E7: https://www.dzif.de/de/neuer-wirkstoff-gegen-krankenhauskeim | F7: Academic applicant, no equity strategy; scenario phase only for routing test, not independently verified current study status. | G7: 25 | H7: 5 | I7: 5 | J7: DIRECT_COMPETITOR_DISCOVERY_OPEN | K7: Direkte nasale Dekolonisierungsalternativen und Standard of Care fehlen als vollstaendig qualifizierte Asset-Liste; gezielte offene Suche. | L7: LOCAL_ROUTING_OBSERVED; NOT_EXTERNAL_RECALL; LANGDOCK_NOT_RUN
A8: DZIF-FLAG-CORA | B8: Corallopyronin A | C8: Filarienindikation / Wolbachia-Symbiont / Corallopyronin A | D8: Filarien und Wolbachia getrennt; DNDi/Emodepsid als klinisch anderer Ansatz. | E8: https://www.dzif.de/de/corallopyronin-neues-antibiotikum-gegen-wurminfektionen | F8: Academic applicant, no equity strategy; scenario phase only for routing test, not independently verified current study status. | G8: 0 | H8: 6 | I8: 5 | J8: Drugs for Neglected Diseases initiative: PLANNED | K8: DNDi hat zugleich Partner- und alternative Asset-Rollen. Weitere antifilariale Programme und Phase live verifizieren. | L8: LOCAL_ROUTING_OBSERVED; NOT_EXTERNAL_RECALL; LANGDOCK_NOT_RUN
A9: DZIF-FLAG-MERS | B9: MVA-MERS-S | C9: MERS-CoV / MVA-Vektorimpfstoff / Praevention | D9: Oxford/ChAdOx1-MERS aus vorhandener Reserve mit stabiler ID uebernommen. | E9: https://www.dzif.de/de/entwicklung-eines-mers-impfstoffes | F9: Academic applicant, no equity strategy; scenario phase only for routing test, not independently verified current study status. | G9: 10 | H9: 6 | I9: 8 | J9: University of Oxford: PLANNED | K9: Oxford-Ankuendigung belegt historischen Programmscope, nicht aktuelle Aktivitaet oder heutige Lizenzrechte. | L9: LOCAL_ROUTING_OBSERVED; NOT_EXTERNAL_RECALL; LANGDOCK_NOT_RUN
A10: DZIF-FLAG-EBV | B10: EBV vaccine / VLP | C10: EBV / VLP-Impfstoff / Praevention der Mononukleose | D10: Moderna/mRNA-1189-Praeventionsanker; EBV-PTLD-Zelltherapie nicht als direkte Impfkonkurrenz. | E10: https://www.dzif.de/de/ein-impfstoff-gegen-das-epstein-barr-virus | F10: Academic applicant, no equity strategy; scenario phase only for routing test, not independently verified current study status. | G10: 11 | H10: 6 | I10: 8 | J10: Moderna: PLANNED | K10: EBViously-Projektrolle und aktuelle Kandidaten/Studien live klaeren; Impfziel von PTLD-Therapie trennen. | L10: LOCAL_ROUTING_OBSERVED; NOT_EXTERNAL_RECALL; LANGDOCK_NOT_RUN
A11: DZIF-FLAG-THERVACB | B11: TherVacB | C11: HBV / therapeutische Impfung / chronische Infektion | D11: THERAPEUTIC_VACCINE separat; BRII-179-Anker statt generischer Praeventionsprofile. | E11: https://www.dzif.de/de/thervacb-eine-therapeutische-impfung-gegen-hepatitis-b | F11: Academic applicant, no equity strategy; scenario phase only for routing test, not independently verified current study status. | G11: 10 | H11: 8 | I11: 10 | J11: Brii Biosciences Ltd: PLANNED | K11: Aktuelle Kombinationen, Rekrutierung und Impfregime gehoeren in die Ergebnisdatenbank; Uebersichtsseite enthaelt alte Zeitangaben. | L11: LOCAL_ROUTING_OBSERVED; NOT_EXTERNAL_RECALL; LANGDOCK_NOT_RUN
A12: DZIF-FLAG-HEPCLUDEX | B12: Hepcludex / bulevirtide | C12: HDV / Bulevirtid-Peptid / zugelassenes Translationsbeispiel | D12: Eigenes Bulevirtid ausgeschlossen, Vir/Assembly als Alternativen erhalten; kein Fruehphasen-Funding-Test. | E12: https://www.dzif.de/de/hepcludex-erstes-medikament-fuer-hepatitis-d-zugelassen | F12: Approved reference; industry/non-equity scenario for M01/M06 only. No fresh clinical-stage inference from overview. | G12: 10 | H12: 7 | I12: 9 | J12: Vir Biotechnology Inc: PLANNED; Assembly Biosciences: PLANNED | K12: Zugelassener Referenzfall, kein neues fruehes Entwicklungsprojekt. Aktuelle HDV-Alternativen und Access-Fragen bleiben live. | L12: LOCAL_ROUTING_OBSERVED; NOT_EXTERNAL_RECALL; LANGDOCK_NOT_RUN

Sheet EFFICIENCY_REVIEW
A1: review_id | B1: area | C1: decision | D1: action | E1: remaining_validation | F1: status
A2: EFF-01 | B2: PURPOSE | C2: KEEP | D2: Master als kuratiertes Such- und Routingverzeichnis. Keine aktuellen Phasen, Calls oder Deals als Stammdaten. | E2: Live-Befunde separat versionieren. | F2: CLOSED_STRUCTURE
A3: EFF-02 | B3: WORKBOOK | C3: SIMPLIFY | D3: 49 Blaetter zuvor; 18 historische, doppelte oder Reserveblaetter ins Auditarchiv; zwei konzentrierte Pruefuebersichten neu. | E3: Operative Module/IDs/Provenance erhalten. | F3: CLOSED_STRUCTURE
A4: EFF-03 | B4: FIELDS | C4: ARCHIVE | D4: Drei ungenutzte HQ-Felder, leeres MATCH_RULES.rule_id und zwei ungenutzte Seed-Schalter entfernt. | E4: HQ ist kein Nachweis der Antragsregion. Archive erhaelt Werte. | F4: CLOSED_STRUCTURE
A5: EFF-04 | B5: DISCOVERY_ROWS | C5: EXCLUDE_FROM_RUNTIME | D5: 141 M01-Discovery-Profile und ein M05-Discovery-Eintrag bleiben in Excel, nicht im Standard-JSON. | E5: Promote nur nach Quellenpruefung. Unabhaengige Discovery bleibt. | F5: CLOSED_STRUCTURE
A6: EFF-05 | B6: RUNTIME_GRAPH | C6: PRUNE_EXPORT | D6: Runtime enthaelt nur referenzierte Organisationen und Quellen, inkl. Parent-/Canonical-Abhaengigkeiten. | E6: Vollstaendige Registry bleibt in Excel. | F6: CLOSED_STRUCTURE
A7: EFF-06 | B7: BLANK_FIELDS | C7: DISTINGUISH | D7: Alle notwendigen IDs, Verknuepfungen, Prioritaeten und Statusfelder geprueft. Optionale Beziehungen/API-Felder duerfen leer sein. | E7: UNKNOWN bedeutet unbekannt, nicht nicht vorhanden; keine erfundenen Details. | F7: PARTIAL_CONTENT
A8: EFF-07 | B8: FUNDING_GEO | C8: KEEP_AND_FIX | D8: Regionale Auswahl fuer alle 16 Bundeslaender erhalten; EU-Erweiterung von vier auf alle 27 Laendercodes korrigiert. | E8: Region ist Suchscope, keine rechtsverbindliche Foerderfaehigkeit. | F8: CLOSED_ROUTING
A9: EFF-08 | B9: FUNDING_IBT | C9: ADD_TARGETED | D9: IBT Lower Saxony als eine zusaetzliche Forschungs-Translationsroute ergaenzt. | E9: Unterprogramme, Standort, IP/Spinout-Anforderungen und offene Frist live pruefen. | F9: SCOPE_ONLY
A10: EFF-09 | B10: OWN_ASSETS | C10: FIX | D10: Eigene Asset-IDs werden vom Konkurrenzranking getrennt, andere Programme derselben Organisation bleiben moeglich. | E10: Intake muss own_asset_ids liefern; keine automatische Kenntnis privater Projektrollen. | F10: CLOSED_ROUTING
A11: EFF-10 | B11: CLINICAL_PURPOSE | C11: FIX | D11: Praevention, Therapie, Dekolonisierung und Diagnostik getrennt; Endolysine sind keine lebenden Phagen. | E11: Andere Modalitaeten im gleichen klinischen Kontext bleiben beruecksichtigt. | F11: CLOSED_ROUTING
A12: EFF-11 | B12: GENERAL_BREADTH | C12: LIMIT | D12: Maximal fuenf allgemeine M01-Firmenprofile pro Lauf; spezifische Asset-Anker und Must-Watches nicht davon betroffen. | E12: Zurueckstellungen als Coverage Gaps; kein Recall-Nachweis oder Kostenversprechen. | F12: PILOT_POLICY
... A17: EFF-16 | B17: TESTS | C17: SEPARATE | D17: 109 ausgefuehrte technische Checks sowie 11 reale und 13 kontrastierende Projektprofile getrennt dokumentiert. | E17: Tests = lokal; fachliche Vollstaendigkeit und Langdock End-to-End offen. | F17: LOCAL_ONLY

Sheet M01_COMPETITORS
A1: record_id | B1: entity_id | C1: entity_name | D1: record_type | E1: topic_tags | F1: pathogen_tags | G1: indication_tags | H1: modality_tags | I1: search_terms | J1: source_id | K1: base_priority | L1: status | M1: evidence_scope | N1: provenance_id | O1: cautions | P1: source_url | Q1: watch_policy
A2: M01-CMP-02e13c78d23 | B2: CMP-02e13c78d23 | C2: =IFERROR(VLOOKUP(B2,ENTITY_MASTER!$A$2:$B$266,2,FALSE),"") -> Hypharm | D2: COMPANY_WATCH | E2: HAI;ANTIBACTERIAL;AMR | F2: S_AUREUS | G2: NASAL_DECOLONIZATION | H2: ENDOLYSIN;PROTEIN | I2: Hypharm;HY-133;HY133;HYpharm;endolysin;nasal decolonization | J2: SRC-V23-HYPHARM | K2: P1 | L2: ACTIVE | M2: INDEX_PLUS_SOURCE_SCOPE | N2: PR-RAD-CMP-02e13c78d23 | O2: Specific programme scope is in MATCH_ANCHORS; no verified current phase or blanket competitor role. Own-project context supplied by intake. | P2: =IFERROR(IF(VLOOKUP(J2,SOURCE_REGISTRY!$A$2:$E$246,5,FALSE)="","",VLOOKUP(J2,SOURCE_REGISTRY!$A$2:$E$246,5,FALSE)),"") -> https://hypharm.de/phagenlysin-wirkstoff-hy-133-start-der-klinischen-phase-i-first-in-human-studie-zur-eliminierung-von-staphylococcus-aureus-im-nasenmikrobiom/ | Q2: CONDITIONAL
A3: M01-CMP-0c4fb4ab435 | B3: CMP-0c4fb4ab435 | C3: =IFERROR(VLOOKUP(B3,ENTITY_MASTER!$A$2:$B$266,2,FALSE),"") -> AiCuris Anti-infective Cures AG | D3: ENTITY_WATCH | E3: VIRAL;HSV;IMMUNOCOMPROMISED | F3: HSV;BK_POLYOMAVIRUS | G3: HSV_INFECTION | H3: SMALL_MOLECULE;RNA | I3: AiCuris Anti-infective Cures AG | J3: SRC-V2-AICURIS | K3: P1 | L3: ACTIVE | M3: SOURCE_BACKED_SCOPE_NOT_CURRENT_ASSET_STATUS | N3: PR-V2-M01-CMP-0c4fb4ab435 | O3: Projektfit pruefen; nicht automatisch direkter Wettbewerber. | P3: =IFERROR(IF(VLOOKUP(J3,SOURCE_REGISTRY!$A$2:$E$246,5,FALSE)="","",VLOOKUP(J3,SOURCE_REGISTRY!$A$2:$E$246,5,FALSE)),"") -> https://www.aicuris.com/pipeline-products/ | Q3: CONDITIONAL
A4: M01-CMP-0fd9a9b02c5 | B4: CMP-0fd9a9b02c5 | C4: =IFERROR(VLOOKUP(B4,ENTITY_MASTER!$A$2:$B$266,2,FALSE),"") -> Seres Therapeutics Inc | D4: COMPANY_WATCH | E4: HAI;ANTIBACTERIAL;MUCOSAL_INFECTIONS;IMMUNOCOMPROMISED | F4: UNKNOWN | G4: UNKNOWN | H4: MICROBIOME | I4: Seres Therapeutics Inc | J4: SRC-RAD-6f35534e04 | K4: P1 | L4: ACTIVE | M4: GD_SNAPSHOT_PROXY | N4: PR-RAD-CMP-0fd9a9b02c5 | O4: Themen/Modalitaeten sind Suchhinweise. Aktive Assets, Phase, Indikation und Konkurrenzstatus immer live verifizieren. | P4: =IFERROR(IF(VLOOKUP(J4,SOURCE_REGISTRY!$A$2:$E$246,5,FALSE)="","",VLOOKUP(J4,SOURCE_REGISTRY!$A$2:$E$246,5,FALSE)),"") -> https://www.serestherapeutics.com/our-programs/ | Q4: CONDITIONAL
A5: M01-CMP-13b02aead78 | B5: CMP-13b02aead78 | C5: =IFERROR(VLOOKUP(B5,ENTITY_MASTER!$A$2:$B$266,2,FALSE),"") -> Profionics | D5: COMPANY_WATCH | E5: HAI | F5: UNKNOWN | G5: UNKNOWN | H5: DIAGNOSTIC | I5: Profionics | J5: SRC-RAD-dd4d6ddb44 | K5: P1 | L5: ACTIVE | M5: CURATED_SOURCE_ASSOCIATION | N5: PR-RAD-CMP-13b02aead78 | O5: Themen/Modalitaeten sind Suchhinweise. Aktive Assets, Phase, Indikation und Konkurrenzstatus immer live verifizieren. GD-Nullwerte bedeuten fehlende Abdeckung, nicht Nullportfolio. | P5: =IFERROR(IF(VLOOKUP(J5,SOURCE_REGISTRY!$A$2:$E$246,5,FALSE)="","",VLOOKUP(J5,SOURCE_REGISTRY!$A$2:$E$246,5,FALSE)),"") -> https://beam-alliance.eu/members/ | Q5: CONDITIONAL
A6: M01-CMP-1a319a119c8 | B6: CMP-1a319a119c8 | C6: =IFERROR(VLOOKUP(B6,ENTITY_MASTER!$A$2:$B$266,2,FALSE),"") -> Arcturus Therapeutics | D6: COMPANY_WATCH | E6: VIRAL;VACCINE;PANDEMIC;RESPIRATORY | F6: UNKNOWN | G6: UNKNOWN | H6: RNA;VACCINE;PLATFORM | I6: Arcturus Therapeutics | J6: SRC-BD-033 | K6: P1 | L6: ACTIVE | M6: BD_DERIVED_SEARCH_HINT | N6: PR-BD-033 | O6: Ergaenzung aus BD-Katalog; kein Nachweis eines aktuellen konkurrierenden Assets. Primaere Pipeline separat pruefen. | P6: =IFERROR(IF(VLOOKUP(J6,SOURCE_REGISTRY!$A$2:$E$246,5,FALSE)="","",VLOOKUP(J6,SOURCE_REGISTRY!$A$2:$E$246,5,FALSE)),"") -> https://ir.arcturusrx.com/news-releases/news-release-details/arcturus-therapeutics-announces-second-quarter-2026-financial | Q6: CONDITIONAL
A7: M01-CMP-1c39dd558a2 | B7: CMP-1c39dd558a2 | C7: =IFERROR(VLOOKUP(B7,ENTITY_MASTER!$A$2:$B$266,2,FALSE),"") -> Ferring Pharmaceuticals | D7: COMPANY_WATCH | E7: HAI;IMMUNOCOMPROMISED;MICROBIOME | F7: C_DIFFICILE | G7: RECURRENT_CDI | H7: MICROBIOME | I7: Ferring;Rebyota;microbiome | J7: SRC-FERRING | K7: P1 | L7: ACTIVE | M7: SOURCE_BACKED_SCOPE_NOT_CURRENT_ASSET_STATUS | N7: PR-RAD-CMP-1c39dd558a2 | O7: GD active=0 war fehlende GD-Abdeckung; nicht als leere Pipeline verwenden. | P7: =IFERROR(IF(VLOOKUP(J7,SOURCE_REGISTRY!$A$2:$E$246,5,FALSE)="","",VLOOKUP(J7,SOURCE_REGISTRY!$A$2:$E$246,5,FALSE)),"") -> https://www.ferring.com/science-innovation/research-and-development/product-pipeline/ | Q7: CONDITIONAL
A8: M01-CMP-1dc25b959ce | B8: CMP-1dc25b959ce | C8: =IFERROR(VLOOKUP(B8,ENTITY_MASTER!$A$2:$B$266,2,FALSE),"") -> BioNTech | D8: COMPANY_WATCH | E8: HIV;ANTIBACTERIAL;EMERGING_INFECTIONS;TUBERCULOSIS;NTD;MUCOSAL_INFECTIONS | F8: UNKNOWN | G8: UNKNOWN | H8: VACCINE | I8: BioNTech;BioNTech SE | J8: SRC-BD-011 | K8: P1 | L8: ACTIVE | M8: GD_SNAPSHOT_PROXY | N8: PR-RAD-CMP-1dc25b959ce | O8: Themen/Modalitaeten sind Suchhinweise. Aktive Assets, Phase, Indikation und Konkurrenzstatus immer live verifizieren. | P8: =IFERROR(IF(VLOOKUP(J8,SOURCE_REGISTRY!$A$2:$E$246,5,FALSE)="","",VLOOKUP(J8,SOURCE_REGISTRY!$A$2:$E$246,5,FALSE)),"") -> https://www.biontech.com/us/en/home/research-and-innovation/therapeutic-areas/infectious-diseases.html | Q8: CONDITIONAL
A9: M01-CMP-24531a6b01f | B9: CMP-24531a6b01f | C9: =IFERROR(VLOOKUP(B9,ENTITY_MASTER!$A$2:$B$266,2,FALSE),"") -> Moderna | D9: COMPANY_WATCH | E9: HIV;EMERGING_INFECTIONS;MUCOSAL_INFECTIONS;IMMUNOCOMPROMISED;VIRAL;VACCINE | F9: EBV | G9: INFECTIOUS_MONONUCLEOSIS | H9: VACCINE;MRNA_VACCINE | I9: Moderna;Moderna Inc;mRNA-1189;Epstein-Barr vaccine | J9: SRC-BD-012 | K9: P1 | L9: ACTIVE | M9: INDEX_PLUS_SOURCE_SCOPE | N9: PR-RAD-CMP-24531a6b01f | O9: Specific programme scope is in MATCH_ANCHORS; no verified current phase or blanket competitor role. Own-project context supplied by intake. | P9: =IFERROR(IF(VLOOKUP(J9,SOURCE_REGISTRY!$A$2:$E$246,5,FALSE)="","",VLOOKUP(J9,SOURCE_REGISTRY!$A$2:$E$246,5,FALSE)),"") -> https://www.modernatx.com/research/product-pipeline | Q9: CONDITIONAL
A10: M01-CMP-272f19fd220 | B10: CMP-272f19fd220 | C10: =IFERROR(VLOOKUP(B10,ENTITY_MASTER!$A$2:$B$266,2,FALSE),"") -> Serum Institute of India | D10: COMPANY_WATCH | E10: ANTIBACTERIAL;EMERGING_INFECTIONS;TUBERCULOSIS;NTD | F10: UNKNOWN | G10: UNKNOWN | H10: VACCINE;ANTIBODY | I10: Serum Institute of India;Serum Institute of India Pvt Ltd;SII | J10: SRC-BD-018 | K10: P1 | L10: ACTIVE | M10: GD_SNAPSHOT_PROXY | N10: PR-RAD-CMP-272f19fd220 | O10: Themen/Modalitaeten sind Suchhinweise. Aktive Assets, Phase, Indikation und Konkurrenzstatus immer live verifizieren. | P10: =IFERROR(IF(VLOOKUP(J10,SOURCE_REGISTRY!$A$2:$E$246,5,FALSE)="","",VLOOKUP(J10,SOURCE_REGISTRY!$A$2:$E$246,5,FALSE)),"") -> https://www.seruminstitute.com/gates-medical-research-institute-and-the-serum-institute-of-india-reach-agreement.php | Q10: CONDITIONAL
A11: M01-CMP-2e66edddf5d | B11: CMP-2e66edddf5d | C11: =IFERROR(VLOOKUP(B11,ENTITY_MASTER!$A$2:$B$266,2,FALSE),"") -> Vedanta Biosciences Inc | D11: COMPANY_WATCH | E11: HAI;ANTIBACTERIAL;IMMUNOCOMPROMISED | F11: UNKNOWN | G11: UNKNOWN | H11: MICROBIOME | I11: Vedanta Biosciences Inc | J11: SRC-RAD-d19726318a | K11: P1 | L11: ACTIVE | M11: GD_SNAPSHOT_PROXY | N11: PR-RAD-CMP-2e66edddf5d | O11: Themen/Modalitaeten sind Suchhinweise. Aktive Assets, Phase, Indikation und Konkurrenzstatus immer live verifizieren. | P11: =IFERROR(IF(VLOOKUP(J11,SOURCE_REGISTRY!$A$2:$E$246,5,FALSE)="","",VLOOKUP(J11,SOURCE_REGISTRY!$A$2:$E$246,5,FALSE)),"") -> https://www.vedantabio.com/pipeline-programs/pipeline/ | Q11: CONDITIONAL
A12: M01-CMP-3150ecd5e02 | B12: CMP-3150ecd5e02 | C12: =IFERROR(VLOOKUP(B12,ENTITY_MASTER!$A$2:$B$266,2,FALSE),"") -> PATH | D12: ENTITY_WATCH | E12: VACCINE;MALARIA;GLOBAL_HEALTH | F12: ANY | G12: ANY | H12: VACCINE;ANTIBODY;DIAGNOSTIC | I12: PATH | J12: SRC-V2-PATH | K12: P1 | L12: ACTIVE | M12: PUBLIC_SCOPE_NOT_LIVE_ASSET | N12: PR-V2-M01-CMP-3150ecd5e02 | O12: Projektfit pruefen; nicht automatisch direkter Wettbewerber. | P12: =IFERROR(IF(VLOOKUP(J12,SOURCE_REGISTRY!$A$2:$E$246,5,FALSE)="","",VLOOKUP(J12,SOURCE_REGISTRY!$A$2:$E$246,5,FALSE)),"") -> https://www.path.org/who-we-are/programs/center-for-vaccine-innovation-and-access/ | Q12: CONDITIONAL
A13: M01-CMP-335ff7e594c | B13: CMP-335ff7e594c | C13: =IFERROR(VLOOKUP(B13,ENTITY_MASTER!$A$2:$B$266,2,FALSE),"") -> Pfizer | D13: COMPANY_WATCH | E13: HAI;ANTIBACTERIAL;EMERGING_INFECTIONS;MUCOSAL_INFECTIONS | F13: UNKNOWN | G13: UNKNOWN | H13: VACCINE | I13: Pfizer;infectious diseases;vaccines | J13: SRC-PFIZER-PIPE | K13: P1 | L13: ACTIVE | M13: INDEX_PLUS_SOURCE_SCOPE | N13: PR-RAD-CMP-335ff7e594c | O13: Keine konkrete Konkurrenzklassifikation oder aktuelle Phase ableiten; andere Modalitaeten nicht pauschal ausschliessen. | P13: =IFERROR(IF(VLOOKUP(J13,SOURCE_REGISTRY!$A$2:$E$246,5,FALSE)="","",VLOOKUP(J13,SOURCE_REGISTRY!$A$2:$E$246,5,FALSE)),"") -> https://www.pfizer.com/science/drug-product-pipeline | Q13: CONDITIONAL
... A245: M01-CMP-fce0f58579d | B245: CMP-fce0f58579d | C245: =IFERROR(VLOOKUP(B245,ENTITY_MASTER!$A$2:$B$266,2,FALSE),"") -> Immorna Hangzhou Biotechnology Co Ltd | D245: COMPANY_WATCH | E245: EMERGING_INFECTIONS;MUCOSAL_INFECTIONS;IMMUNOCOMPROMISED | F245: UNKNOWN | G245: UNKNOWN | H245: UNKNOWN | I245: Immorna Hangzhou Biotechnology Co Ltd | J245: SRC-NAME-SEARCH | K245: P2 | L245: ACTIVE | M245: DISCOVERY_CANDIDATE_UNVERIFIED | N245: PR-RAD-CMP-fce0f58579d | O245: Themen/Modalitaeten sind Suchhinweise. Aktive Assets, Phase, Indikation und Konkurrenzstatus immer live verifizieren. Kein bestaetigter Primaer-URL im Input; Namenssuche vorgesehen. | P245: =IFERROR(IF(VLOOKUP(J245,SOURCE_REGISTRY!$A$2:$E$246,5,FALSE)="","",VLOOKUP(J245,SOURCE_REGISTRY!$A$2:$E$246,5,FALSE)),"") | Q245: DISCOVERY

Sheet M02_CLINICAL
A1: record_id | B1: record_name | C1: record_type | D1: scope_note | E1: topic_tags | F1: pathogen_tags | G1: modality_tags | H1: jurisdiction_tags | I1: query_class | J1: source_id | K1: base_priority | L1: watch_policy | M1: status | N1: catalog_review_on | O1: source_url | P1: cautions
A2: M02-CTG | B2: ClinicalTrials.gov API | C2: SOURCE_WATCH | D2: REGISTRY_API_DOCS | E2: ANY | F2: ANY | G2: ANY | H2: GLOBAL | I2: M02_REGISTRY | J2: SRC-V2-CTG | K2: P1 | L2: CORE | M2: ACTIVE | N2: 2026-10-29 | O2: =IFERROR(IF(VLOOKUP(J2,SOURCE_REGISTRY!$A$2:$E$246,5,FALSE)="","",VLOOKUP(J2,SOURCE_REGISTRY!$A$2:$E$246,5,FALSE)),"") -> https://clinicaltrials.gov/data-api/api | P2: Registerroute; API und Pagination im Langdock-Workspace noch nicht getestet.
A3: M02-CTIS | B3: EMA CTIS public information | C3: SOURCE_WATCH | D3: EU_REGISTRY_ROUTE | E3: ANY | F3: ANY | G3: ANY | H3: EU | I3: M02_REGISTRY | J3: SRC-V2-CTIS | K3: P1 | L3: CORE | M3: ACTIVE | N3: 2026-10-29 | O3: =IFERROR(IF(VLOOKUP(J3,SOURCE_REGISTRY!$A$2:$E$246,5,FALSE)="","",VLOOKUP(J3,SOURCE_REGISTRY!$A$2:$E$246,5,FALSE)),"") -> https://euclinicaltrials.eu/ | P3: EU/EEA-Studien. Oeffentliches Portal ueber offizielle EMA-Seite aufrufen; keine freie API unterstellen.
A4: M02-ICTRP | B4: WHO ICTRP | C4: SOURCE_WATCH | D4: GLOBAL_REGISTRY_AGGREGATOR | E4: ANY | F4: ANY | G4: ANY | H4: GLOBAL | I4: M02_REGISTRY | J4: SRC-V2-ICTRP | K4: P1 | L4: CORE | M4: ACTIVE | N4: 2026-10-29 | O4: =IFERROR(IF(VLOOKUP(J4,SOURCE_REGISTRY!$A$2:$E$246,5,FALSE)="","",VLOOKUP(J4,SOURCE_REGISTRY!$A$2:$E$246,5,FALSE)),"") -> https://trialsearch.who.int/ | P4: Internationaler Aggregator; Dubletten ueber Register-IDs zusammenfuehren; Zugriffsbedingungen beachten.
A5: M02-V21-DRKS | B5: DRKS | C5: SOURCE_ANCHOR | D5: Register search; study ID and secondary IDs available. Search execution and pagination not tested in Langdock. | E5: ANY | F5: ANY | G5: ANY | H5: ANY | I5: M02_REGISTRY | J5: SRC-V21-DRKS | K5: P0 | L5: CONDITIONAL | M5: ACTIVE | N5: 2026-10-29 | O5: =IFERROR(IF(VLOOKUP(J5,SOURCE_REGISTRY!$A$2:$E$246,5,FALSE)="","",VLOOKUP(J5,SOURCE_REGISTRY!$A$2:$E$246,5,FALSE)),"") -> https://drks.de/search/de | P5: Reference source only. No module activation and no live evidence implied.
A6: M02-V21-DZIF_CTU | B6: DZIF CTU register entry | C6: SOURCE_ANCHOR | D6: Public entry page only. Full use/downloads may require DZIF SSO; do not infer public bulk access. | E6: ANY | F6: ANY | G6: ANY | H6: ANY | I6: M02_REGISTRY | J6: SRC-V21-DZIF_CTU | K6: P1 | L6: CONDITIONAL | M6: ACTIVE | N6: 2026-10-29 | O6: =IFERROR(IF(VLOOKUP(J6,SOURCE_REGISTRY!$A$2:$E$246,5,FALSE)="","",VLOOKUP(J6,SOURCE_REGISTRY!$A$2:$E$246,5,FALSE)),"") -> https://dt-hub.dzif.de/anwendungsfaelle | P6: DZIF SSO/full-use permissions unresolved; never treat inaccessible data as no trials.

Sheet M03_SCI_TECH
A1: record_id | B1: record_name | C1: record_type | D1: scope_note | E1: topic_tags | F1: pathogen_tags | G1: modality_tags | H1: jurisdiction_tags | I1: query_class | J1: source_id | K1: base_priority | L1: watch_policy | M1: status | N1: catalog_review_on | O1: source_url | P1: cautions
A2: M03-PUBMED | B2: NCBI E-utilities | C2: SOURCE_WATCH | D2: LITERATURE_API_DOCS | E2: ANY | F2: ANY | G2: ANY | H2: GLOBAL | I2: M03_LITERATURE | J2: SRC-V2-PUBMED | K2: P1 | L2: CORE | M2: ACTIVE | N2: 2026-10-29 | O2: =IFERROR(IF(VLOOKUP(J2,SOURCE_REGISTRY!$A$2:$E$246,5,FALSE)="","",VLOOKUP(J2,SOURCE_REGISTRY!$A$2:$E$246,5,FALSE)),"") -> https://pubmed.ncbi.nlm.nih.gov/ | P2: PubMed und PMC APIs; API-Limits/Batching beachten; keine Volltextlizenz aus Metadatenzugriff ableiten.
A3: M03-EPMC | B3: Europe PMC REST API | C3: SOURCE_WATCH | D3: LITERATURE_API_DOCS | E3: ANY | F3: ANY | G3: ANY | H3: GLOBAL | I3: M03_LITERATURE | J3: SRC-V2-EPMC | K3: P1 | L3: CORE | M3: ACTIVE | N3: 2026-10-29 | O3: =IFERROR(IF(VLOOKUP(J3,SOURCE_REGISTRY!$A$2:$E$246,5,FALSE)="","",VLOOKUP(J3,SOURCE_REGISTRY!$A$2:$E$246,5,FALSE)),"") -> https://europepmc.org/RestfulWebService | P3: Produktiver REST-Dienst bei ebi.ac.uk dokumentiert; Guide-Abruf hier 403, offizielle Dev-Dokumentation gegengeprueft. Preprints gesondert markieren.
A4: M03-V21-CORDIS | B4: CORDIS academic and consortium research | C4: SOURCE_ANCHOR | D4: Academic and early-development consortium discovery; project records do not prove an active commercial pipeline. | E4: ANY | F4: ANY | G4: ANY | H4: ANY | I4: M03_LITERATURE | J4: SRC-V21-CORDIS | K4: P1 | L4: CONDITIONAL | M4: ACTIVE | N4: 2026-10-29 | O4: =IFERROR(IF(VLOOKUP(J4,SOURCE_REGISTRY!$A$2:$E$246,5,FALSE)="","",VLOOKUP(J4,SOURCE_REGISTRY!$A$2:$E$246,5,FALSE)),"") -> https://cordis.europa.eu/projects | P4: Reference source only. No module activation and no live evidence implied.

Sheet M04_REGULATORY
A1: record_id | B1: record_name | C1: record_type | D1: scope_note | E1: topic_tags | F1: pathogen_tags | G1: modality_tags | H1: jurisdiction_tags | I1: query_class | J1: source_id | K1: base_priority | L1: watch_policy | M1: status | N1: catalog_review_on | O1: source_url | P1: cautions
A2: M04-EMA_GUIDE | B2: EMA scientific guidelines | C2: SOURCE_WATCH | D2: REGULATORY_GUIDELINE_HUB | E2: ANY | F2: ANY | G2: ANY | H2: EU | I2: M04_GUIDANCE | J2: SRC-V2-EMA_GUIDE | K2: P1 | L2: CORE | M2: ACTIVE | N2: 2026-10-29 | O2: =IFERROR(IF(VLOOKUP(J2,SOURCE_REGISTRY!$A$2:$E$246,5,FALSE)="","",VLOOKUP(J2,SOURCE_REGISTRY!$A$2:$E$246,5,FALSE)),"") -> https://www.ema.europa.eu/en/human-regulatory-overview/research-development/scientific-guidelines-human-medicines | P2: Version, Draft/Final, Gueltigkeitsdatum und Produktklasse live pruefen. Keine vertraulichen Scientific-Advice-Protokolle erwarten.
A3: M04-FDA_GUIDE | B3: FDA guidance documents | C3: SOURCE_WATCH | D3: FDA_GUIDELINE_HUB | E3: ANY | F3: ANY | G3: ANY | H3: US | I3: M04_GUIDANCE | J3: SRC-V2-FDA_GUIDE | K3: P1 | L3: CORE | M3: ACTIVE | N3: 2026-10-29 | O3: =IFERROR(IF(VLOOKUP(J3,SOURCE_REGISTRY!$A$2:$E$246,5,FALSE)="","",VLOOKUP(J3,SOURCE_REGISTRY!$A$2:$E$246,5,FALSE)),"") -> https://www.fda.gov/regulatory-information/search-fda-guidance-documents | P3: Filter nach Produkttyp, Ausgabedatum und Draft/Final; Tabelleninhalt dynamisch.
A4: M04-EMA_MED | B4: EMA medicines | C4: SOURCE_WATCH | D4: AUTHORIZATION_ROUTE | E4: ANY | F4: ANY | G4: ANY | H4: EU | I4: M04_GUIDANCE | J4: SRC-V2-EMA_MED | K4: P1 | L4: CORE | M4: ACTIVE | N4: 2026-10-29 | O4: =IFERROR(IF(VLOOKUP(J4,SOURCE_REGISTRY!$A$2:$E$246,5,FALSE)="","",VLOOKUP(J4,SOURCE_REGISTRY!$A$2:$E$246,5,FALSE)),"") -> https://www.ema.europa.eu/en/medicines | P4: EPAR, oeffentliche Bewertungen und Zulassungsentscheidungen; nicht vollstaendig fuer nationale Zulassungen.
A5: M04-EMA_ATMP | B5: EMA investigational ATMP guideline | C5: SOURCE_WATCH | D5: ATMP_GUIDELINE_ROUTE | E5: ANY | F5: ANY | G5: CELL_GENE_THERAPY;CELL_THERAPY;GENE_THERAPY | H5: EU | I5: M04_GUIDANCE | J5: SRC-V2-EMA_ATMP | K5: P1 | L5: CONDITIONAL | M5: ACTIVE | N5: 2026-10-29 | O5: =IFERROR(IF(VLOOKUP(J5,SOURCE_REGISTRY!$A$2:$E$246,5,FALSE)="","",VLOOKUP(J5,SOURCE_REGISTRY!$A$2:$E$246,5,FALSE)),"") -> https://www.ema.europa.eu/en/scientific-guidelines/guideline-quality-non-clinical-clinical-requirements-investigational-advanced-therapy-medicinal-products-clinical-trials | P5: Zell-/Gentherapie; einschlaegige Version und Umsetzungsdatum pruefen.
A6: M04-FDA_CGT | B6: FDA cellular and gene therapy guidance | C6: SOURCE_WATCH | D6: CGT_GUIDELINE_ROUTE | E6: ANY | F6: ANY | G6: CELL_GENE_THERAPY;CELL_THERAPY;GENE_THERAPY | H6: US | I6: M04_GUIDANCE | J6: SRC-V2-FDA_CGT | K6: P1 | L6: CONDITIONAL | M6: ACTIVE | N6: 2026-10-29 | O6: =IFERROR(IF(VLOOKUP(J6,SOURCE_REGISTRY!$A$2:$E$246,5,FALSE)="","",VLOOKUP(J6,SOURCE_REGISTRY!$A$2:$E$246,5,FALSE)),"") -> https://www.fda.gov/vaccines-blood-biologics/biologics-guidances/cellular-gene-therapy-guidances | P6: CBER-Zell-/Gentherapie; produkt- und risikospezifische Anforderungen.
A7: M04-PEI | B7: PEI regulation | C7: SOURCE_WATCH | D7: GERMAN_BIOLOGICS_REGULATION | E7: ANY | F7: ANY | G7: VACCINE;ANTIBODY;CELL_GENE_THERAPY;CELL_THERAPY;GENE_THERAPY | H7: DE | I7: M04_GUIDANCE | J7: SRC-V2-PEI | K7: P1 | L7: CONDITIONAL | M7: ACTIVE | N7: 2026-10-29 | O7: =IFERROR(IF(VLOOKUP(J7,SOURCE_REGISTRY!$A$2:$E$246,5,FALSE)="","",VLOOKUP(J7,SOURCE_REGISTRY!$A$2:$E$246,5,FALSE)),"") -> https://www.pei.de/EN/regulation/regulation-node.html | P7: Biologics source hub, not a blanket classification for all phages/microbiome products; authority responsibility is product-specific. Access still untested in Langdock.
A8: M04-EU_IVDR | B8: EU MDR / IVDR framework | C8: SOURCE_WATCH | D8: IVD_REGULATORY_ROUTE | E8: ANY | F8: ANY | G8: DIAGNOSTIC | H8: EU | I8: M04_GUIDANCE | J8: SRC-V2-EU_IVDR | K8: P1 | L8: CONDITIONAL | M8: ACTIVE | N8: 2026-10-29 | O8: =IFERROR(IF(VLOOKUP(J8,SOURCE_REGISTRY!$A$2:$E$246,5,FALSE)="","",VLOOKUP(J8,SOURCE_REGISTRY!$A$2:$E$246,5,FALSE)),"") -> https://health.ec.europa.eu/medical-devices-new-regulations_en | P8: MDR und IVDR getrennt von Arzneimittelregulierung; Produktklassifikation und aktuelle Uebergangsregeln pruefen.
A9: M04-EMA_PHAGE | B9: EMA phage quality guideline | C9: SOURCE_WATCH | D9: PHAGE_QUALITY_GUIDELINE | E9: ANY | F9: ANY | G9: PHAGE | H9: EU | I9: M04_GUIDANCE | J9: SRC-V2-EMA_PHAGE | K9: P1 | L9: CONDITIONAL | M9: ACTIVE | N9: 2026-10-29 | O9: =IFERROR(IF(VLOOKUP(J9,SOURCE_REGISTRY!$A$2:$E$246,5,FALSE)="","",VLOOKUP(J9,SOURCE_REGISTRY!$A$2:$E$246,5,FALSE)),"") -> https://www.ema.europa.eu/en/scientific-guidelines/quality-aspects-phage-therapy-medicinal-products | P9: Offizielle Seite zeigt Draft / consultation closed; nicht als finale verbindliche Leitlinie ausgeben.
A10: M04-FDA_LBP | B10: FDA live biotherapeutic CMC guidance | C10: SOURCE_WATCH | D10: LIVE_BIOTHERAPEUTIC_CMC | E10: ANY | F10: ANY | G10: MICROBIOME | H10: US | I10: M04_GUIDANCE | J10: SRC-V2-FDA_LBP | K10: P1 | L10: CONDITIONAL | M10: ACTIVE | N10: 2026-10-29 | O10: =IFERROR(IF(VLOOKUP(J10,SOURCE_REGISTRY!$A$2:$E$246,5,FALSE)="","",VLOOKUP(J10,SOURCE_REGISTRY!$A$2:$E$246,5,FALSE)),"") -> https://www.fda.gov/regulatory-information/search-fda-guidance-documents/early-clinical-trials-live-biotherapeutic-products-chemistry-manufacturing-and-control-information | P10: FDA-Route fuer Live Biotherapeutic Products. Nicht automatisch auf Gentherapie-Vektoren anwendbar.
A11: M04-BFARM | B11: BfArM clinical trials / medicinal products | C11: SOURCE_WATCH | D11: GERMAN_MEDICINAL_PRODUCT_REGULATION | E11: ANY | F11: ANY | G11: SMALL_MOLECULE;PHAGE;ENDOLYSIN;PEPTIDE;MICROBIOME | H11: DE | I11: M04_GUIDANCE | J11: SRC-V23-BFARM | K11: P1 | L11: CONDITIONAL | M11: ACTIVE | N11: 2026-10-29 | O11: =IFERROR(IF(VLOOKUP(J11,SOURCE_REGISTRY!$A$2:$E$246,5,FALSE)="","",VLOOKUP(J11,SOURCE_REGISTRY!$A$2:$E$246,5,FALSE)),"") -> https://www.bfarm.de/DE/Arzneimittel/Klinische-Pruefung/_node.html | P11: Official source blocked here (403). Product classification and German authority responsibility require product-specific confirmation. Not an automatic PEI/BfArM determination.

Sheet M05_FUNDING
A1: record_id | B1: record_name | C1: record_type | D1: applicant_types | E1: region_scope | F1: institution_scope | G1: trigger_tags | H1: required_context_tags | I1: development_scope | J1: activity_tags | K1: routing_mode | L1: source_id | M1: base_priority | N1: status | O1: eligibility_note | P1: provenance_id | Q1: source_url | R1: parent_record_id | S1: context_match | T1: watch_policy
A2: DE_FDB | B2: Förderdatenbank Bund / Länder / EU | C2: PORTAL | D2: ANY | E2: DE | F2: ANY | G2: ANY | H2: ANY | I2: ANY | J2: ANY | K2: BASELINE | L2: SRC-DE_FDB | M2: P1 | N2: ACTIVE | O2: Bund/Laender/EU-Einstieg; keine pauschale Foerderfaehigkeit. | P2: PR-FUND-DE_FDB | Q2: =IFERROR(IF(VLOOKUP(L2,SOURCE_REGISTRY!$A$2:$E$246,5,FALSE)="","",VLOOKUP(L2,SOURCE_REGISTRY!$A$2:$E$246,5,FALSE)),"") -> https://www.foerderdatenbank.de/FDB/DE/Foerderprogramme/foerderprogramme.html | S2: ANY | T2: CORE
A3: DE_BMFTR_HEALTH | B3: BMFTR Gesundheitsforschung - Bekanntmachungen | C3: PORTAL | D3: ACADEMIA;PUBLIC_BODY;CONSORTIUM | E3: DE | F3: ANY | G3: ANY | H3: ANY | I3: ANY | J3: ANY | K3: BASELINE | L3: SRC-DE_BMFTR_HEALTH | M3: P1 | N3: ACTIVE | O3: Suchquelle, kein bestaetigter offener Call. Antragsteller, Konsortium, Standort und Bedingungen pro Ausschreibung pruefen. | P3: PR-FUND-DE_BMFTR_HEALTH | Q3: =IFERROR(IF(VLOOKUP(L3,SOURCE_REGISTRY!$A$2:$E$246,5,FALSE)="","",VLOOKUP(L3,SOURCE_REGISTRY!$A$2:$E$246,5,FALSE)),"") -> https://www.gesundheitsforschung-bmftr.de/de/bekanntmachungen-5786.php | S3: ANY | T3: CORE
A4: DE_DFG | B4: DFG Förderprogramme | C4: PORTAL | D4: ACADEMIA | E4: DE | F4: ANY | G4: BASIC;CLINICAL;HEALTH | H4: ANY | I4: DISCOVERY;PRECLINICAL;PHASE_1;PHASE_2;PHASE_3 | J4: CLINICAL | K4: MATCH | L4: SRC-DE_DFG | M4: P2 | N4: ACTIVE | O4: Suchquelle, kein bestaetigter offener Call. Antragsteller, Konsortium, Standort und Bedingungen pro Ausschreibung pruefen. | P4: PR-FUND-DE_DFG | Q4: =IFERROR(IF(VLOOKUP(L4,SOURCE_REGISTRY!$A$2:$E$246,5,FALSE)="","",VLOOKUP(L4,SOURCE_REGISTRY!$A$2:$E$246,5,FALSE)),"") -> https://www.dfg.de/de/foerderung/foerdermoeglichkeiten/programme | S4: ANY | T4: CONDITIONAL
A5: DE_DFG_CLINICAL | B5: DFG Klinische Studien | C5: PROGRAMME | D5: ACADEMIA | E5: DE | F5: ANY | G5: CLINICAL | H5: ANY | I5: PHASE_1;PHASE_2;PHASE_3 | J5: CLINICAL | K5: MATCH | L5: SRC-DE_DFG_CLINICAL | M5: P2 | N5: ACTIVE | O5: Suchquelle, kein bestaetigter offener Call. Antragsteller, Konsortium, Standort und Bedingungen pro Ausschreibung pruefen. | P5: PR-FUND-DE_DFG_CLINICAL | Q5: =IFERROR(IF(VLOOKUP(L5,SOURCE_REGISTRY!$A$2:$E$246,5,FALSE)="","",VLOOKUP(L5,SOURCE_REGISTRY!$A$2:$E$246,5,FALSE)),"") -> https://www.dfg.de/de/foerderung/foerdermoeglichkeiten/programme/einzelfoerderung/klinische-studien | S5: ANY | T5: CONDITIONAL
A6: DE_FORTRA | B6: EKFS / ForTra Translatorik | C6: PROGRAMME | D6: ACADEMIA;PUBLIC_BODY | E6: DE | F6: ANY | G6: TRANSLATION;THERAPEUTICS;DIAGNOSTICS;MEDTECH | H6: ANY | I6: PRECLINICAL;PHASE_1 | J6: CMC | K6: MATCH | L6: SRC-DE_FORTRA | M6: P1 | N6: ACTIVE | O6: Translatorische Programmfamilie; konkrete Ausschreibung und Eligibility bleiben live. | P6: PR-FUND-DE_FORTRA | Q6: =IFERROR(IF(VLOOKUP(L6,SOURCE_REGISTRY!$A$2:$E$246,5,FALSE)="","",VLOOKUP(L6,SOURCE_REGISTRY!$A$2:$E$246,5,FALSE)),"") -> https://ekfs.de/wissenschaftliche-foerderung/Translatorik-ForTra/Foerderverfahren | S6: ANY | T6: CONDITIONAL
A7: DE_EKFS_CALLS | B7: EKFS Ausschreibungskalender | C7: PORTAL | D7: ACADEMIA;PUBLIC_BODY | E7: DE | F7: ANY | G7: HEALTH;CLINICAL;TRANSLATION | H7: ANY | I7: ANY | J7: ANY | K7: MATCH | L7: SRC-DE_EKFS_CALLS | M7: P2 | N7: ACTIVE | O7: Suchquelle, kein bestaetigter offener Call. Antragsteller, Konsortium, Standort und Bedingungen pro Ausschreibung pruefen. | P7: PR-FUND-DE_EKFS_CALLS | Q7: =IFERROR(IF(VLOOKUP(L7,SOURCE_REGISTRY!$A$2:$E$246,5,FALSE)="","",VLOOKUP(L7,SOURCE_REGISTRY!$A$2:$E$246,5,FALSE)),"") -> https://ekfs.de/en/current-topics/funding-application-calender | S7: ANY | T7: CONDITIONAL
A8: DE_GO_BIO | B8: GO-Bio next | C8: PROGRAMME | D8: ACADEMIA;SPINOUT | E8: DE | F8: ANY | G8: TRANSLATION;COMMERCIALIZATION | H8: ANY | I8: PRECLINICAL;DISCOVERY;LEAD | J8: CMC | K8: MATCH | L8: SRC-DE_GO_BIO | M8: P2 | N8: ACTIVE | O8: Suchquelle, kein bestaetigter offener Call. Antragsteller, Konsortium, Standort und Bedingungen pro Ausschreibung pruefen. | P8: PR-FUND-DE_GO_BIO | Q8: =IFERROR(IF(VLOOKUP(L8,SOURCE_REGISTRY!$A$2:$E$246,5,FALSE)="","",VLOOKUP(L8,SOURCE_REGISTRY!$A$2:$E$246,5,FALSE)),"") -> https://www.foerderdatenbank.de/FDB/Content/DE/Foerderprogramm/Bund/BMBF/go-bio-next.html | S8: ANY | T8: CONDITIONAL
A9: DE_KMU_BIOMED | B9: KMU-innovativ Biomedizin | C9: PROGRAMME | D9: SME;CONSORTIUM | E9: DE | F9: ANY | G9: HEALTH;THERAPEUTICS;DIAGNOSTICS;MEDTECH | H9: ANY | I9: PRECLINICAL;PHASE_1;PHASE_2;PHASE_3 | J9: CMC;CLINICAL | K9: MATCH | L9: SRC-DE_KMU_BIOMED | M9: P2 | N9: ACTIVE | O9: Suchquelle, kein bestaetigter offener Call. Antragsteller, Konsortium, Standort und Bedingungen pro Ausschreibung pruefen. | P9: PR-FUND-DE_KMU_BIOMED | Q9: =IFERROR(IF(VLOOKUP(L9,SOURCE_REGISTRY!$A$2:$E$246,5,FALSE)="","",VLOOKUP(L9,SOURCE_REGISTRY!$A$2:$E$246,5,FALSE)),"") -> https://www.foerderdatenbank.de/FDB/Content/DE/Foerderprogramm/Bund/BMBF/biomedizin.html | S9: ANY | T9: CONDITIONAL
A10: DE_ZIM | B10: ZIM - Zentrales Innovationsprogramm Mittelstand | C10: PROGRAMME | D10: SME;CONSORTIUM | E10: DE | F10: ANY | G10: INNOVATION;COMMERCIALIZATION | H10: ANY | I10: DISCOVERY;LEAD;PRECLINICAL | J10: CMC | K10: MATCH | L10: SRC-DE_ZIM | M10: P2 | N10: ACTIVE | O10: Suchquelle, kein bestaetigter offener Call. Antragsteller, Konsortium, Standort und Bedingungen pro Ausschreibung pruefen. | P10: PR-FUND-DE_ZIM | Q10: =IFERROR(IF(VLOOKUP(L10,SOURCE_REGISTRY!$A$2:$E$246,5,FALSE)="","",VLOOKUP(L10,SOURCE_REGISTRY!$A$2:$E$246,5,FALSE)),"") -> https://www.zim.de/ | S10: ANY | T10: CONDITIONAL
A11: DE_EXIST | B11: EXIST | C11: PROGRAMME | D11: ACADEMIA;SPINOUT | E11: DE | F11: ANY | G11: SPINOUT;COMMERCIALIZATION | H11: ANY | I11: DISCOVERY;LEAD;PRECLINICAL | J11: ANY | K11: MATCH | L11: SRC-DE_EXIST | M11: P2 | N11: REVIEW | O11: Suchquelle, kein bestaetigter offener Call. Antragsteller, Konsortium, Standort und Bedingungen pro Ausschreibung pruefen. | P11: PR-FUND-DE_EXIST | Q11: =IFERROR(IF(VLOOKUP(L11,SOURCE_REGISTRY!$A$2:$E$246,5,FALSE)="","",VLOOKUP(L11,SOURCE_REGISTRY!$A$2:$E$246,5,FALSE)),"") -> https://www.exist.de/ | S11: ANY | T11: CONDITIONAL
A12: DE_VW_STIFTUNG | B12: VolkswagenStiftung - Förderangebote | C12: FOUNDATION | D12: ACADEMIA | E12: DE | F12: ANY | G12: BASIC;HEALTH;INNOVATION | H12: ANY | I12: DISCOVERY;PRECLINICAL | J12: ANY | K12: MATCH | L12: SRC-DE_VW_STIFTUNG | M12: P2 | N12: REVIEW | O12: Suchquelle, kein bestaetigter offener Call. Antragsteller, Konsortium, Standort und Bedingungen pro Ausschreibung pruefen. | P12: PR-FUND-DE_VW_STIFTUNG | Q12: =IFERROR(IF(VLOOKUP(L12,SOURCE_REGISTRY!$A$2:$E$246,5,FALSE)="","",VLOOKUP(L12,SOURCE_REGISTRY!$A$2:$E$246,5,FALSE)),"") -> https://www.volkswagenstiftung.de/de/foerderung | S12: ANY | T12: CONDITIONAL
A13: DE_DZIF_INTERNAL | B13: DZIF interne Projekt- und Transferförderung | C13: INSTITUTION | D13: ACADEMIA;PUBLIC_BODY | E13: DE | F13: DZIF | G13: INSTITUTION;TRANSLATION;HEALTH | H13: ANY | I13: ANY | J13: ANY | K13: INSTITUTION | L13: SRC-DE_DZIF_INTERNAL | M13: P1 | N13: REVIEW | O13: Suchquelle, kein bestaetigter offener Call. Antragsteller, Konsortium, Standort und Bedingungen pro Ausschreibung pruefen. Interne Calls ggf. nicht oeffentlich; autorisierte interne Quelle erforderlich. | P13: PR-FUND-DE_DZIF_INTERNAL | Q13: =IFERROR(IF(VLOOKUP(L13,SOURCE_REGISTRY!$A$2:$E$246,5,FALSE)="","",VLOOKUP(L13,SOURCE_REGISTRY!$A$2:$E$246,5,FALSE)),"") -> https://www.dzif.de/ | S13: ANY | T13: CONDITIONAL
... A52: DE_GO_BIO_INITIAL | B52: GO-Bio initial | C52: PROGRAMME | D52: ACADEMIA;PUBLIC_BODY | E52: DE | F52: ANY | G52: TRANSLATION;BIOTECH;SPINOUT | H52: ANY | I52: DISCOVERY;PRECLINICAL | J52: ANY | K52: MATCH | L52: SRC-V2-GO_BIO_INITIAL | M52: P1 | N52: ACTIVE | O52: Fruehe Verwertungsideen; kein Ersatz fuer GO-Bio next. | P52: PR-V2-DE_GO_BIO_INITIAL | Q52: =IFERROR(IF(VLOOKUP(L52,SOURCE_REGISTRY!$A$2:$E$246,5,FALSE)="","",VLOOKUP(L52,SOURCE_REGISTRY!$A$2:$E$246,5,FALSE)),"") -> https://www.foerderdatenbank.de/FDB/Content/DE/Foerderprogramm/Bund/BMBF/gesundheitsforschung-go-bio-initial2.html | S52: ALL | T52: CONDITIONAL
A53: EU_HORIZON_HEALTH | B53: Horizon Europe Cluster 1 Health | C53: PROGRAMME | D53: ACADEMIA;SME;INDUSTRY;PUBLIC_BODY;CONSORTIUM | E53: EU | F53: ANY | G53: HEALTH;INFECTIOUS_BROAD | H53: ANY | I53: ANY | J53: ANY | K53: MATCH | L53: SRC-EU_FT | M53: P1 | N53: ACTIVE | O53: Topic-, Konsortial- und Laenderbedingungen konkret pruefen; Portal mit EU_FT geteilt. | P53: PR-V2-EU_HORIZON_HEALTH | Q53: =IFERROR(IF(VLOOKUP(L53,SOURCE_REGISTRY!$A$2:$E$246,5,FALSE)="","",VLOOKUP(L53,SOURCE_REGISTRY!$A$2:$E$246,5,FALSE)),"") -> https://ec.europa.eu/info/funding-tenders/opportunities/portal/screen/opportunities/calls-for-proposals | R53: EU_FT | S53: ALL | T53: CONDITIONAL
A54: EU_EIC_PATHFINDER | B54: EIC Pathfinder | C54: PROGRAMME | D54: ACADEMIA;SME;INDUSTRY;CONSORTIUM | E54: EU | F54: ANY | G54: PLATFORM;BIOTECH;BASIC | H54: ANY | I54: DISCOVERY;PRECLINICAL | J54: ANY | K54: MATCH | L54: SRC-V2-EIC_PATHFINDER | M54: P1 | N54: ACTIVE | O54: Open und Challenges haben unterschiedliche Regeln; TRL nicht klinischer Phase gleichsetzen. | P54: PR-V2-EU_EIC_PATHFINDER | Q54: =IFERROR(IF(VLOOKUP(L54,SOURCE_REGISTRY!$A$2:$E$246,5,FALSE)="","",VLOOKUP(L54,SOURCE_REGISTRY!$A$2:$E$246,5,FALSE)),"") -> https://eic.ec.europa.eu/eic-funding-opportunities/eic-pathfinder_en | R54: EU_EIC | S54: ALL | T54: CONDITIONAL
A55: EU_EIC_TRANSITION | B55: EIC Transition | C55: PROGRAMME | D55: ACADEMIA;SME;CONSORTIUM | E55: EU | F55: ANY | G55: TRANSLATION;PLATFORM;BIOTECH | H55: ELIGIBLE_EU_RESULT | I55: ANY | J55: ANY | K55: MATCH | L55: SRC-V2-EIC_TRANSITION | M55: P1 | N55: ACTIVE | O55: Zugelassenes EU-Vorprojektergebnis und Fristfenster zwingend verifizieren. | P55: PR-V2-EU_EIC_TRANSITION | Q55: =IFERROR(IF(VLOOKUP(L55,SOURCE_REGISTRY!$A$2:$E$246,5,FALSE)="","",VLOOKUP(L55,SOURCE_REGISTRY!$A$2:$E$246,5,FALSE)),"") -> https://eic.ec.europa.eu/eic-funding-opportunities/eic-transition_en | R55: EU_EIC | S55: ALL | T55: CONDITIONAL
A56: EU_EIC_ACCELERATOR | B56: EIC Accelerator | C56: PROGRAMME | D56: SME | E56: EU | F56: ANY | G56: SPINOUT;COMMERCIALIZATION;BIOTECH | H56: ANY | I56: ANY | J56: ANY | K56: MATCH | L56: SRC-V2-EIC_ACCELERATOR | M56: P1 | N56: ACTIVE | O56: SME-/Startup- bzw. Gruendungskonstellation, TRL und Grant/Investment-Komponente pro Call pruefen. | P56: PR-V2-EU_EIC_ACCELERATOR | Q56: =IFERROR(IF(VLOOKUP(L56,SOURCE_REGISTRY!$A$2:$E$246,5,FALSE)="","",VLOOKUP(L56,SOURCE_REGISTRY!$A$2:$E$246,5,FALSE)),"") -> https://eic.ec.europa.eu/eic-funding-opportunities/eic-accelerator_en | R56: EU_EIC | S56: ALL | T56: CONDITIONAL
A57: EU_ERC_POC | B57: ERC Proof of Concept | C57: PROGRAMME | D57: ACADEMIA | E57: EU | F57: ANY | G57: TRANSLATION;SPINOUT;COMMERCIALIZATION | H57: ELIGIBLE_ERC_GRANT | I57: ANY | J57: ANY | K57: MATCH | L57: SRC-V2-ERC_POC | M57: P1 | N57: ACTIVE | O57: Kein offenes allgemeines Transferprogramm; Foerderfaehigkeit der ERC-PI-Vorfoerderung pruefen. | P57: PR-V2-EU_ERC_POC | Q57: =IFERROR(IF(VLOOKUP(L57,SOURCE_REGISTRY!$A$2:$E$246,5,FALSE)="","",VLOOKUP(L57,SOURCE_REGISTRY!$A$2:$E$246,5,FALSE)),"") -> https://erc.europa.eu/apply-grant/proof-concept | S57: ALL | T57: CONDITIONAL
A58: US_BARDA_BAA | B58: BARDA BAA | C58: SOLICITATION | D58: ACADEMIA;SME;INDUSTRY;CONSORTIUM | E58: GLOBAL | F58: ANY | G58: PREPAREDNESS;PANDEMIC;AMR | H58: US_MCM_FIT | I58: ANY | J58: ANY | K58: MATCH | L58: SRC-V2-BARDA_BAA | M58: P1 | N58: ACTIVE | O58: US-Bedarfsfit, aktive AOIs, internationale Teilnahme und Vertragsbedingungen pruefen. | P58: PR-V2-US_BARDA_BAA | Q58: =IFERROR(IF(VLOOKUP(L58,SOURCE_REGISTRY!$A$2:$E$246,5,FALSE)="","",VLOOKUP(L58,SOURCE_REGISTRY!$A$2:$E$246,5,FALSE)),"") -> https://www.medicalcountermeasures.gov/barda/barda-baa | S58: ALL | T58: CONDITIONAL
A59: US_BARDA_DRIVE | B59: BARDA DRIVe opportunities | C59: OPPORTUNITIES_PORTAL | D59: ACADEMIA;SME;INDUSTRY;CONSORTIUM | E59: GLOBAL | F59: ANY | G59: PREPAREDNESS;DIAGNOSTICS;PLATFORM | H59: US_MCM_FIT | I59: ANY | J59: ANY | K59: MATCH | L59: SRC-V2-BARDA_DRIVE | M59: P1 | N59: ACTIVE | O59: Kein Always-open-Grant; EZ-BAA derzeit laut separater offizieller Statusroute geschlossen. | P59: PR-V2-US_BARDA_DRIVE | Q59: =IFERROR(IF(VLOOKUP(L59,SOURCE_REGISTRY!$A$2:$E$246,5,FALSE)="","",VLOOKUP(L59,SOURCE_REGISTRY!$A$2:$E$246,5,FALSE)),"") -> https://www.drive.hhs.gov/partner.html | S59: ALL | T59: CONDITIONAL
A60: GL_FIND_PARTNERS | B60: FIND calls for partners | C60: PARTNER_CALL | D60: ACADEMIA;SME;INDUSTRY;PUBLIC_BODY;CONSORTIUM | E60: GLOBAL | F60: ANY | G60: DIAGNOSTICS | H60: ANY | I60: ANY | J60: ANY | K60: MATCH | L60: SRC-V2-FIND | M60: P1 | N60: ACTIVE | O60: Partnerschafts-/Entwicklungsaufruf; Budget und Zuschusscharakter nur bei explizitem Nachweis. | P60: PR-V2-GL_FIND_PARTNERS | Q60: =IFERROR(IF(VLOOKUP(L60,SOURCE_REGISTRY!$A$2:$E$246,5,FALSE)="","",VLOOKUP(L60,SOURCE_REGISTRY!$A$2:$E$246,5,FALSE)),"") -> https://www.finddx.org/about-us/donors-and-partners/calls-for-partners/ | S60: ALL | T60: CONDITIONAL
A61: EU_HERA_OPPORTUNITIES | B61: HERA funding and opportunities | C61: OPPORTUNITIES_PORTAL | D61: ACADEMIA;SME;INDUSTRY;PUBLIC_BODY;CONSORTIUM | E61: EU | F61: ANY | G61: PREPAREDNESS;PANDEMIC;AMR | H61: ANY | I61: ANY | J61: ANY | K61: MATCH | L61: SRC-V2-HERA | M61: P1 | N61: ACTIVE | O61: Forschungsfoerderung, Beschaffung und Bevorratung sind unterschiedliche Instrumente. | P61: PR-V2-EU_HERA_OPPORTUNITIES | Q61: =IFERROR(IF(VLOOKUP(L61,SOURCE_REGISTRY!$A$2:$E$246,5,FALSE)="","",VLOOKUP(L61,SOURCE_REGISTRY!$A$2:$E$246,5,FALSE)),"") -> https://health.ec.europa.eu/health-emergency-preparedness-and-response-hera_en | R61: EU_FT | S61: ALL | T61: CONDITIONAL
A62: INST_BONN_BONFOR | B62: BONFOR - Medizinische Fakultaet Bonn | C62: INSTITUTION | D62: ACADEMIA | E62: DE-NW | F62: UNI_BONN_MED | G62: BASIC;CLINICAL;TRANSLATION | H62: ANY | I62: DISCOVERY;PRECLINICAL | J62: CLINICAL | K62: INSTITUTION | L62: SRC-V22-BONFOR | M62: P2 | N62: ACTIVE | O62: Nur geeignete Angehoerige der Medizinischen Fakultaet Bonn; aktuelle Instrumente, Bewerberstatus und Fristen live pruefen. | P62: PR-V22-INST-BONN-BONFOR | Q62: =IFERROR(IF(VLOOKUP(L62,SOURCE_REGISTRY!$A$2:$E$246,5,FALSE)="","",VLOOKUP(L62,SOURCE_REGISTRY!$A$2:$E$246,5,FALSE)),"") -> https://www.medfak.uni-bonn.de/de/forschung/forschungsfoerderung/bonfor/bonfor-forschungsfoerderprogramm | S62: ALL | T62: CONDITIONAL
A63: INST_TUEBINGEN_FORTUNE | B63: fortuene - Medizinische Fakultaet Tuebingen | C63: INSTITUTION | D63: ACADEMIA | E63: DE-BW | F63: UNI_TUEBINGEN_MED | G63: BASIC;CLINICAL;TRANSLATION | H63: ANY | I63: DISCOVERY;PRECLINICAL | J63: TRANSLATION;CLINICAL | K63: INSTITUTION | L63: SRC-V22-FORTUNE | M63: P2 | N63: ACTIVE | O63: Intramurale Ausschreibungen; eligibles Arbeitsverhaeltnis und Foerderlinie anhand Originalseite pruefen. | P63: PR-V22-INST-TUEBINGEN-FORTUNE | Q63: =IFERROR(IF(VLOOKUP(L63,SOURCE_REGISTRY!$A$2:$E$246,5,FALSE)="","",VLOOKUP(L63,SOURCE_REGISTRY!$A$2:$E$246,5,FALSE)),"") -> https://www.medizin.uni-tuebingen.de/de/medizinische-fakultaet/forschung/forschungsfoerderung | S63: ALL | T63: CONDITIONAL
A64: INST_MHH_HILF | B64: MHH Hochschulinterne Leistungsfoerderung (HiLF) | C64: INSTITUTION | D64: ACADEMIA | E64: DE-NI | F64: MHH | G64: BASIC;CLINICAL;TRANSLATION | H64: ANY | I64: DISCOVERY;PRECLINICAL | J64: CLINICAL | K64: INSTITUTION | L64: SRC-V22-MHH | M64: P2 | N64: ACTIVE | O64: MHH-interne Foerderung; Details nur im Intranet, verbindlicher Zugriff muss vor Antragsplanung geklaert werden. | P64: PR-V22-INST-MHH-HILF | Q64: =IFERROR(IF(VLOOKUP(L64,SOURCE_REGISTRY!$A$2:$E$246,5,FALSE)="","",VLOOKUP(L64,SOURCE_REGISTRY!$A$2:$E$246,5,FALSE)),"") -> https://www.mhh.de/forschung/hochschulinterne-leistungsfoerderung | S64: ALL | T64: CONDITIONAL
A65: INST_HEIDELBERG_COLLAB | B65: Heidelberg Medizin - Collaborative Seed Grant | C65: INSTITUTION | D65: ACADEMIA | E65: DE-BW | F65: UNI_HEIDELBERG_MED | G65: BASIC;CLINICAL;TRANSLATION | H65: ANY | I65: DISCOVERY;PRECLINICAL | J65: TRANSLATION;CLINICAL | K65: INSTITUTION | L65: SRC-V22-HDSEED | M65: P2 | N65: ACTIVE | O65: Befristete fakultatsinterne Anschubfoerderung; keine universelle DZIF-Foerderung. | P65: PR-V22-INST-HEIDELBERG-COLLAB | Q65: =IFERROR(IF(VLOOKUP(L65,SOURCE_REGISTRY!$A$2:$E$246,5,FALSE)="","",VLOOKUP(L65,SOURCE_REGISTRY!$A$2:$E$246,5,FALSE)),"") -> https://www.medizinische-fakultaet-hd.uni-heidelberg.de/forschung/forschungsfoerderung/foerderprogramme-der-fakultaet/collaborative-seed-grant-funding/ | S65: ALL | T65: CONDITIONAL
A66: REG_HE_LOEWE | B66: Hessen LOEWE - Forschung und Transfer | C66: PROGRAMME | D66: ACADEMIA;SME;CONSORTIUM;PUBLIC_BODY | E66: DE-HE | F66: ANY | G66: BASIC;TRANSLATION;BIOTECH | H66: ANY | I66: ANY | J66: TRANSLATION;CLINICAL | K66: REGION | L66: SRC-V22-LOEWE | M66: P2 | N66: ACTIVE | O66: Unterschiedliche LOEWE-Foerderlinien; akademisch, KMU-Verbund und Forschung nicht gleichsetzen. | P66: PR-V22-REG-HE-LOEWE | Q66: =IFERROR(IF(VLOOKUP(L66,SOURCE_REGISTRY!$A$2:$E$246,5,FALSE)="","",VLOOKUP(L66,SOURCE_REGISTRY!$A$2:$E$246,5,FALSE)),"") -> https://wissenschaft.hessen.de/forschen/forschungsfoerderprogramm-loewe | S66: ALL | T66: CONDITIONAL
A67: GL_UNITAID_PROJECTS | B67: Unitaid - Global Health Project & Funding Calls | C67: OPPORTUNITIES_PORTAL | D67: ACADEMIA;SME;NONPROFIT;CONSORTIUM | E67: GLOBAL | F67: ANY | G67: GLOBAL_HEALTH;HIV;TUBERCULOSIS;MALARIA;DIAGNOSTICS | H67: ANY | I67: ANY | J67: ANY | K67: MATCH | L67: SRC-V22-UNITAID | M67: P2 | N67: ACTIVE | O67: Programm-/Projektquellen; aktuelle Wettbewerbe, Aufrufart und Eligibility in jedem Run pruefen. Viele Instrumente sind Implementierung, nicht preclinical R&D. | P67: PR-V22-GL-UNITAID-PROJECTS | Q67: =IFERROR(IF(VLOOKUP(L67,SOURCE_REGISTRY!$A$2:$E$246,5,FALSE)="","",VLOOKUP(L67,SOURCE_REGISTRY!$A$2:$E$246,5,FALSE)),"") -> https://unitaid.org/projects/ | S67: ALL | T67: CONDITIONAL
A68: DE_NI_IBT | B68: IBT Lower Saxony - EXPLORE / PRE-SEED | C68: PROGRAMME_FAMILY | D68: ACADEMIA;PUBLIC_BODY | E68: DE-NI | F68: ANY | G68: TRANSLATION;THERAPEUTICS;DIAGNOSTICS;MEDTECH | H68: ANY | I68: DISCOVERY;LEAD;PRECLINICAL | J68: TRANSLATION;COMMERCIALIZATION | K68: REGION | L68: SRC-V23-IBT_LS | M68: P1 | N68: ACTIVE | O68: Research from Lower Saxony; EXPLORE and PRE-SEED conditions differ. State and applicant eligibility, IP, commercialization plan and current call must be verified; do not infer an open call. | P68: PR-V23-IBT | Q68: =IFERROR(IF(VLOOKUP(L68,SOURCE_REGISTRY!$A$2:$E$246,5,FALSE)="","",VLOOKUP(L68,SOURCE_REGISTRY!$A$2:$E$246,5,FALSE)),"") -> https://niedersachsen-next.de/themen/life-science/ibt-lower-saxony/ | S68: ANY | T68: CONDITIONAL

Sheet M06_BD_PARTNERS
A1: record_id | B1: entity_id | C1: entity_name | D1: partner_role | E1: topic_tags | F1: modality_tags | G1: development_scope | H1: investment_stage | I1: applicant_route | J1: geography_scope | K1: source_id | L1: base_priority | M1: status | N1: fit_note | O1: constraints | P1: provenance_id | Q1: source_url | R1: watch_policy
A2: BD-001 | B2: CMP-579c450159e | C2: =IFERROR(VLOOKUP(B2,ENTITY_MASTER!$A$2:$B$266,2,FALSE),"") -> GSK | D2: LICENSING_PARTNER | E2: BACTERIAL;VIRAL;VACCINE;HIV | F2: VACCINE;ANTIBODY;SMALL_MOLECULE | G2: ANY | H2: NOT_APPLICABLE | I2: ACADEMIA_OR_COMPANY | J2: GLOBAL | K2: SRC-GSK-BD | L2: P1 | M2: ACTIVE | N2: Allgemeiner Licensing-/Partnering-Einstieg; keine positive Asset-Fit-Aussage. | O2: Aktuelle therapeutische Schwerpunkte je Projekt abgleichen. | P2: PR-BD-001 | Q2: =IFERROR(IF(VLOOKUP(K2,SOURCE_REGISTRY!$A$2:$E$246,5,FALSE)="","",VLOOKUP(K2,SOURCE_REGISTRY!$A$2:$E$246,5,FALSE)),"") -> https://www.gsk.com/en-gb/innovation/partnerships/ | R2: CONDITIONAL
A3: BD-002 | B3: CMP-3f134522796 | C3: =IFERROR(VLOOKUP(B3,ENTITY_MASTER!$A$2:$B$266,2,FALSE),"") -> MSD / Merck & Co. | D3: LICENSING_PARTNER | E3: VIRAL;BACTERIAL;VACCINE | F3: VACCINE;ANTIBODY;SMALL_MOLECULE;CELL_GENE_THERAPY | G3: PRECLINICAL;PHASE_1;PHASE_2;PHASE_3;APPROVED | H3: NOT_APPLICABLE | I3: ACADEMIA_OR_COMPANY | J3: GLOBAL | K3: SRC-BD-002 | L3: P1 | M3: ACTIVE | N3: Ausgangsbegruendung (nicht neu live validiert): Offizielles BD&L-Formular erfasst Infectious Diseases, Vaccines und Pre-PoC. | O3: Merck & Co. (MSD) nicht mit Merck KGaA verwechseln. | P3: PR-BD-002 | Q3: =IFERROR(IF(VLOOKUP(K3,SOURCE_REGISTRY!$A$2:$E$246,5,FALSE)="","",VLOOKUP(K3,SOURCE_REGISTRY!$A$2:$E$246,5,FALSE)),"") -> https://www.msd.com/research/business-development-and-licensing/collaborate-with-us/ | R3: CONDITIONAL
A4: BD-003 | B4: CMP-ef3fd5062fb | C4: =IFERROR(VLOOKUP(B4,ENTITY_MASTER!$A$2:$B$266,2,FALSE),"") -> Sanofi | D4: LICENSING_PARTNER | E4: VIRAL;BACTERIAL;VACCINE;RESPIRATORY | F4: VACCINE;ANTIBODY;RNA;PLATFORM | G4: DISCOVERY;LEAD;PRECLINICAL;PHASE_1;PHASE_2;PHASE_3;APPROVED | H4: NOT_APPLICABLE | I4: ACADEMIA_OR_COMPANY | J4: GLOBAL | K4: SRC-BD-003 | L4: P1 | M4: ACTIVE | N4: Ausgangsbegruendung (nicht neu live validiert): Ausdrueckliches Vaccines-Partnering inkl. externer Innovationsprogramme. | O4: Konkreter Indikationsfit und IP-Rechte projektbezogen pruefen. | P4: PR-BD-003 | Q4: =IFERROR(IF(VLOOKUP(K4,SOURCE_REGISTRY!$A$2:$E$246,5,FALSE)="","",VLOOKUP(K4,SOURCE_REGISTRY!$A$2:$E$246,5,FALSE)),"") -> https://www.sanofi.com/en/partnering/partnering-focus-areas/vaccines | R4: CONDITIONAL
A5: BD-004 | B5: CMP-335ff7e594c | C5: =IFERROR(VLOOKUP(B5,ENTITY_MASTER!$A$2:$B$266,2,FALSE),"") -> Pfizer | D5: LICENSING_PARTNER | E5: BACTERIAL;VIRAL;VACCINE | F5: VACCINE;RNA;ANTIBODY;PLATFORM | G5: ANY | H5: NOT_APPLICABLE | I5: ACADEMIA_OR_COMPANY | J5: GLOBAL | K5: SRC-PFIZER-BD | L5: P1 | M5: ACTIVE | N5: Partnering-Ziel getrennt von Pfizer Ventures; Schwerpunkt laufend pruefen. | O5: Pfizer Ventures als eigene Investment-Einheit separat erfassen. | P5: PR-BD-004 | Q5: =IFERROR(IF(VLOOKUP(K5,SOURCE_REGISTRY!$A$2:$E$246,5,FALSE)="","",VLOOKUP(K5,SOURCE_REGISTRY!$A$2:$E$246,5,FALSE)),"") -> https://www.pfizer.com/about/partners/research-and-business-development-partnerships/ | R5: CONDITIONAL
A6: BD-005 | B6: CMP-578ce8097cb | C6: =IFERROR(VLOOKUP(B6,ENTITY_MASTER!$A$2:$B$266,2,FALSE),"") -> Roche | D6: LICENSING_PARTNER | E6: VIRAL;BACTERIAL;AMR | F6: ANTIBODY;SMALL_MOLECULE;PLATFORM | G6: DISCOVERY;LEAD;PRECLINICAL;PHASE_1;PHASE_2;PHASE_3;APPROVED | H6: NOT_APPLICABLE | I6: ACADEMIA_OR_COMPANY | J6: GLOBAL | K6: SRC-BD-005 | L6: P1 | M6: ACTIVE | N6: Ausgangsbegruendung (nicht neu live validiert): Offizielle Pharma-Partnering-Schwerpunkte HBV und MDR-Gramnegative. | O6: Interesse an anderem Pathogen/Target nicht unterstellen. | P6: PR-BD-005 | Q6: =IFERROR(IF(VLOOKUP(K6,SOURCE_REGISTRY!$A$2:$E$246,5,FALSE)="","",VLOOKUP(K6,SOURCE_REGISTRY!$A$2:$E$246,5,FALSE)),"") -> https://www.roche.com/innovation/partnering/areas-of-interest/infectious-diseases | R6: CONDITIONAL
A7: BD-006 | B7: CMP-e1f2b6c9f07 | C7: =IFERROR(VLOOKUP(B7,ENTITY_MASTER!$A$2:$B$266,2,FALSE),"") -> Shionogi | D7: LICENSING_PARTNER | E7: BACTERIAL;AMR;VIRAL;HIV;FUNGAL | F7: SMALL_MOLECULE;ANTIBODY;VACCINE | G7: PHASE_1;PHASE_2;PHASE_3;APPROVED | H7: NOT_APPLICABLE | I7: ACADEMIA_OR_COMPANY | J7: GLOBAL;EU | K7: SRC-BD-006 | L7: P1 | M7: ACTIVE | N7: Ausgangsbegruendung (nicht neu live validiert): Aktive europaeische In-Licensing-Interessen fuer Infektionskrankheiten. | O7: Bestehende Target- und Gebietsrechte pruefen. | P7: PR-BD-006 | Q7: =IFERROR(IF(VLOOKUP(K7,SOURCE_REGISTRY!$A$2:$E$246,5,FALSE)="","",VLOOKUP(K7,SOURCE_REGISTRY!$A$2:$E$246,5,FALSE)),"") -> https://www.shionogi.com/eu/en/innovation/strategic-partnering-in-europe/partnering-licensing-interests.html | R7: CONDITIONAL
A8: BD-007 | B8: CMP-93148ce3ea6 | C8: =IFERROR(VLOOKUP(B8,ENTITY_MASTER!$A$2:$B$266,2,FALSE),"") -> Basilea Pharmaceutica | D8: LICENSING_PARTNER | E8: BACTERIAL;AMR;FUNGAL | F8: SMALL_MOLECULE | G8: PRECLINICAL;PHASE_1;PHASE_2;PHASE_3;APPROVED | H8: NOT_APPLICABLE | I8: ACADEMIA_OR_COMPANY | J8: GLOBAL | K8: SRC-BD-007 | L8: P1 | M8: ACTIVE | N8: Ausgangsbegruendung (nicht neu live validiert): Nachgewiesene externe Antiinfektiva-Einlizenzierungen und Portfolioaufbau. | O8: Modalitaetsfit fuer Impfstoffe/Antikoerper nicht automatisch gegeben. | P8: PR-BD-007 | Q8: =IFERROR(IF(VLOOKUP(K8,SOURCE_REGISTRY!$A$2:$E$246,5,FALSE)="","",VLOOKUP(K8,SOURCE_REGISTRY!$A$2:$E$246,5,FALSE)),"") -> https://www.basilea.com/news/news/basilea-informiert-ueber-stand-seines-portfolios-und-gibt-ausblick-1 | R8: CONDITIONAL
A9: BD-008 | B9: CMP-3d4eedeeed7 | C9: =IFERROR(VLOOKUP(B9,ENTITY_MASTER!$A$2:$B$266,2,FALSE),"") -> Eli Lilly | D9: ACQUIRER | E9: VIRAL;BACTERIAL;VACCINE | F9: VACCINE;PLATFORM;CELL_GENE_THERAPY | G9: PRECLINICAL;PHASE_1;PHASE_2;PHASE_3;APPROVED | H9: NOT_APPLICABLE | I9: ACADEMIA_OR_COMPANY | J9: GLOBAL | K9: SRC-BD-008 | L9: P1 | M9: ACTIVE | N9: Ausgangsbegruendung (nicht neu live validiert): 2026 Erwerb von drei Impfstoff-/Infektionsentwicklern. | O9: Neue Infectious-Diseases-Strategie erst 2026 aufgebaut. | P9: PR-BD-008 | Q9: =IFERROR(IF(VLOOKUP(K9,SOURCE_REGISTRY!$A$2:$E$246,5,FALSE)="","",VLOOKUP(K9,SOURCE_REGISTRY!$A$2:$E$246,5,FALSE)),"") -> https://investor.lilly.com/node/54346 | R9: CONDITIONAL
A10: BD-009 | B10: ENT-BD-009 | C10: =IFERROR(VLOOKUP(B10,ENTITY_MASTER!$A$2:$B$266,2,FALSE),"") -> Asahi Kasei Therapeutics (group route) | D10: ACQUIRER | E10: VIRAL;IMMUNOCOMPROMISED | F10: SMALL_MOLECULE | G10: PHASE_1;PHASE_2;PHASE_3;APPROVED | H10: NOT_APPLICABLE | I10: ACADEMIA_OR_COMPANY | J10: GLOBAL | K10: SRC-V2-AKTX | L10: P1 | M10: REVIEW | N10: Ausgangsbegruendung (nicht neu live validiert): 2026 abgeschlossene Uebernahme von AiCuris fuer schwere Virusinfektionen. | O10: AiCuris kein unabhaengiger Uebernahmekandidat mehr. | P10: PR-BD-009 | Q10: =IFERROR(IF(VLOOKUP(K10,SOURCE_REGISTRY!$A$2:$E$246,5,FALSE)="","",VLOOKUP(K10,SOURCE_REGISTRY!$A$2:$E$246,5,FALSE)),"") -> https://www.aktx.com/ | R10: CONDITIONAL
A11: BD-010 | B11: CMP-85e7acc8115 | C11: =IFERROR(VLOOKUP(B11,ENTITY_MASTER!$A$2:$B$266,2,FALSE),"") -> AstraZeneca | D11: STRATEGIC_PARTNER | E11: BACTERIAL;VIRAL;RESPIRATORY | F11: ANTIBODY;VACCINE | G11: PRECLINICAL;PHASE_1;PHASE_2;PHASE_3;APPROVED | H11: NOT_APPLICABLE | I11: ACADEMIA_OR_COMPANY | J11: GLOBAL | K11: SRC-BD-010 | L11: P2 | M11: ACTIVE | N11: Ausgangsbegruendung (nicht neu live validiert): Aktive Infectious-Disease- und Antikoerperprogramme laut Pipeline. | O11: Eigene konkurrierende Assets und aktuelle BD-Interessen pruefen. | P11: PR-BD-010 | Q11: =IFERROR(IF(VLOOKUP(K11,SOURCE_REGISTRY!$A$2:$E$246,5,FALSE)="","",VLOOKUP(K11,SOURCE_REGISTRY!$A$2:$E$246,5,FALSE)),"") -> https://www.astrazeneca.com/our-therapy-areas/pipeline.html | R11: CONDITIONAL
A12: BD-011 | B12: CMP-1dc25b959ce | C12: =IFERROR(VLOOKUP(B12,ENTITY_MASTER!$A$2:$B$266,2,FALSE),"") -> BioNTech | D12: STRATEGIC_PARTNER | E12: VIRAL;BACTERIAL;PARASITIC;VACCINE | F12: RNA;VACCINE;CELL_GENE_THERAPY;ANTIBODY | G12: PRECLINICAL;PHASE_1;PHASE_2;PHASE_3;APPROVED | H12: NOT_APPLICABLE | I12: ACADEMIA_OR_COMPANY | J12: GLOBAL | K12: SRC-BD-011 | L12: P1 | M12: ACTIVE | N12: Ausgangsbegruendung (nicht neu live validiert): mRNA-Impfstoffprogramme gegen TB, Malaria, HIV, Mpox; aktive Partnerschaften. | O12: Aktuelles Investment-/Lizenzinteresse nicht aus Pipeline ableiten. | P12: PR-BD-011 | Q12: =IFERROR(IF(VLOOKUP(K12,SOURCE_REGISTRY!$A$2:$E$246,5,FALSE)="","",VLOOKUP(K12,SOURCE_REGISTRY!$A$2:$E$246,5,FALSE)),"") -> https://www.biontech.com/us/en/home/research-and-innovation/therapeutic-areas/infectious-diseases.html | R12: CONDITIONAL
A13: BD-012 | B13: CMP-24531a6b01f | C13: =IFERROR(VLOOKUP(B13,ENTITY_MASTER!$A$2:$B$266,2,FALSE),"") -> Moderna | D13: STRATEGIC_PARTNER | E13: VIRAL;BACTERIAL;VACCINE;PANDEMIC | F13: RNA;VACCINE | G13: PRECLINICAL;PHASE_1;PHASE_2;PHASE_3;APPROVED | H13: NOT_APPLICABLE | I13: ACADEMIA_OR_COMPANY | J13: GLOBAL | K13: SRC-BD-012 | L13: P1 | M13: ACTIVE | N13: Ausgangsbegruendung (nicht neu live validiert): Breites klinisches mRNA-Vakzinportfolio inkl. viraler und bakterieller Targets. | O13: Partnering-Fit und aktuelle Programme separat pruefen. | P13: PR-BD-012 | Q13: =IFERROR(IF(VLOOKUP(K13,SOURCE_REGISTRY!$A$2:$E$246,5,FALSE)="","",VLOOKUP(K13,SOURCE_REGISTRY!$A$2:$E$246,5,FALSE)),"") -> https://www.modernatx.com/research/product-pipeline | R13: CONDITIONAL
... A79: BD-V22-UNITAID | B79: ENT-V22-UNITAID | C79: =IFERROR(VLOOKUP(B79,ENTITY_MASTER!$A$2:$B$266,2,FALSE),"") -> Unitaid | D79: STRATEGIC_PARTNER | E79: GLOBAL_HEALTH;HIV;TUBERCULOSIS;MALARIA;DIAGNOSTICS | F79: MULTI_MODALITY | G79: UNKNOWN | H79: NOT_APPLICABLE | I79: ACADEMIA_OR_COMPANY | J79: GLOBAL | K79: SRC-V22-UNITAID | L79: P2 | M79: ACTIVE | N79: Access, deployment, implementation partnerships; not a universal preclinical grant. | O79: Organisation/Technologiebezug ist kein offenes Licensing- oder Equity-Mandat. Konditionen projektspezifisch live pruefen. | P79: PR-V22-BD-V22-UNITAID | Q79: =IFERROR(IF(VLOOKUP(K79,SOURCE_REGISTRY!$A$2:$E$246,5,FALSE)="","",VLOOKUP(K79,SOURCE_REGISTRY!$A$2:$E$246,5,FALSE)),"") -> https://unitaid.org/projects/ | R79: CONDITIONAL

Sheet M07_DEALS
A1: record_id | B1: entity_id | C1: entity_name | D1: record_type | E1: topic_tags | F1: modality_tags | G1: transaction_types | H1: source_id | I1: base_priority | J1: status | K1: provenance_id | L1: cautions | M1: watch_policy
A2: M07-BD-001 | B2: CMP-579c450159e | C2: =IFERROR(VLOOKUP(B2,ENTITY_MASTER!$A$2:$B$266,2,FALSE),"") -> GSK | D2: DEAL_WATCH | E2: BACTERIAL;VIRAL;VACCINE;HIV | F2: VACCINE;ANTIBODY;SMALL_MOLECULE | G2: LICENSING;COLLABORATION;M_AND_A;FINANCING | H2: SRC-GSK-BD | I2: P1 | J2: ACTIVE | K2: PR-BD-001 | L2: Suchprofil aus BD, kein behaupteter Deal. Aktuelle News/Investments suchen; historische Einstiegsseite nicht als laufendes Ereignis behandeln. | M2: CONDITIONAL
A3: M07-BD-002 | B3: CMP-3f134522796 | C3: =IFERROR(VLOOKUP(B3,ENTITY_MASTER!$A$2:$B$266,2,FALSE),"") -> MSD / Merck & Co. | D3: DEAL_WATCH | E3: VIRAL;BACTERIAL;VACCINE | F3: VACCINE;ANTIBODY;SMALL_MOLECULE;CELL_GENE_THERAPY | G3: LICENSING;COLLABORATION;M_AND_A;FINANCING | H3: SRC-BD-002 | I3: P1 | J3: ACTIVE | K3: PR-BD-002 | L3: Suchprofil aus BD, kein behaupteter Deal. Aktuelle News/Investments suchen; historische Einstiegsseite nicht als laufendes Ereignis behandeln. | M3: CONDITIONAL
A4: M07-BD-003 | B4: CMP-ef3fd5062fb | C4: =IFERROR(VLOOKUP(B4,ENTITY_MASTER!$A$2:$B$266,2,FALSE),"") -> Sanofi | D4: DEAL_WATCH | E4: VIRAL;BACTERIAL;VACCINE;RESPIRATORY | F4: VACCINE;ANTIBODY;RNA;PLATFORM | G4: LICENSING;COLLABORATION;M_AND_A;FINANCING | H4: SRC-BD-003 | I4: P1 | J4: ACTIVE | K4: PR-BD-003 | L4: Suchprofil aus BD, kein behaupteter Deal. Aktuelle News/Investments suchen; historische Einstiegsseite nicht als laufendes Ereignis behandeln. | M4: CONDITIONAL
A5: M07-BD-004 | B5: CMP-335ff7e594c | C5: =IFERROR(VLOOKUP(B5,ENTITY_MASTER!$A$2:$B$266,2,FALSE),"") -> Pfizer | D5: DEAL_WATCH | E5: BACTERIAL;VIRAL;VACCINE | F5: VACCINE;RNA;ANTIBODY;PLATFORM | G5: LICENSING;COLLABORATION;M_AND_A;FINANCING | H5: SRC-PFIZER-BD | I5: P1 | J5: ACTIVE | K5: PR-BD-004 | L5: Suchprofil aus BD, kein behaupteter Deal. Aktuelle News/Investments suchen; historische Einstiegsseite nicht als laufendes Ereignis behandeln. | M5: CONDITIONAL
A6: M07-BD-005 | B6: CMP-578ce8097cb | C6: =IFERROR(VLOOKUP(B6,ENTITY_MASTER!$A$2:$B$266,2,FALSE),"") -> Roche | D6: DEAL_WATCH | E6: VIRAL;BACTERIAL;AMR | F6: ANTIBODY;SMALL_MOLECULE;PLATFORM | G6: LICENSING;COLLABORATION;M_AND_A;FINANCING | H6: SRC-BD-005 | I6: P1 | J6: ACTIVE | K6: PR-BD-005 | L6: Suchprofil aus BD, kein behaupteter Deal. Aktuelle News/Investments suchen; historische Einstiegsseite nicht als laufendes Ereignis behandeln. | M6: CONDITIONAL
A7: M07-BD-006 | B7: CMP-e1f2b6c9f07 | C7: =IFERROR(VLOOKUP(B7,ENTITY_MASTER!$A$2:$B$266,2,FALSE),"") -> Shionogi | D7: DEAL_WATCH | E7: BACTERIAL;AMR;VIRAL;HIV;FUNGAL | F7: SMALL_MOLECULE;ANTIBODY;VACCINE | G7: LICENSING;COLLABORATION;M_AND_A;FINANCING | H7: SRC-BD-006 | I7: P1 | J7: ACTIVE | K7: PR-BD-006 | L7: Suchprofil aus BD, kein behaupteter Deal. Aktuelle News/Investments suchen; historische Einstiegsseite nicht als laufendes Ereignis behandeln. | M7: CONDITIONAL
A8: M07-BD-007 | B8: CMP-93148ce3ea6 | C8: =IFERROR(VLOOKUP(B8,ENTITY_MASTER!$A$2:$B$266,2,FALSE),"") -> Basilea Pharmaceutica | D8: DEAL_WATCH | E8: BACTERIAL;AMR;FUNGAL | F8: SMALL_MOLECULE | G8: LICENSING;COLLABORATION;M_AND_A;FINANCING | H8: SRC-BD-007 | I8: P1 | J8: ACTIVE | K8: PR-BD-007 | L8: Suchprofil aus BD, kein behaupteter Deal. Aktuelle News/Investments suchen; historische Einstiegsseite nicht als laufendes Ereignis behandeln. | M8: CONDITIONAL
A9: M07-BD-008 | B9: CMP-3d4eedeeed7 | C9: =IFERROR(VLOOKUP(B9,ENTITY_MASTER!$A$2:$B$266,2,FALSE),"") -> Eli Lilly | D9: DEAL_WATCH | E9: VIRAL;BACTERIAL;VACCINE | F9: VACCINE;PLATFORM;CELL_GENE_THERAPY | G9: LICENSING;COLLABORATION;M_AND_A;FINANCING | H9: SRC-BD-008 | I9: P1 | J9: ACTIVE | K9: PR-BD-008 | L9: Suchprofil aus BD, kein behaupteter Deal. Aktuelle News/Investments suchen; historische Einstiegsseite nicht als laufendes Ereignis behandeln. | M9: CONDITIONAL
A10: M07-BD-009 | B10: ENT-BD-009 | C10: =IFERROR(VLOOKUP(B10,ENTITY_MASTER!$A$2:$B$266,2,FALSE),"") -> Asahi Kasei Therapeutics (group route) | D10: DEAL_WATCH | E10: VIRAL;IMMUNOCOMPROMISED | F10: SMALL_MOLECULE | G10: LICENSING;COLLABORATION;M_AND_A;FINANCING | H10: SRC-V2-AKTX | I10: P1 | J10: REVIEW | K10: PR-BD-009 | L10: Suchprofil aus BD, kein behaupteter Deal. Aktuelle News/Investments suchen; historische Einstiegsseite nicht als laufendes Ereignis behandeln. | M10: CONDITIONAL
A11: M07-BD-010 | B11: CMP-85e7acc8115 | C11: =IFERROR(VLOOKUP(B11,ENTITY_MASTER!$A$2:$B$266,2,FALSE),"") -> AstraZeneca | D11: DEAL_WATCH | E11: BACTERIAL;VIRAL;RESPIRATORY | F11: ANTIBODY;VACCINE | G11: LICENSING;COLLABORATION;M_AND_A;FINANCING | H11: SRC-BD-010 | I11: P2 | J11: ACTIVE | K11: PR-BD-010 | L11: Suchprofil aus BD, kein behaupteter Deal. Aktuelle News/Investments suchen; historische Einstiegsseite nicht als laufendes Ereignis behandeln. | M11: CONDITIONAL
A12: M07-BD-011 | B12: CMP-1dc25b959ce | C12: =IFERROR(VLOOKUP(B12,ENTITY_MASTER!$A$2:$B$266,2,FALSE),"") -> BioNTech | D12: DEAL_WATCH | E12: VIRAL;BACTERIAL;PARASITIC;VACCINE | F12: RNA;VACCINE;CELL_GENE_THERAPY;ANTIBODY | G12: LICENSING;COLLABORATION;M_AND_A;FINANCING | H12: SRC-BD-011 | I12: P1 | J12: ACTIVE | K12: PR-BD-011 | L12: Suchprofil aus BD, kein behaupteter Deal. Aktuelle News/Investments suchen; historische Einstiegsseite nicht als laufendes Ereignis behandeln. | M12: CONDITIONAL
A13: M07-BD-012 | B13: CMP-24531a6b01f | C13: =IFERROR(VLOOKUP(B13,ENTITY_MASTER!$A$2:$B$266,2,FALSE),"") -> Moderna | D13: DEAL_WATCH | E13: VIRAL;BACTERIAL;VACCINE;PANDEMIC | F13: RNA;VACCINE | G13: LICENSING;COLLABORATION;M_AND_A;FINANCING | H13: SRC-BD-012 | I13: P1 | J13: ACTIVE | K13: PR-BD-012 | L13: Suchprofil aus BD, kein behaupteter Deal. Aktuelle News/Investments suchen; historische Einstiegsseite nicht als laufendes Ereignis behandeln. | M13: CONDITIONAL
... A58: M07-BD-057 | B58: ENT-BD-057 | C58: =IFERROR(VLOOKUP(B58,ENTITY_MASTER!$A$2:$B$266,2,FALSE),"") -> KHAN Technology Transfer Fund II | D58: DEAL_WATCH | E58: BIOTECH;PLATFORM;INFECTIOUS_BROAD | F58: MULTI_MODALITY | G58: EQUITY_FINANCING;FUNDRAISING | H58: SRC-BD-057 | I58: P1 | J58: ACTIVE | K58: PR-BD-057 | L58: Suchprofil aus BD, kein behaupteter Deal. Aktuelle News/Investments suchen; historische Einstiegsseite nicht als laufendes Ereignis behandeln. | M58: CONDITIONAL

Sheet M08_EVENTS
A1: record_id | B1: record_name | C1: record_type | D1: scope_note | E1: topic_tags | F1: pathogen_tags | G1: modality_tags | H1: jurisdiction_tags | I1: query_class | J1: source_id | K1: base_priority | L1: watch_policy | M1: status | N1: catalog_review_on | O1: source_url | P1: cautions
A2: M08-ESCMID | B2: ESCMID Global | C2: EVENT_SERIES | D2: EVENT_SERIES | E2: ANY | F2: ANY | G2: ANY | H2: GLOBAL | I2: M08_EVENT | J2: SRC-V2-ESCMID | K2: P1 | L2: CORE | M2: ACTIVE | N2: 2026-10-29 | O2: =IFERROR(IF(VLOOKUP(J2,SOURCE_REGISTRY!$A$2:$E$246,5,FALSE)="","",VLOOKUP(J2,SOURCE_REGISTRY!$A$2:$E$246,5,FALSE)),"") -> https://www.escmid.org/congress-events/escmid-global/ | P2: Veranstaltungsreihe; Termine und Abstract-/Partneringfristen live ermitteln.
A3: M08-IDWEEK | B3: IDWeek | C3: EVENT_SERIES | D3: EVENT_SERIES | E3: ANY | F3: ANY | G3: ANY | H3: GLOBAL | I3: M08_EVENT | J3: SRC-V2-IDWEEK | K3: P1 | L3: CORE | M3: ACTIVE | N3: 2026-10-29 | O3: =IFERROR(IF(VLOOKUP(J3,SOURCE_REGISTRY!$A$2:$E$246,5,FALSE)="","",VLOOKUP(J3,SOURCE_REGISTRY!$A$2:$E$246,5,FALSE)),"") -> https://www.idweek.org/ | P3: Veranstaltungsreihe; bereits vergangene Ausgabe nicht als kommende Veranstaltung ausgeben.
A4: M08-BIO | B4: BIO International Convention | C4: EVENT_SERIES | D4: EVENT_SERIES | E4: ANY | F4: ANY | G4: ANY | H4: GLOBAL | I4: M08_EVENT | J4: SRC-V2-BIO | K4: P1 | L4: CORE | M4: ACTIVE | N4: 2026-10-29 | O4: =IFERROR(IF(VLOOKUP(J4,SOURCE_REGISTRY!$A$2:$E$246,5,FALSE)="","",VLOOKUP(J4,SOURCE_REGISTRY!$A$2:$E$246,5,FALSE)),"") -> https://convention.bio.org/ | P4: BD-/Partnering-Reihe; konkrete Ausgabe und Fristen live pruefen.
A5: M08-BIOEUROPE | B5: BIO-Europe | C5: EVENT_SERIES | D5: EVENT_SERIES | E5: ANY | F5: ANY | G5: ANY | H5: GLOBAL | I5: M08_EVENT | J5: SRC-V2-BIOEUROPE | K5: P1 | L5: CORE | M5: ACTIVE | N5: 2026-10-29 | O5: =IFERROR(IF(VLOOKUP(J5,SOURCE_REGISTRY!$A$2:$E$246,5,FALSE)="","",VLOOKUP(J5,SOURCE_REGISTRY!$A$2:$E$246,5,FALSE)),"") -> https://informaconnect.com/bioeurope/ | P5: BD-Partnering; Veranstaltungsreihe, keine dauerhaft gueltigen Jahresdaten.
A6: M08-ASGCT | B6: ASGCT annual meeting | C6: EVENT_SERIES | D6: EVENT_SERIES | E6: ANY | F6: ANY | G6: CELL_GENE_THERAPY;GENE_THERAPY;CELL_THERAPY;RNA | H6: GLOBAL | I6: M08_EVENT | J6: SRC-V2-ASGCT | K6: P1 | L6: CONDITIONAL | M6: ACTIVE | N6: 2026-10-29 | O6: =IFERROR(IF(VLOOKUP(J6,SOURCE_REGISTRY!$A$2:$E$246,5,FALSE)="","",VLOOKUP(J6,SOURCE_REGISTRY!$A$2:$E$246,5,FALSE)),"") -> https://annualmeeting.asgct.org/ | P6: Zell-/Gentherapieplattformen und Translational Development.
A7: M08-WVC | B7: World Vaccine Congress Europe | C7: EVENT_SERIES | D7: EVENT_SERIES | E7: ANY | F7: ANY | G7: VACCINE | H7: GLOBAL | I7: M08_EVENT | J7: SRC-V2-WVC | K7: P1 | L7: CONDITIONAL | M7: ACTIVE | N7: 2026-10-29 | O7: =IFERROR(IF(VLOOKUP(J7,SOURCE_REGISTRY!$A$2:$E$246,5,FALSE)="","",VLOOKUP(J7,SOURCE_REGISTRY!$A$2:$E$246,5,FALSE)),"") -> https://www.terrapinn.com/conference/world-vaccine-congress-europe/ | P7: Impfstoffentwicklung und Partnering; Eventtermine gesondert abrufen.
A8: M08-V21-CROI | B8: CROI | C8: SOURCE_ANCHOR | D8: HIV and opportunistic infections; deadlines not stored as permanent master facts. | E8: HIV;IMMUNOCOMPROMISED | F8: ANY | G8: ANY | H8: ANY | I8: M08_EVENT | J8: SRC-V21-CROI | K8: P1 | L8: CONDITIONAL | M8: ACTIVE | N8: 2026-10-29 | O8: =IFERROR(IF(VLOOKUP(J8,SOURCE_REGISTRY!$A$2:$E$246,5,FALSE)="","",VLOOKUP(J8,SOURCE_REGISTRY!$A$2:$E$246,5,FALSE)),"") -> https://www.croiconference.org/ | P8: Reference source only. No module activation and no live evidence implied.

Sheet M09_MEDICAL
A1: record_id | B1: record_name | C1: record_type | D1: scope_note | E1: topic_tags | F1: pathogen_tags | G1: modality_tags | H1: jurisdiction_tags | I1: query_class | J1: source_id | K1: base_priority | L1: watch_policy | M1: status | N1: catalog_review_on | O1: source_url | P1: cautions
A2: M09-IDSA | B2: IDSA guidelines | C2: SOURCE_WATCH | D2: MEDICAL_GUIDELINE_HUB | E2: ANY | F2: ANY | G2: ANY | H2: GLOBAL | I2: M09_MEDICAL | J2: SRC-V2-IDSA | K2: P1 | L2: CORE | M2: ACTIVE | N2: 2026-10-29 | O2: =IFERROR(IF(VLOOKUP(J2,SOURCE_REGISTRY!$A$2:$E$246,5,FALSE)="","",VLOOKUP(J2,SOURCE_REGISTRY!$A$2:$E$246,5,FALSE)),"") -> https://www.idsociety.org/practice-guideline/practice-guidelines/ | P2: Standard of Care nach Indikation/Population/Jurisdiktion, aktuelle Version verifizieren.
A3: M09-WHO_GUIDE | B3: WHO guidelines | C3: SOURCE_WATCH | D3: MEDICAL_PUBLIC_HEALTH_GUIDELINES | E3: ANY | F3: ANY | G3: ANY | H3: GLOBAL | I3: M09_MEDICAL | J3: SRC-V2-WHO_GUIDE | K3: P1 | L3: CORE | M3: ACTIVE | N3: 2026-10-29 | O3: =IFERROR(IF(VLOOKUP(J3,SOURCE_REGISTRY!$A$2:$E$246,5,FALSE)="","",VLOOKUP(J3,SOURCE_REGISTRY!$A$2:$E$246,5,FALSE)),"") -> https://www.who.int/publications/who-guidelines | P3: Planung und publizierte Guidelines trennen; erwartetes Datum ist keine bereits veroeffentlichte Empfehlung.
A4: M09-AWMF | B4: AWMF guidelines register | C4: SOURCE_WATCH | D4: GERMAN_GUIDELINE_REGISTER | E4: ANY | F4: ANY | G4: ANY | H4: DE | I4: M09_MEDICAL | J4: SRC-V2-AWMF | K4: P1 | L4: CORE | M4: ACTIVE | N4: 2026-10-29 | O4: =IFERROR(IF(VLOOKUP(J4,SOURCE_REGISTRY!$A$2:$E$246,5,FALSE)="","",VLOOKUP(J4,SOURCE_REGISTRY!$A$2:$E$246,5,FALSE)),"") -> https://register.awmf.org/de/leitlinien/aktuelle-leitlinien | P4: Bot-Schutz blockiert Direktabruf. Manuelle/offizielle Suchroute notwendig; keine Umgehung implementiert.
A5: M09-ECDC | B5: ECDC data dashboards | C5: SOURCE_WATCH | D5: EU_EPIDEMIOLOGY | E5: ANY | F5: ANY | G5: ANY | H5: EU | I5: M09_MEDICAL | J5: SRC-V2-ECDC | K5: P1 | L5: CORE | M5: ACTIVE | N5: 2026-10-29 | O5: =IFERROR(IF(VLOOKUP(J5,SOURCE_REGISTRY!$A$2:$E$246,5,FALSE)="","",VLOOKUP(J5,SOURCE_REGISTRY!$A$2:$E$246,5,FALSE)),"") -> https://www.ecdc.europa.eu/en/data-dashboards-and-databases | P5: Datenraum, Berichtsjahr, Definitionen und Nenner dokumentieren; keine DACH-Marktgroesse direkt ableiten.
A6: M09-PHAGE_MEDICAL | B6: IDSA phage consensus guideline | C6: SOURCE_WATCH | D6: CLINICAL_CONSENSUS_GUIDELINE | E6: ANY | F6: ANY | G6: PHAGE | H6: GLOBAL | I6: M09_MEDICAL | J6: SRC-V2-PHAGE_MEDICAL | K6: P1 | L6: CONDITIONAL | M6: ACTIVE | N6: 2026-10-29 | O6: =IFERROR(IF(VLOOKUP(J6,SOURCE_REGISTRY!$A$2:$E$246,5,FALSE)="","",VLOOKUP(J6,SOURCE_REGISTRY!$A$2:$E$246,5,FALSE)),"") -> https://www.idsociety.org/practice-guideline/personalized-bacteriophage-therapy/ | P6: Consensus Statement vom 21.09.2026; individualisierte klinische Phagentherapie, keine Marktzulassungsentscheidung.
A7: M09-V21-ESCMID_GUIDE | B7: ESCMID clinical guidelines | C7: SOURCE_ANCHOR | D7: Clinical-management source, distinct from ESCMID congress; scope, version and recommendations checked per run. | E7: ANY | F7: ANY | G7: ANY | H7: ANY | I7: M09_MEDICAL | J7: SRC-V21-ESCMID_GUIDE | K7: P1 | L7: CONDITIONAL | M7: ACTIVE | N7: 2026-10-29 | O7: =IFERROR(IF(VLOOKUP(J7,SOURCE_REGISTRY!$A$2:$E$246,5,FALSE)="","",VLOOKUP(J7,SOURCE_REGISTRY!$A$2:$E$246,5,FALSE)),"") -> https://www.escmid.org/guidelines-journals/guidelines/published-guidelines/ | P7: Reference source only. No module activation and no live evidence implied.

Sheet M10_IP_PATENT
A1: record_id | B1: record_name | C1: record_type | D1: scope_note | E1: topic_tags | F1: pathogen_tags | G1: modality_tags | H1: jurisdiction_tags | I1: query_class | J1: source_id | K1: base_priority | L1: watch_policy | M1: status | N1: catalog_review_on | O1: source_url | P1: cautions
A2: M10-ESPACENET | B2: EPO Espacenet | C2: SOURCE_WATCH | D2: PATENT_SEARCH_ROUTE | E2: ANY | F2: ANY | G2: ANY | H2: GLOBAL | I2: M10_PATENT | J2: SRC-V2-ESPACENET | K2: P1 | L2: CORE | M2: ACTIVE | N2: 2026-10-29 | O2: =IFERROR(IF(VLOOKUP(J2,SOURCE_REGISTRY!$A$2:$E$246,5,FALSE)="","",VLOOKUP(J2,SOURCE_REGISTRY!$A$2:$E$246,5,FALSE)),"") -> https://www.epo.org/en/searching-for-patents/technical/espacenet | P2: Patentanmeldungen, Familien und Prioritaeten; keine Freedom-to-Operate-Freigabe.
A3: M10-PATENTSCOPE | B3: WIPO PATENTSCOPE | C3: SOURCE_WATCH | D3: PATENT_SEARCH_ROUTE | E3: ANY | F3: ANY | G3: ANY | H3: GLOBAL | I3: M10_PATENT | J3: SRC-V2-PATENTSCOPE | K3: P1 | L3: CORE | M3: ACTIVE | N3: 2026-10-29 | O3: =IFERROR(IF(VLOOKUP(J3,SOURCE_REGISTRY!$A$2:$E$246,5,FALSE)="","",VLOOKUP(J3,SOURCE_REGISTRY!$A$2:$E$246,5,FALSE)),"") -> https://www.wipo.int/en/web/patentscope | P3: PCT und teilnehmende Aemter; Familie/Dubletten/Status pruefen; nicht alle nationalen Rechtsstaende.
A4: M10-DPMA | B4: DPMAregister | C4: SOURCE_WATCH | D4: GERMAN_PATENT_STATUS | E4: ANY | F4: ANY | G4: ANY | H4: DE | I4: M10_PATENT | J4: SRC-V2-DPMA | K4: P1 | L4: CORE | M4: ACTIVE | N4: 2026-10-29 | O4: =IFERROR(IF(VLOOKUP(J4,SOURCE_REGISTRY!$A$2:$E$246,5,FALSE)="","",VLOOKUP(J4,SOURCE_REGISTRY!$A$2:$E$246,5,FALSE)),"") -> https://www.dpma.de/recherche/dpmaregister/index.html | P4: Rechts-/Verfahrensstand in Deutschland; rechtliche Bewertung durch Patentexperten.

Sheet M11_CMC
A1: record_id | B1: record_name | C1: record_type | D1: scope_note | E1: topic_tags | F1: pathogen_tags | G1: modality_tags | H1: jurisdiction_tags | I1: query_class | J1: source_id | K1: base_priority | L1: watch_policy | M1: status | N1: catalog_review_on | O1: source_url | P1: cautions
A2: M11-EU_GMP | B2: EudraLex Volume 4 | C2: SOURCE_WATCH | D2: GMP_GUIDANCE | E2: ANY | F2: ANY | G2: ANY | H2: GLOBAL | I2: M11_CMC | J2: SRC-V2-EU_GMP | K2: P1 | L2: CORE | M2: ACTIVE | N2: 2026-10-29 | O2: =IFERROR(IF(VLOOKUP(J2,SOURCE_REGISTRY!$A$2:$E$246,5,FALSE)="","",VLOOKUP(J2,SOURCE_REGISTRY!$A$2:$E$246,5,FALSE)),"") -> https://health.ec.europa.eu/medicinal-products/eudralex/eudralex-volume-4_en | P2: EU GMP einschliesslich ATMP Teil IV; einschlaegige Anhaenge live pruefen.
A3: M11-ICH_Q | B3: ICH quality guidelines | C3: SOURCE_WATCH | D3: QUALITY_GUIDELINE_HUB | E3: ANY | F3: ANY | G3: ANY | H3: GLOBAL | I3: M11_CMC | J3: SRC-V2-ICH_Q | K3: P1 | L3: CORE | M3: ACTIVE | N3: 2026-10-29 | O3: =IFERROR(IF(VLOOKUP(J3,SOURCE_REGISTRY!$A$2:$E$246,5,FALSE)="","",VLOOKUP(J3,SOURCE_REGISTRY!$A$2:$E$246,5,FALSE)),"") -> https://www.ich.org/page/quality-guidelines | P3: Dynamische Seite; ICH-Versionen, regionale Implementierung und Produktklasse beachten.
A4: M11-EMA_GUIDE | B4: EMA scientific guidelines | C4: SOURCE_WATCH | D4: REGULATORY_GUIDELINE_HUB | E4: ANY | F4: ANY | G4: ANY | H4: GLOBAL | I4: M11_CMC | J4: SRC-V2-EMA_GUIDE | K4: P1 | L4: CORE | M4: ACTIVE | N4: 2026-10-29 | O4: =IFERROR(IF(VLOOKUP(J4,SOURCE_REGISTRY!$A$2:$E$246,5,FALSE)="","",VLOOKUP(J4,SOURCE_REGISTRY!$A$2:$E$246,5,FALSE)),"") -> https://www.ema.europa.eu/en/human-regulatory-overview/research-development/scientific-guidelines-human-medicines | P4: Version, Draft/Final, Gueltigkeitsdatum und Produktklasse live pruefen. Keine vertraulichen Scientific-Advice-Protokolle erwarten.
A5: M11-FDA_CGT | B5: FDA cellular and gene therapy guidance | C5: SOURCE_WATCH | D5: CGT_GUIDELINE_ROUTE | E5: ANY | F5: ANY | G5: CELL_GENE_THERAPY;CELL_THERAPY;GENE_THERAPY | H5: US | I5: M11_CMC | J5: SRC-V2-FDA_CGT | K5: P1 | L5: CONDITIONAL | M5: ACTIVE | N5: 2026-10-29 | O5: =IFERROR(IF(VLOOKUP(J5,SOURCE_REGISTRY!$A$2:$E$246,5,FALSE)="","",VLOOKUP(J5,SOURCE_REGISTRY!$A$2:$E$246,5,FALSE)),"") -> https://www.fda.gov/vaccines-blood-biologics/biologics-guidances/cellular-gene-therapy-guidances | P5: CBER-Zell-/Gentherapie; produkt- und risikospezifische Anforderungen.
A6: M11-EMA_ATMP | B6: EMA investigational ATMP guideline | C6: SOURCE_WATCH | D6: ATMP_GUIDELINE_ROUTE | E6: ANY | F6: ANY | G6: CELL_GENE_THERAPY;CELL_THERAPY;GENE_THERAPY | H6: EU | I6: M11_CMC | J6: SRC-V2-EMA_ATMP | K6: P1 | L6: CONDITIONAL | M6: ACTIVE | N6: 2026-10-29 | O6: =IFERROR(IF(VLOOKUP(J6,SOURCE_REGISTRY!$A$2:$E$246,5,FALSE)="","",VLOOKUP(J6,SOURCE_REGISTRY!$A$2:$E$246,5,FALSE)),"") -> https://www.ema.europa.eu/en/scientific-guidelines/guideline-quality-non-clinical-clinical-requirements-investigational-advanced-therapy-medicinal-products-clinical-trials | P6: Zell-/Gentherapie; einschlaegige Version und Umsetzungsdatum pruefen.
A7: M11-EMA_PHAGE | B7: EMA phage quality guideline | C7: SOURCE_WATCH | D7: PHAGE_QUALITY_GUIDELINE | E7: ANY | F7: ANY | G7: PHAGE | H7: GLOBAL | I7: M11_CMC | J7: SRC-V2-EMA_PHAGE | K7: P1 | L7: CONDITIONAL | M7: ACTIVE | N7: 2026-10-29 | O7: =IFERROR(IF(VLOOKUP(J7,SOURCE_REGISTRY!$A$2:$E$246,5,FALSE)="","",VLOOKUP(J7,SOURCE_REGISTRY!$A$2:$E$246,5,FALSE)),"") -> https://www.ema.europa.eu/en/scientific-guidelines/quality-aspects-phage-therapy-medicinal-products | P7: Offizielle Seite zeigt Draft / consultation closed; nicht als finale verbindliche Leitlinie ausgeben.
A8: M11-FDA_LBP | B8: FDA live biotherapeutic CMC guidance | C8: SOURCE_WATCH | D8: LIVE_BIOTHERAPEUTIC_CMC | E8: ANY | F8: ANY | G8: MICROBIOME | H8: US | I8: M11_CMC | J8: SRC-V2-FDA_LBP | K8: P1 | L8: CONDITIONAL | M8: ACTIVE | N8: 2026-10-29 | O8: =IFERROR(IF(VLOOKUP(J8,SOURCE_REGISTRY!$A$2:$E$246,5,FALSE)="","",VLOOKUP(J8,SOURCE_REGISTRY!$A$2:$E$246,5,FALSE)),"") -> https://www.fda.gov/regulatory-information/search-fda-guidance-documents/early-clinical-trials-live-biotherapeutic-products-chemistry-manufacturing-and-control-information | P8: FDA-Route fuer Live Biotherapeutic Products. Nicht automatisch auf Gentherapie-Vektoren anwendbar.

Sheet M12_POLICY_ACCESS
A1: record_id | B1: record_name | C1: record_type | D1: scope_note | E1: topic_tags | F1: pathogen_tags | G1: modality_tags | H1: jurisdiction_tags | I1: query_class | J1: source_id | K1: base_priority | L1: watch_policy | M1: status | N1: catalog_review_on | O1: source_url | P1: cautions
A2: M12-HERA | B2: HERA opportunities and policy | C2: SOURCE_WATCH | D2: PREPAREDNESS_OPPORTUNITIES | E2: PREPAREDNESS;PANDEMIC;AMR | F2: ANY | G2: ANY | H2: EU | I2: M12_POLICY | J2: SRC-V2-HERA | K2: P1 | L2: CONDITIONAL | M2: ACTIVE | N2: 2026-10-29 | O2: =IFERROR(IF(VLOOKUP(J2,SOURCE_REGISTRY!$A$2:$E$246,5,FALSE)="","",VLOOKUP(J2,SOURCE_REGISTRY!$A$2:$E$246,5,FALSE)),"") -> https://health.ec.europa.eu/health-emergency-preparedness-and-response-hera_en | P2: Forschung, Beschaffung und Preparedness trennen; kein einzelner universell offener Call.
A3: M12-GBA | B3: G-BA benefit assessment | C3: SOURCE_WATCH | D3: DE_ACCESS_ASSESSMENT | E3: ANY | F3: ANY | G3: ANY | H3: DE | I3: M12_POLICY | J3: SRC-V2-GBA | K3: P1 | L3: CORE | M3: ACTIVE | N3: 2026-10-29 | O3: =IFERROR(IF(VLOOKUP(J3,SOURCE_REGISTRY!$A$2:$E$246,5,FALSE)="","",VLOOKUP(J3,SOURCE_REGISTRY!$A$2:$E$246,5,FALSE)),"") -> https://www.g-ba.de/bewertungsverfahren/nutzenbewertung/ | P3: Nutzenbewertungsverfahren und Vergleichstherapie; Relevanz fuer Produkt und Land pruefen.
A4: M12-EU_HTA | B4: EU Health Technology Assessment | C4: SOURCE_WATCH | D4: EU_HTA_POLICY | E4: ANY | F4: ANY | G4: ANY | H4: EU | I4: M12_POLICY | J4: SRC-V2-EU_HTA | K4: P1 | L4: CORE | M4: ACTIVE | N4: 2026-10-29 | O4: =IFERROR(IF(VLOOKUP(J4,SOURCE_REGISTRY!$A$2:$E$246,5,FALSE)="","",VLOOKUP(J4,SOURCE_REGISTRY!$A$2:$E$246,5,FALSE)),"") -> https://health.ec.europa.eu/health-technology-assessment_en | P4: Gemeinsame Bewertungen/Beratungen und Umsetzung; Scope und Anwendungstermine pruefen.
A5: M12-UNICEF | B5: UNICEF immunization market dashboard | C5: SOURCE_WATCH | D5: VACCINE_MARKET_PROCUREMENT | E5: ANY | F5: ANY | G5: VACCINE | H5: GLOBAL | I5: M12_POLICY | J5: SRC-V2-UNICEF | K5: P1 | L5: CONDITIONAL | M5: ACTIVE | N5: 2026-10-29 | O5: =IFERROR(IF(VLOOKUP(J5,SOURCE_REGISTRY!$A$2:$E$246,5,FALSE)="","",VLOOKUP(J5,SOURCE_REGISTRY!$A$2:$E$246,5,FALSE)),"") -> https://www.unicef.org/supply/immunization-market-dashboard | P5: Beschaffungs- und Marktinformationen; Preis/Volumen nicht in jaehrlichem Master festschreiben.
A6: M12-NHS_AMR | B6: NHS antibiotic subscription model | C6: SOURCE_WATCH | D6: UK_AMR_PULL_ROUTE | E6: AMR;ANTIBACTERIAL | F6: ANY | G6: ANY | H6: UK | I6: M12_POLICY | J6: SRC-V2-NHS_AMR | K6: P1 | L6: CONDITIONAL | M6: ACTIVE | N6: 2026-10-29 | O6: =IFERROR(IF(VLOOKUP(J6,SOURCE_REGISTRY!$A$2:$E$246,5,FALSE)="","",VLOOKUP(J6,SOURCE_REGISTRY!$A$2:$E$246,5,FALSE)),"") -> https://www.england.nhs.uk/medicines-2/antimicrobial-products-subscription-model/ | P6: Bot-Schutz; Teilnahmebedingungen und aktuelles Verfahren separat pruefen.
A7: M12-V21-GLASS | B7: WHO GLASS | C7: SOURCE_ANCHOR | D7: AMR surveillance source; not a company pipeline or efficacy source. | E7: AMR;ANTIBACTERIAL | F7: ANY | G7: ANY | H7: ANY | I7: M12_POLICY | J7: SRC-V21-GLASS | K7: P1 | L7: CONDITIONAL | M7: ACTIVE | N7: 2026-10-29 | O7: =IFERROR(IF(VLOOKUP(J7,SOURCE_REGISTRY!$A$2:$E$246,5,FALSE)="","",VLOOKUP(J7,SOURCE_REGISTRY!$A$2:$E$246,5,FALSE)),"") -> https://www.who.int/initiatives/glass | P7: Reference source only. No module activation and no live evidence implied.
A8: M12-V21-EARSNET | B8: ECDC EARS-Net | C8: SOURCE_ANCHOR | D8: European AMR surveillance, primarily invasive isolates; not representative of every infection context. | E8: AMR;ANTIBACTERIAL | F8: ANY | G8: ANY | H8: ANY | I8: M12_POLICY | J8: SRC-V21-EARSNET | K8: P1 | L8: CONDITIONAL | M8: ACTIVE | N8: 2026-10-29 | O8: =IFERROR(IF(VLOOKUP(J8,SOURCE_REGISTRY!$A$2:$E$246,5,FALSE)="","",VLOOKUP(J8,SOURCE_REGISTRY!$A$2:$E$246,5,FALSE)),"") -> https://www.ecdc.europa.eu/en/about-us/networks/disease-networks-and-laboratory-networks/ears-net-data | P8: Reference source only. No module activation and no live evidence implied.

Sheet ENTITY_MASTER
A1: entity_id | B1: entity_name | C1: entity_type | D1: aliases | E1: parent_entity_id | F1: group_note | G1: homepage_url | H1: status | I1: provenance_ids | J1: curator_note
A2: CMP-1a25fe5bbff | B2: 60 Degrees Pharmaceuticals Inc | C2: ORGANISATION_UNCLASSIFIED | H2: ACTIVE | I2: PR-RAD-CMP-1a25fe5bbff;PR-ALL-CMP-1a25fe5bbff | J2: ACTIVE = fuer Katalogauswahl freigegeben, nicht Bestaetigung des aktuellen Unternehmens-/Pipeline-Status.
A3: CMP-ed793550845 | B3: A&J Science | C3: ORGANISATION_UNCLASSIFIED | H3: ACTIVE | I3: PR-RAD-CMP-ed793550845;PR-ALL-CMP-ed793550845 | J3: ACTIVE = fuer Katalogauswahl freigegeben, nicht Bestaetigung des aktuellen Unternehmens-/Pipeline-Status.
A4: CMP-b372a79ea29 | B4: AbbVie Inc | C4: PHARMA | G4: https://www.abbvie.com/science/pipeline.html | H4: ACTIVE | I4: PR-RAD-CMP-b372a79ea29;PR-ALL-CMP-b372a79ea29 | J4: ACTIVE = fuer Katalogauswahl freigegeben, nicht Bestaetigung des aktuellen Unternehmens-/Pipeline-Status.
A5: CMP-5e8e018b773 | B5: Abion Inc | C5: ORGANISATION_UNCLASSIFIED | H5: ACTIVE | I5: PR-RAD-CMP-5e8e018b773;PR-ALL-CMP-5e8e018b773 | J5: ACTIVE = fuer Katalogauswahl freigegeben, nicht Bestaetigung des aktuellen Unternehmens-/Pipeline-Status.
A6: CMP-5e80d86ddfe | B6: AbVacc Inc | C6: ORGANISATION_UNCLASSIFIED | H6: ACTIVE | I6: PR-RAD-CMP-5e80d86ddfe;PR-ALL-CMP-5e80d86ddfe | J6: ACTIVE = fuer Katalogauswahl freigegeben, nicht Bestaetigung des aktuellen Unternehmens-/Pipeline-Status.
A7: CMP-a3444927172 | B7: Adimmune Corp | C7: ORGANISATION_UNCLASSIFIED | H7: ACTIVE | I7: PR-RAD-CMP-a3444927172;PR-ALL-CMP-a3444927172 | J7: ACTIVE = fuer Katalogauswahl freigegeben, nicht Bestaetigung des aktuellen Unternehmens-/Pipeline-Status.
A8: ENT-BD-041 | B8: Adjuvant Capital | C8: INVESTOR | H8: ACTIVE | I8: PR-BD-041 | J8: ACTIVE = fuer Katalogauswahl freigegeben, nicht Bestaetigung des aktuellen Unternehmens-/Pipeline-Status.
A9: CMP-b69f0599844 | B9: AIM Vaccine Co Ltd | C9: ORGANISATION_UNCLASSIFIED | H9: ACTIVE | I9: PR-RAD-CMP-b69f0599844;PR-ALL-CMP-b69f0599844 | J9: ACTIVE = fuer Katalogauswahl freigegeben, nicht Bestaetigung des aktuellen Unternehmens-/Pipeline-Status.
A10: CMP-3f23dcf79de | B10: AimMax Therapeutics Inc | C10: ORGANISATION_UNCLASSIFIED | H10: ACTIVE | I10: PR-RAD-CMP-3f23dcf79de;PR-ALL-CMP-3f23dcf79de | J10: ACTIVE = fuer Katalogauswahl freigegeben, nicht Bestaetigung des aktuellen Unternehmens-/Pipeline-Status.
A11: CMP-d30edde7435 | B11: Akagera Medicines Inc | C11: ORGANISATION_UNCLASSIFIED | H11: ACTIVE | I11: PR-RAD-CMP-d30edde7435;PR-ALL-CMP-d30edde7435 | J11: ACTIVE = fuer Katalogauswahl freigegeben, nicht Bestaetigung des aktuellen Unternehmens-/Pipeline-Status.
A12: CMP-4146497d3c7 | B12: Aligos Therapeutics Inc | C12: BIOTECH | G12: https://aligos.com/science/scientific-overview/ | H12: ACTIVE | I12: PR-RAD-CMP-4146497d3c7;PR-ALL-CMP-4146497d3c7 | J12: ACTIVE = fuer Katalogauswahl freigegeben, nicht Bestaetigung des aktuellen Unternehmens-/Pipeline-Status.
A13: CMP-1230b627b39 | B13: Alopexx Inc | C13: ORGANISATION_UNCLASSIFIED | H13: ACTIVE | I13: PR-RAD-CMP-1230b627b39;PR-ALL-CMP-1230b627b39 | J13: ACTIVE = fuer Katalogauswahl freigegeben, nicht Bestaetigung des aktuellen Unternehmens-/Pipeline-Status.
A14: ENT-BD-039 | B14: AMR Action Fund | C14: INVESTOR | G14: https://www.amractionfund.com/ | H14: ACTIVE | I14: PR-BD-039 | J14: Investor-Rolle getrennt vom Unternehmens-/Asset-Radar.
A15: CMP-42c932e38d3 | B15: Antabio | C15: BIOTECH | D15: Antabio SAS | H15: ACTIVE | I15: PR-RAD-CMP-42c932e38d3;PR-BD-027;PR-ALL-CMP-42c932e38d3 | J15: ACTIVE = fuer Katalogauswahl freigegeben, nicht Bestaetigung des aktuellen Unternehmens-/Pipeline-Status.
A16: CMP-a013038a1b4 | B16: Archivel Farma SL | C16: ORGANISATION_UNCLASSIFIED | H16: ACTIVE | I16: PR-RAD-CMP-a013038a1b4;PR-ALL-CMP-a013038a1b4 | J16: ACTIVE = fuer Katalogauswahl freigegeben, nicht Bestaetigung des aktuellen Unternehmens-/Pipeline-Status.
A17: CMP-1a319a119c8 | B17: Arcturus Therapeutics | C17: BIOTECH | H17: ACTIVE | I17: PR-BD-033;PR-ALL-CMP-1a319a119c8 | J17: ACTIVE = fuer Katalogauswahl freigegeben, nicht Bestaetigung des aktuellen Unternehmens-/Pipeline-Status.
A18: CMP-cdc8013144b | B18: AriBioLab Co Ltd | C18: ORGANISATION_UNCLASSIFIED | H18: ACTIVE | I18: PR-RAD-CMP-cdc8013144b;PR-ALL-CMP-cdc8013144b | J18: ACTIVE = fuer Katalogauswahl freigegeben, nicht Bestaetigung des aktuellen Unternehmens-/Pipeline-Status.
A19: CMP-3fd58dd38dd | B19: Aridis Pharmaceuticals Inc | C19: BIOTECH | G19: https://www.aridispharma.com/ | H19: ACTIVE | I19: PR-RAD-CMP-3fd58dd38dd;PR-ALL-CMP-3fd58dd38dd | J19: V2.3 official programme scope review. ACTIVE means searchable catalogue row, not confirmation of company status or deal willingness.
A20: CMP-3a0fa1b3462 | B20: Armata Pharmaceuticals | C20: BIOTECH | D20: Armata Pharmaceuticals Inc | G20: https://www.armatapharma.com/ | H20: ACTIVE | I20: PR-RAD-CMP-3a0fa1b3462;PR-ALL-CMP-3a0fa1b3462 | J20: Organisation ist ein Rechercheanker, kein nachgewiesener Lizenznehmer oder aktuelles Asset.
A21: CMP-a8a014d97c6 | B21: ArrePath | C21: ORGANISATION_UNCLASSIFIED | H21: ACTIVE | I21: PR-RAD-CMP-a8a014d97c6;PR-ALL-CMP-a8a014d97c6 | J21: ACTIVE = fuer Katalogauswahl freigegeben, nicht Bestaetigung des aktuellen Unternehmens-/Pipeline-Status.
A22: CMP-c650577a6ad | B22: Arrowsmith Inc | C22: ORGANISATION_UNCLASSIFIED | H22: ACTIVE | I22: PR-RAD-CMP-c650577a6ad;PR-ALL-CMP-c650577a6ad | J22: ACTIVE = fuer Katalogauswahl freigegeben, nicht Bestaetigung des aktuellen Unternehmens-/Pipeline-Status.
A23: ENT-BD-009 | B23: Asahi Kasei Therapeutics (group route) | C23: CORPORATE_ROUTE | D23: Asahi Kasei / Veloxis;Asahi Kasei / Veloxis (BD-Gruppeneinstieg) | F23: Marken-/Gruppeneinstieg, nicht einzelne juristische Einheit; keine automatische Verschmelzung mit AiCuris/Veloxis. | G23: https://www.aktx.com/ | H23: REVIEW | I23: PR-BD-009 | J23: ACTIVE = fuer Katalogauswahl freigegeben, nicht Bestaetigung des aktuellen Unternehmens-/Pipeline-Status.
A24: CMP-c5c2748c797 | B24: Asia Scientific Global | C24: ORGANISATION_UNCLASSIFIED | H24: ACTIVE | I24: PR-RAD-CMP-c5c2748c797;PR-ALL-CMP-c5c2748c797 | J24: ACTIVE = fuer Katalogauswahl freigegeben, nicht Bestaetigung des aktuellen Unternehmens-/Pipeline-Status.
A25: CMP-37b3da7d795 | B25: Assembly Biosciences | C25: BIOTECH | H25: ACTIVE | I25: PR-BD-034;PR-ALL-CMP-37b3da7d795 | J25: ACTIVE = fuer Katalogauswahl freigegeben, nicht Bestaetigung des aktuellen Unternehmens-/Pipeline-Status.
A26: CMP-85e7acc8115 | B26: AstraZeneca | C26: PHARMA | D26: AstraZeneca Plc | H26: ACTIVE | I26: PR-RAD-CMP-85e7acc8115;PR-BD-010;PR-ALL-CMP-85e7acc8115 | J26: ACTIVE = fuer Katalogauswahl freigegeben, nicht Bestaetigung des aktuellen Unternehmens-/Pipeline-Status.
A27: CMP-db564be93cb | B27: Atara Biotherapeutics | C27: ORGANISATION_UNCLASSIFIED | H27: ACTIVE | I27: PR-RAD-CMP-db564be93cb;PR-ALL-CMP-db564be93cb | J27: ACTIVE = fuer Katalogauswahl freigegeben, nicht Bestaetigung des aktuellen Unternehmens-/Pipeline-Status.
A28: CMP-68725fd05c9 | B28: Atea Pharmaceuticals | C28: BIOTECH | D28: Atea Pharmaceuticals Inc | H28: ACTIVE | I28: PR-RAD-CMP-68725fd05c9;PR-BD-038;PR-ALL-CMP-68725fd05c9 | J28: ACTIVE = fuer Katalogauswahl freigegeben, nicht Bestaetigung des aktuellen Unternehmens-/Pipeline-Status.
A29: CMP-a5c7a831bb1 | B29: Aurobac Therapeutics SAS | C29: ORGANISATION_UNCLASSIFIED | H29: ACTIVE | I29: PR-RAD-CMP-a5c7a831bb1;PR-ALL-CMP-a5c7a831bb1 | J29: ACTIVE = fuer Katalogauswahl freigegeben, nicht Bestaetigung des aktuellen Unternehmens-/Pipeline-Status.
A30: CMP-6b4f0aaee02 | B30: Austrianni GmbH | C30: ORGANISATION_UNCLASSIFIED | H30: ACTIVE | I30: PR-RAD-CMP-6b4f0aaee02;PR-ALL-CMP-6b4f0aaee02 | J30: ACTIVE = fuer Katalogauswahl freigegeben, nicht Bestaetigung des aktuellen Unternehmens-/Pipeline-Status.
A31: CMP-d048b7e58a6 | B31: Autonomous Therapeutics Inc | C31: ORGANISATION_UNCLASSIFIED | H31: ACTIVE | I31: PR-RAD-CMP-d048b7e58a6;PR-ALL-CMP-d048b7e58a6 | J31: ACTIVE = fuer Katalogauswahl freigegeben, nicht Bestaetigung des aktuellen Unternehmens-/Pipeline-Status.
A32: CMP-0e7071bcdb5 | B32: Aviex Technologies LLC | C32: ORGANISATION_UNCLASSIFIED | H32: ACTIVE | I32: PR-RAD-CMP-0e7071bcdb5;PR-ALL-CMP-0e7071bcdb5 | J32: ACTIVE = fuer Katalogauswahl freigegeben, nicht Bestaetigung des aktuellen Unternehmens-/Pipeline-Status.
A33: CMP-662744fae82 | B33: Bactobio | C33: ORGANISATION_UNCLASSIFIED | H33: ACTIVE | I33: PR-RAD-CMP-662744fae82;PR-ALL-CMP-662744fae82 | J33: ACTIVE = fuer Katalogauswahl freigegeben, nicht Bestaetigung des aktuellen Unternehmens-/Pipeline-Status.
A34: CMP-93148ce3ea6 | B34: Basilea Pharmaceutica | C34: PHARMA | D34: Basilea Pharmaceutica Ltd | H34: ACTIVE | I34: PR-RAD-CMP-93148ce3ea6;PR-BD-007;PR-ALL-CMP-93148ce3ea6 | J34: ACTIVE = fuer Katalogauswahl freigegeben, nicht Bestaetigung des aktuellen Unternehmens-/Pipeline-Status.
A35: CMP-9a50f62c0bf | B35: Bavarian Nordic | C35: PHARMA | D35: Bavarian Nordic AS | H35: ACTIVE | I35: PR-RAD-CMP-9a50f62c0bf;PR-BD-013;PR-ALL-CMP-9a50f62c0bf | J35: ACTIVE = fuer Katalogauswahl freigegeben, nicht Bestaetigung des aktuellen Unternehmens-/Pipeline-Status.
A36: CMP-413f8fd9f55 | B36: Bayer AG | C36: ORGANISATION_UNCLASSIFIED | H36: ACTIVE | I36: PR-RAD-CMP-413f8fd9f55;PR-ALL-CMP-413f8fd9f55 | J36: ACTIVE = fuer Katalogauswahl freigegeben, nicht Bestaetigung des aktuellen Unternehmens-/Pipeline-Status.
A37: CMP-bb2003e8cb6 | B37: Becton, Dickinson and Company | C37: ORGANISATION_UNCLASSIFIED | H37: ACTIVE | I37: PR-RAD-CMP-bb2003e8cb6;PR-ALL-CMP-bb2003e8cb6 | J37: ACTIVE = fuer Katalogauswahl freigegeben, nicht Bestaetigung des aktuellen Unternehmens-/Pipeline-Status.
A38: CMP-ce583ab95df | B38: Beijing Kawin Technology Share-Holding Co Ltd | C38: ORGANISATION_UNCLASSIFIED | H38: ACTIVE | I38: PR-RAD-CMP-ce583ab95df;PR-ALL-CMP-ce583ab95df | J38: ACTIVE = fuer Katalogauswahl freigegeben, nicht Bestaetigung des aktuellen Unternehmens-/Pipeline-Status.
A39: CMP-1441b9ac13e | B39: Beijing Luzhu Biotechnology Co Ltd | C39: ORGANISATION_UNCLASSIFIED | H39: ACTIVE | I39: PR-RAD-CMP-1441b9ac13e;PR-ALL-CMP-1441b9ac13e | J39: ACTIVE = fuer Katalogauswahl freigegeben, nicht Bestaetigung des aktuellen Unternehmens-/Pipeline-Status.
A40: CMP-feb7d44c4f0 | B40: Beijing Minhai Biotechnology Co Ltd | C40: ORGANISATION_UNCLASSIFIED | H40: ACTIVE | I40: PR-RAD-CMP-feb7d44c4f0;PR-ALL-CMP-feb7d44c4f0 | J40: ACTIVE = fuer Katalogauswahl freigegeben, nicht Bestaetigung des aktuellen Unternehmens-/Pipeline-Status.
A41: CMP-c34e195e985 | B41: Beijing Sanroad Biological Products Co Ltd | C41: ORGANISATION_UNCLASSIFIED | H41: ACTIVE | I41: PR-RAD-CMP-c34e195e985;PR-ALL-CMP-c34e195e985 | J41: ACTIVE = fuer Katalogauswahl freigegeben, nicht Bestaetigung des aktuellen Unternehmens-/Pipeline-Status.
A42: CMP-b3f407f932b | B42: Beijing Sinovac Biotech Co Ltd | C42: ORGANISATION_UNCLASSIFIED | H42: ACTIVE | I42: PR-RAD-CMP-b3f407f932b;PR-ALL-CMP-b3f407f932b | J42: ACTIVE = fuer Katalogauswahl freigegeben, nicht Bestaetigung des aktuellen Unternehmens-/Pipeline-Status.
A43: CMP-425a0205bf3 | B43: Bharat Biotech Ltd | C43: BIOTECH | G43: https://www.bharatbiotech.com/product_overview.html | H43: ACTIVE | I43: PR-RAD-CMP-425a0205bf3;PR-ALL-CMP-425a0205bf3 | J43: ACTIVE = fuer Katalogauswahl freigegeben, nicht Bestaetigung des aktuellen Unternehmens-/Pipeline-Status.
A44: CMP-9decd84757e | B44: Biocidium Biopharmaceuticals Inc | C44: ORGANISATION_UNCLASSIFIED | H44: ACTIVE | I44: PR-RAD-CMP-9decd84757e;PR-ALL-CMP-9decd84757e | J44: ACTIVE = fuer Katalogauswahl freigegeben, nicht Bestaetigung des aktuellen Unternehmens-/Pipeline-Status.
A45: CMP-4e3acc2788c | B45: Biological E Ltd | C45: ORGANISATION_UNCLASSIFIED | H45: ACTIVE | I45: PR-RAD-CMP-4e3acc2788c;PR-ALL-CMP-4e3acc2788c | J45: ACTIVE = fuer Katalogauswahl freigegeben, nicht Bestaetigung des aktuellen Unternehmens-/Pipeline-Status.
A46: CMP-3f2e0eccbeb | B46: bioMerieux | C46: ORGANISATION_UNCLASSIFIED | H46: ACTIVE | I46: PR-RAD-CMP-3f2e0eccbeb;PR-ALL-CMP-3f2e0eccbeb | J46: ACTIVE = fuer Katalogauswahl freigegeben, nicht Bestaetigung des aktuellen Unternehmens-/Pipeline-Status.
A47: CMP-59cc13297d8 | B47: BioNet-Asia Co Ltd | C47: ORGANISATION_UNCLASSIFIED | H47: ACTIVE | I47: PR-RAD-CMP-59cc13297d8;PR-ALL-CMP-59cc13297d8 | J47: ACTIVE = fuer Katalogauswahl freigegeben, nicht Bestaetigung des aktuellen Unternehmens-/Pipeline-Status.
A48: CMP-1dc25b959ce | B48: BioNTech | C48: PHARMA | D48: BioNTech SE | H48: ACTIVE | I48: PR-RAD-CMP-1dc25b959ce;PR-BD-011;PR-ALL-CMP-1dc25b959ce | J48: ACTIVE = fuer Katalogauswahl freigegeben, nicht Bestaetigung des aktuellen Unternehmens-/Pipeline-Status.
A49: CMP-bded2171a7f | B49: Biotron Ltd | C49: ORGANISATION_UNCLASSIFIED | H49: ACTIVE | I49: PR-RAD-CMP-bded2171a7f;PR-ALL-CMP-bded2171a7f | J49: ACTIVE = fuer Katalogauswahl freigegeben, nicht Bestaetigung des aktuellen Unternehmens-/Pipeline-Status.
A50: CMP-b82e0112382 | B50: BioVersys | C50: BIOTECH | D50: Bioversys AG | H50: ACTIVE | I50: PR-RAD-CMP-b82e0112382;PR-BD-026;PR-ALL-CMP-b82e0112382 | J50: ACTIVE = fuer Katalogauswahl freigegeben, nicht Bestaetigung des aktuellen Unternehmens-/Pipeline-Status.
A51: CMP-0c333834d33 | B51: Boehringer Ingelheim International GmbH | C51: ORGANISATION_UNCLASSIFIED | H51: ACTIVE | I51: PR-RAD-CMP-0c333834d33;PR-ALL-CMP-0c333834d33 | J51: ACTIVE = fuer Katalogauswahl freigegeben, nicht Bestaetigung des aktuellen Unternehmens-/Pipeline-Status.
A52: ENT-BD-054 | B52: Boehringer Ingelheim Venture Fund | C52: CVC | D52: BIVF | F52: Eigenes Investment-Team, nicht mit Muttergesellschaft zusammenfuehren. | G52: https://www.boehringer-ingelheim.com/ | H52: REVIEW | I52: PR-BD-054 | J52: BIVF-Identitaet behalten; aktuell behauptetes AMR-Mandat nicht aus historischem Deal ableiten.
A53: CMP-6d82459e523 | B53: Bolder Biotechnology Inc | C53: ORGANISATION_UNCLASSIFIED | H53: ACTIVE | I53: PR-RAD-CMP-6d82459e523;PR-ALL-CMP-6d82459e523 | J53: ACTIVE = fuer Katalogauswahl freigegeben, nicht Bestaetigung des aktuellen Unternehmens-/Pipeline-Status.
A54: CMP-c148cfc9d75 | B54: Brandenburg Antiinfektiva GmbH | C54: ORGANISATION_UNCLASSIFIED | H54: ACTIVE | I54: PR-RAD-CMP-c148cfc9d75;PR-ALL-CMP-c148cfc9d75 | J54: ACTIVE = fuer Katalogauswahl freigegeben, nicht Bestaetigung des aktuellen Unternehmens-/Pipeline-Status.
A55: CMP-bebf092fda0 | B55: Brii Biosciences Ltd | C55: BIOTECH | G55: https://briibio.com/en/media/press-release/20261029/ | H55: ACTIVE | I55: PR-RAD-CMP-bebf092fda0;PR-ALL-CMP-bebf092fda0 | J55: ACTIVE = fuer Katalogauswahl freigegeben, nicht Bestaetigung des aktuellen Unternehmens-/Pipeline-Status.
A56: CMP-9f2367b42ec | B56: Bristar Immunotech Biotechnology Co Ltd | C56: ORGANISATION_UNCLASSIFIED | H56: ACTIVE | I56: PR-RAD-CMP-9f2367b42ec;PR-ALL-CMP-9f2367b42ec | J56: ACTIVE = fuer Katalogauswahl freigegeben, nicht Bestaetigung des aktuellen Unternehmens-/Pipeline-Status.
A57: CMP-ea5495c6494 | B57: Bristol-Myers Squibb Co | C57: ORGANISATION_UNCLASSIFIED | H57: ACTIVE | I57: PR-RAD-CMP-ea5495c6494;PR-ALL-CMP-ea5495c6494 | J57: ACTIVE = fuer Katalogauswahl freigegeben, nicht Bestaetigung des aktuellen Unternehmens-/Pipeline-Status.
A58: CMP-9b3f31b82f1 | B58: BugSee | C58: ORGANISATION_UNCLASSIFIED | H58: ACTIVE | I58: PR-RAD-CMP-9b3f31b82f1;PR-ALL-CMP-9b3f31b82f1 | J58: ACTIVE = fuer Katalogauswahl freigegeben, nicht Bestaetigung des aktuellen Unternehmens-/Pipeline-Status.
A59: CMP-add35b11171 | B59: CanSino Biologics Inc | C59: BIOTECH | G59: https://www.cansinotech.com/PipelineAndStrategy | H59: ACTIVE | I59: PR-RAD-CMP-add35b11171;PR-ALL-CMP-add35b11171 | J59: ACTIVE = fuer Katalogauswahl freigegeben, nicht Bestaetigung des aktuellen Unternehmens-/Pipeline-Status.
A60: CMP-33c76a2d988 | B60: Centauri Therapeutics | C60: BIOTECH | H60: ACTIVE | I60: PR-RAD-CMP-33c76a2d988;PR-BD-025;PR-ALL-CMP-33c76a2d988;PR-ALL-CMP-41a54006729 | J60: ACTIVE = fuer Katalogauswahl freigegeben, nicht Bestaetigung des aktuellen Unternehmens-/Pipeline-Status.
A61: CMP-36f899e5b8d | B61: Cepheid | C61: ORGANISATION_UNCLASSIFIED | F61: Danaher Group | H61: ACTIVE | I61: PR-RAD-CMP-36f899e5b8d;PR-ALL-CMP-36f899e5b8d | J61: ACTIVE = fuer Katalogauswahl freigegeben, nicht Bestaetigung des aktuellen Unternehmens-/Pipeline-Status.
A62: CMP-a455fe8ed3b | B62: Changchun Bcht Biotechnology Co Ltd | C62: ORGANISATION_UNCLASSIFIED | H62: ACTIVE | I62: PR-RAD-CMP-a455fe8ed3b;PR-ALL-CMP-a455fe8ed3b | J62: ACTIVE = fuer Katalogauswahl freigegeben, nicht Bestaetigung des aktuellen Unternehmens-/Pipeline-Status.
A63: CMP-dbe4abdb422 | B63: Changzhou Yinsheng Pharmaceutical Co Ltd | C63: ORGANISATION_UNCLASSIFIED | H63: ACTIVE | I63: PR-RAD-CMP-dbe4abdb422;PR-ALL-CMP-dbe4abdb422 | J63: ACTIVE = fuer Katalogauswahl freigegeben, nicht Bestaetigung des aktuellen Unternehmens-/Pipeline-Status.
A64: CMP-ce1905883b7 | B64: Chengdu Anyong Dingye Biotechnology Co Ltd | C64: ORGANISATION_UNCLASSIFIED | H64: ACTIVE | I64: PR-RAD-CMP-ce1905883b7;PR-ALL-CMP-ce1905883b7 | J64: ACTIVE = fuer Katalogauswahl freigegeben, nicht Bestaetigung des aktuellen Unternehmens-/Pipeline-Status.
A65: CMP-895a161abc0 | B65: Chengdu Keen Biotechnology Co Ltd | C65: ORGANISATION_UNCLASSIFIED | H65: ACTIVE | I65: PR-RAD-CMP-895a161abc0;PR-ALL-CMP-895a161abc0 | J65: ACTIVE = fuer Katalogauswahl freigegeben, nicht Bestaetigung des aktuellen Unternehmens-/Pipeline-Status.
A66: CMP-246ca48d6d7 | B66: Chengdu Olymvax Biopharmaceuticals Inc | C66: ORGANISATION_UNCLASSIFIED | H66: ACTIVE | I66: PR-RAD-CMP-246ca48d6d7;PR-ALL-CMP-246ca48d6d7 | J66: ACTIVE = fuer Katalogauswahl freigegeben, nicht Bestaetigung des aktuellen Unternehmens-/Pipeline-Status.
A67: CMP-89418911969 | B67: Chia Tai Tianqing Pharmaceutical Group Co Ltd | C67: ORGANISATION_UNCLASSIFIED | H67: ACTIVE | I67: PR-RAD-CMP-89418911969;PR-ALL-CMP-89418911969 | J67: ACTIVE = fuer Katalogauswahl freigegeben, nicht Bestaetigung des aktuellen Unternehmens-/Pipeline-Status.
A68: CMP-cc9fc6ac0ff | B68: Chongqing Zhifei Biological Products Co Ltd | C68: ORGANISATION_UNCLASSIFIED | H68: ACTIVE | I68: PR-RAD-CMP-cc9fc6ac0ff;PR-ALL-CMP-cc9fc6ac0ff | J68: ACTIVE = fuer Katalogauswahl freigegeben, nicht Bestaetigung des aktuellen Unternehmens-/Pipeline-Status.
A69: CMP-6a58fd2de4b | B69: Chugai Pharmaceutical Co Ltd | C69: ORGANISATION_UNCLASSIFIED | H69: ACTIVE | I69: PR-RAD-CMP-6a58fd2de4b;PR-ALL-CMP-6a58fd2de4b | J69: ACTIVE = fuer Katalogauswahl freigegeben, nicht Bestaetigung des aktuellen Unternehmens-/Pipeline-Status.
A70: CMP-104615421c5 | B70: Citius Pharmaceuticals Inc | C70: ORGANISATION_UNCLASSIFIED | H70: ACTIVE | I70: PR-RAD-CMP-104615421c5;PR-ALL-CMP-104615421c5 | J70: ACTIVE = fuer Katalogauswahl freigegeben, nicht Bestaetigung des aktuellen Unternehmens-/Pipeline-Status.
A71: CMP-108641addb6 | B71: City of Hope | C71: ORGANISATION_UNCLASSIFIED | H71: ACTIVE | I71: PR-RAD-CMP-108641addb6;PR-ALL-CMP-108641addb6 | J71: ACTIVE = fuer Katalogauswahl freigegeben, nicht Bestaetigung des aktuellen Unternehmens-/Pipeline-Status.
A72: CMP-410a276e6c6 | B72: Clarametyx Biosciences | C72: BIOTECH | D72: Clarametyx Biosciences Inc | H72: ACTIVE | I72: PR-RAD-CMP-410a276e6c6;PR-BD-023;PR-ALL-CMP-410a276e6c6 | J72: ACTIVE = fuer Katalogauswahl freigegeben, nicht Bestaetigung des aktuellen Unternehmens-/Pipeline-Status.
A73: CMP-58ed874c974 | B73: Clover Biopharmaceuticals Ltd | C73: ORGANISATION_UNCLASSIFIED | H73: ACTIVE | I73: PR-RAD-CMP-58ed874c974;PR-ALL-CMP-58ed874c974 | J73: ACTIVE = fuer Katalogauswahl freigegeben, nicht Bestaetigung des aktuellen Unternehmens-/Pipeline-Status.
A74: CMP-561749078f8 | B74: Codagenix Inc | C74: ORGANISATION_UNCLASSIFIED | H74: ACTIVE | I74: PR-RAD-CMP-561749078f8;PR-ALL-CMP-561749078f8 | J74: ACTIVE = fuer Katalogauswahl freigegeben, nicht Bestaetigung des aktuellen Unternehmens-/Pipeline-Status.
A75: CMP-b226b1ca0a8 | B75: Collaborations Pharmaceuticals Inc | C75: ORGANISATION_UNCLASSIFIED | H75: ACTIVE | I75: PR-RAD-CMP-b226b1ca0a8;PR-ALL-CMP-b226b1ca0a8 | J75: ACTIVE = fuer Katalogauswahl freigegeben, nicht Bestaetigung des aktuellen Unternehmens-/Pipeline-Status.
A76: CMP-38726f0edd0 | B76: ConserV Bioscience Ltd | C76: ORGANISATION_UNCLASSIFIED | H76: ACTIVE | I76: PR-RAD-CMP-38726f0edd0;PR-ALL-CMP-38726f0edd0 | J76: ACTIVE = fuer Katalogauswahl freigegeben, nicht Bestaetigung des aktuellen Unternehmens-/Pipeline-Status.
A77: CMP-aedbc6dad69 | B77: Crestone Inc | C77: ORGANISATION_UNCLASSIFIED | H77: ACTIVE | I77: PR-RAD-CMP-aedbc6dad69;PR-ALL-CMP-aedbc6dad69 | J77: ACTIVE = fuer Katalogauswahl freigegeben, nicht Bestaetigung des aktuellen Unternehmens-/Pipeline-Status.
A78: CMP-53fd82f1af9 | B78: CSL Ltd | C78: ORGANISATION_UNCLASSIFIED | H78: ACTIVE | I78: PR-RAD-CMP-53fd82f1af9;PR-ALL-CMP-53fd82f1af9 | J78: ACTIVE = fuer Katalogauswahl freigegeben, nicht Bestaetigung des aktuellen Unternehmens-/Pipeline-Status.
A79: CMP-155bfcfe459 | B79: CSL Seqirus | C79: PHARMA | D79: Seqirus Ltd | E79: CMP-53fd82f1af9 | F79: Quellfeld Gruppe;keine Aliasverschmelzung: CSL Limited;Seqirus;Separater Katalogeintrag trotz Konzernbezug;Rechte-/Teamzuordnung live pruefen. | G79: https://www.cslseqirus.us/ | H79: ACTIVE | I79: PR-RAD-CMP-155bfcfe459;PR-BD-020;PR-ALL-CMP-155bfcfe459 | J79: ACTIVE = fuer Katalogauswahl freigegeben, nicht Bestaetigung des aktuellen Unternehmens-/Pipeline-Status.
A80: CMP-c132e3a36c6 | B80: CSPC Pharmaceutical Group Ltd | C80: ORGANISATION_UNCLASSIFIED | H80: ACTIVE | I80: PR-RAD-CMP-c132e3a36c6;PR-ALL-CMP-c132e3a36c6 | J80: ACTIVE = fuer Katalogauswahl freigegeben, nicht Bestaetigung des aktuellen Unternehmens-/Pipeline-Status.
A81: CMP-e0fa5955eec | B81: Debiopharm International | C81: ORGANISATION_UNCLASSIFIED | H81: ACTIVE | I81: PR-RAD-CMP-e0fa5955eec;PR-ALL-CMP-e0fa5955eec | J81: ACTIVE = fuer Katalogauswahl freigegeben, nicht Bestaetigung des aktuellen Unternehmens-/Pipeline-Status.
A82: CMP-4cdbd28fa00 | B82: Disperazol Pharma | C82: ORGANISATION_UNCLASSIFIED | H82: ACTIVE | I82: PR-RAD-CMP-4cdbd28fa00;PR-ALL-CMP-4cdbd28fa00 | J82: ACTIVE = fuer Katalogauswahl freigegeben, nicht Bestaetigung des aktuellen Unternehmens-/Pipeline-Status.
A83: CMP-6dcf8867166 | B83: Drugs for Neglected Diseases initiative | C83: NONPROFIT | D83: Drugs for Neglected Diseases initiative | G83: https://dndi.org/ | H83: ACTIVE | I83: PR-RAD-CMP-6dcf8867166;PR-ALL-CMP-6dcf8867166;PR-V2-CMP-6dcf8867166 | J83: V2.3 official programme scope review. ACTIVE means searchable catalogue row, not confirmation of company status or deal willingness.
A84: CMP-2297c0d2f25 | B84: Dynavax Technologies Corp | C84: ORGANISATION_UNCLASSIFIED | H84: ACTIVE | I84: PR-RAD-CMP-2297c0d2f25;PR-ALL-CMP-2297c0d2f25 | J84: ACTIVE = fuer Katalogauswahl freigegeben, nicht Bestaetigung des aktuellen Unternehmens-/Pipeline-Status.
A85: ENT-BD-048 | B85: Easton Capital | C85: INVESTOR | H85: ACTIVE | I85: PR-BD-048 | J85: ACTIVE = fuer Katalogauswahl freigegeben, nicht Bestaetigung des aktuellen Unternehmens-/Pipeline-Status.
A86: CMP-3f15ddb6b50 | B86: Eisai Co Ltd | C86: ORGANISATION_UNCLASSIFIED | H86: ACTIVE | I86: PR-RAD-CMP-3f15ddb6b50;PR-ALL-CMP-3f15ddb6b50 | J86: ACTIVE = fuer Katalogauswahl freigegeben, nicht Bestaetigung des aktuellen Unternehmens-/Pipeline-Status.
A87: CMP-3d4eedeeed7 | B87: Eli Lilly | C87: PHARMA | F87: Quellfeld Gruppe;keine Aliasverschmelzung: Lilly;Curevo;LimmaTech Biologics;Vaccine Company | H87: ACTIVE | I87: PR-BD-008;PR-ALL-CMP-3d4eedeeed7 | J87: ACTIVE = fuer Katalogauswahl freigegeben, nicht Bestaetigung des aktuellen Unternehmens-/Pipeline-Status.
A88: CMP-ebec5cdb20c | B88: Elion Therapeutics | C88: BIOTECH | H88: ACTIVE | I88: PR-BD-030;PR-ALL-CMP-ebec5cdb20c | J88: ACTIVE = fuer Katalogauswahl freigegeben, nicht Bestaetigung des aktuellen Unternehmens-/Pipeline-Status.
A89: CMP-a192e827864 | B89: Emergent BioSolutions Inc | C89: ORGANISATION_UNCLASSIFIED | H89: ACTIVE | I89: PR-RAD-CMP-a192e827864;PR-ALL-CMP-a192e827864 | J89: ACTIVE = fuer Katalogauswahl freigegeben, nicht Bestaetigung des aktuellen Unternehmens-/Pipeline-Status.
A90: ENT-BD-055 | B90: EQT Life Sciences | C90: INVESTOR | D90: LSP;EQT Life Sciences | H90: ACTIVE | I90: PR-BD-055 | J90: ACTIVE = fuer Katalogauswahl freigegeben, nicht Bestaetigung des aktuellen Unternehmens-/Pipeline-Status.
A91: CMP-3f19c5bc4ac | B91: Eubiologics Co Ltd | C91: ORGANISATION_UNCLASSIFIED | H91: ACTIVE | I91: PR-RAD-CMP-3f19c5bc4ac;PR-ALL-CMP-3f19c5bc4ac | J91: ACTIVE = fuer Katalogauswahl freigegeben, nicht Bestaetigung des aktuellen Unternehmens-/Pipeline-Status.
A92: CMP-c2df97c26fd | B92: Excision BioTherapeutics | C92: ORGANISATION_UNCLASSIFIED | H92: ACTIVE | I92: PR-RAD-CMP-c2df97c26fd;PR-ALL-CMP-c2df97c26fd | J92: ACTIVE = fuer Katalogauswahl freigegeben, nicht Bestaetigung des aktuellen Unternehmens-/Pipeline-Status.
A93: CMP-6f9f822213f | B93: EyeGene Inc | C93: ORGANISATION_UNCLASSIFIED | H93: ACTIVE | I93: PR-RAD-CMP-6f9f822213f;PR-ALL-CMP-6f9f822213f | J93: ACTIVE = fuer Katalogauswahl freigegeben, nicht Bestaetigung des aktuellen Unternehmens-/Pipeline-Status.
A94: ENT-BD-053 | B94: F-Prime Capital | C94: INVESTOR | H94: ACTIVE | I94: PR-BD-053 | J94: ACTIVE = fuer Katalogauswahl freigegeben, nicht Bestaetigung des aktuellen Unternehmens-/Pipeline-Status.
A95: CMP-b3350328f73 | B95: F2G | C95: BIOTECH | D95: F2G Ltd | H95: ACTIVE | I95: PR-RAD-CMP-b3350328f73;PR-BD-028;PR-ALL-CMP-b3350328f73 | J95: ACTIVE = fuer Katalogauswahl freigegeben, nicht Bestaetigung des aktuellen Unternehmens-/Pipeline-Status.
A96: CMP-1c39dd558a2 | B96: Ferring Pharmaceuticals | C96: PHARMA | F96: Ferring Group | G96: https://www.ferring.com/ | H96: ACTIVE | I96: PR-RAD-CMP-1c39dd558a2;PR-ALL-CMP-1c39dd558a2 | J96: Organisation ist ein Rechercheanker, kein nachgewiesener Lizenznehmer oder aktuelles Asset.
A97: ENT-BD-042 | B97: Forbion | C97: INVESTOR | H97: ACTIVE | I97: PR-BD-042 | J97: ACTIVE = fuer Katalogauswahl freigegeben, nicht Bestaetigung des aktuellen Unternehmens-/Pipeline-Status.
A98: CMP-9b5b6eb5241 | B98: Frontier Biotechnologies Inc | C98: ORGANISATION_UNCLASSIFIED | H98: ACTIVE | I98: PR-RAD-CMP-9b5b6eb5241;PR-ALL-CMP-9b5b6eb5241 | J98: ACTIVE = fuer Katalogauswahl freigegeben, nicht Bestaetigung des aktuellen Unternehmens-/Pipeline-Status.
A99: CMP-5756f6656b7 | B99: GC Biopharma Corp | C99: ORGANISATION_UNCLASSIFIED | H99: ACTIVE | I99: PR-RAD-CMP-5756f6656b7;PR-ALL-CMP-5756f6656b7 | J99: ACTIVE = fuer Katalogauswahl freigegeben, nicht Bestaetigung des aktuellen Unternehmens-/Pipeline-Status.
A100: CMP-4b7ea901498 | B100: GeneCure Biotechnologies LLC | C100: ORGANISATION_UNCLASSIFIED | H100: ACTIVE | I100: PR-RAD-CMP-4b7ea901498;PR-ALL-CMP-4b7ea901498 | J100: ACTIVE = fuer Katalogauswahl freigegeben, nicht Bestaetigung des aktuellen Unternehmens-/Pipeline-Status.
...

Sheet SOURCE_REGISTRY
A1: source_id | B1: source_name | C1: source_type | D1: module_ids | E1: entry_url | F1: access_method | G1: web_check_status | H1: checked_on | I1: langdock_access | J1: use_scope | K1: rights_scope | L1: access_note | M1: review_batch | N1: api_endpoint | O1: pagination_rule | P1: source_evidence_type | Q1: content_validation_status | R1: identity_verification_status | S1: canonical_source_id
A2: SRC-DE_FDB | B2: Förderdatenbank Bund / Länder / EU | C2: OFFICIAL_WEB | D2: M05 | E2: https://www.foerderdatenbank.de/FDB/DE/Foerderprogramme/foerderprogramme.html | F2: WEB_TEXT | G2: CONTENT_READ | H2: 2026-10-29 | I2: UNTESTED | J2: FUNDING_ENTRY_ONLY | K2: PUBLIC | L2: [Pilotpruefung uebernommen, nicht erneut vollvalidiert] Einstiegsquelle gelesen; keine einzelnen offenen Calls oder verbindliche Foerderfaehigkeit bestaetigt. | M2: INHERITED_NOT_RECHECKED | P2: OFFICIAL_ORGANISATION_OR_PROGRAMME_CLAIM_UNCHECKED | Q2: INHERITED_NOT_RECHECKED | R2: NO_AUTOMATIC_MISMATCH_DETECTED_NOT_PROOF | S2: SRC-DE_FDB
A3: SRC-EU_FT | B3: EU Funding & Tenders - Calls for Proposals | C3: OFFICIAL_WEB | D3: M05 | E3: https://ec.europa.eu/info/funding-tenders/opportunities/portal/screen/opportunities/calls-for-proposals | F3: DYNAMIC_OR_IMAGE_REVIEW | G3: PARTIAL | H3: 2026-10-29 | I3: UNTESTED | J3: FUNDING_ENTRY_ONLY | K3: PUBLIC | L3: [Pilotpruefung uebernommen, nicht erneut vollvalidiert] Textabruf liefert nur Einstieg/Topic-Link, keine vollstaendige Call-Liste. Separater Connector-/Browser-/API-Test erforderlich. | M3: INHERITED_NOT_RECHECKED | P3: OFFICIAL_ORGANISATION_OR_PROGRAMME_CLAIM_UNCHECKED | Q3: INHERITED_NOT_RECHECKED | R3: NO_AUTOMATIC_MISMATCH_DETECTED_NOT_PROOF | S3: SRC-EU_FT
A4: SRC-DE_FORTRA | B4: EKFS / ForTra Translatorik | C4: OFFICIAL_WEB | D4: M05 | E4: https://ekfs.de/wissenschaftliche-foerderung/Translatorik-ForTra/Foerderverfahren | F4: WEB_TEXT | G4: CONTENT_READ | H4: 2026-10-29 | I4: UNTESTED | J4: FUNDING_ENTRY_ONLY | K4: PUBLIC | L4: [Pilotpruefung uebernommen, nicht erneut vollvalidiert] Programmprofil gelesen; Antragstellereignung und Ausschreibungsbedingungen je Antrag erneut pruefen. | M4: INHERITED_NOT_RECHECKED | P4: OFFICIAL_ORGANISATION_OR_PROGRAMME_CLAIM_UNCHECKED | Q4: INHERITED_NOT_RECHECKED | R4: NO_AUTOMATIC_MISMATCH_DETECTED_NOT_PROOF | S4: SRC-DE_FORTRA
A5: SRC-GL_CARBX | B5: CARB-X | C5: OFFICIAL_WEB | D5: M05 | E5: https://carb-x.org/apply/funding-themes/ | F5: DYNAMIC_OR_IMAGE_REVIEW | G5: PARTIAL | H5: 2026-10-29 | I5: UNTESTED | J5: FUNDING_ENTRY_ONLY | K5: PUBLIC | L5: [Pilotpruefung uebernommen, nicht erneut vollvalidiert] 2026 Funding Themes bestaetigt; Themen teilweise bildbasiert. Keine Call-Eligibility oder Deadlines geprueft. | M5: INHERITED_NOT_RECHECKED | P5: OFFICIAL_ORGANISATION_OR_PROGRAMME_CLAIM_UNCHECKED | Q5: INHERITED_NOT_RECHECKED | R5: NO_AUTOMATIC_MISMATCH_DETECTED_NOT_PROOF | S5: SRC-GL_CARBX
A6: SRC-GL_CEPI | B6: CEPI Calls for Proposals | C6: OFFICIAL_WEB | D6: M05 | E6: https://cepi.net/calls-for-proposals | F6: WEB_TEXT | G6: CONTENT_READ | H6: 2026-10-29 | I6: UNTESTED | J6: FUNDING_ENTRY_ONLY | K6: PUBLIC | L6: [Pilotpruefung uebernommen, nicht erneut vollvalidiert] Programmkontext: Impfstoffe und Tools gegen epidemische/pandemische Bedrohungen; keine allgemeine Impfstofffoerderung zusagen. | M6: INHERITED_NOT_RECHECKED | P6: OFFICIAL_ORGANISATION_OR_PROGRAMME_CLAIM_UNCHECKED | Q6: INHERITED_NOT_RECHECKED | R6: NO_AUTOMATIC_MISMATCH_DETECTED_NOT_PROOF | S6: SRC-GL_CEPI
A7: SRC-REG_NW | B7: Innovationsförderagentur NRW - Maßnahmen | C7: OFFICIAL_WEB | D7: M05 | E7: https://www.in.nrw/massnahmen | F7: WEB_TEXT | G7: CONTENT_READ | H7: 2026-10-29 | I7: UNTESTED | J7: FUNDING_ENTRY_ONLY | K7: PUBLIC | L7: [Pilotpruefung uebernommen, nicht erneut vollvalidiert] Einstiegsquelle gelesen; keine einzelnen offenen Calls oder verbindliche Foerderfaehigkeit bestaetigt. | M7: INHERITED_NOT_RECHECKED | P7: OFFICIAL_ORGANISATION_OR_PROGRAMME_CLAIM_UNCHECKED | Q7: INHERITED_NOT_RECHECKED | R7: NO_AUTOMATIC_MISMATCH_DETECTED_NOT_PROOF | S7: SRC-REG_NW
A8: SRC-INST_KOELN_FORTUNE | B8: Köln Fortune (Medizinische Fakultät) | C8: OFFICIAL_WEB | D8: M05 | E8: https://medfak.uni-koeln.de/forschung/service-foerderangebote/fakultaetsfoerderungen/koeln-fortune | F8: WEB_TEXT | G8: CONTENT_READ | H8: 2026-10-29 | I8: UNTESTED | J8: FUNDING_ENTRY_ONLY | K8: PUBLIC | L8: [Pilotpruefung uebernommen, nicht erneut vollvalidiert] Personen-/Karrierefoerderung fuer wissenschaftliche Mitarbeitende der Medizinischen Fakultaet; kein universeller CMC-Finanzierungsweg. | M8: INHERITED_NOT_RECHECKED | P8: OFFICIAL_ORGANISATION_OR_PROGRAMME_CLAIM_UNCHECKED | Q8: INHERITED_NOT_RECHECKED | R8: NO_AUTOMATIC_MISMATCH_DETECTED_NOT_PROOF | S8: SRC-INST_KOELN_FORTUNE
A9: SRC-DE_HELMHOLTZ_ENTERPRISE | B9: Helmholtz Enterprise | C9: OFFICIAL_WEB | D9: M05 | E9: https://www.helmholtz.de/transfer/innovations-und-foerderprogramme/helmholtz-enterprise/ | F9: WEB_TEXT | G9: CONTENT_READ | H9: 2026-10-29 | I9: UNTESTED | J9: FUNDING_ENTRY_ONLY | K9: PUBLIC | L9: [Pilotpruefung uebernommen, nicht erneut vollvalidiert] Institution und Gruendungskontext gemeinsam pruefen; SPINOUT allein reicht nicht. | M9: INHERITED_NOT_RECHECKED | P9: OFFICIAL_ORGANISATION_OR_PROGRAMME_CLAIM_UNCHECKED | Q9: INHERITED_NOT_RECHECKED | R9: NO_AUTOMATIC_MISMATCH_DETECTED_NOT_PROOF | S9: SRC-DE_HELMHOLTZ_ENTERPRISE
A10: SRC-GSK-PIPE | B10: GSK Pipeline | C10: OFFICIAL_WEB | D10: M01 | E10: https://www.gsk.com/en-gb/innovation/pipeline/ | F10: WEB_PLUS_DOWNLOAD | G10: PARTIAL | H10: 2026-10-29 | I10: UNTESTED | J10: COMPANY_SCOPE_ONLY | K10: PUBLIC | L10: [Pilotpruefung uebernommen, nicht erneut vollvalidiert] Pipeline-Seite und XLSX-Verweis vorhanden. HTML enthaelt nicht zwingend alle Assetzeilen; keine Asset-Level-Validierung. | M10: INHERITED_NOT_RECHECKED | P10: OFFICIAL_ORGANISATION_OR_PROGRAMME_CLAIM_UNCHECKED | Q10: INHERITED_NOT_RECHECKED | R10: NO_AUTOMATIC_MISMATCH_DETECTED_NOT_PROOF | S10: SRC-GSK-PIPE
A11: SRC-PFIZER-PIPE | B11: Pfizer Pipeline | C11: OFFICIAL_WEB | D11: M01 | E11: https://www.pfizer.com/science/drug-product-pipeline | F11: WEB_PLUS_DOWNLOAD | G11: PARTIAL | H11: 2026-10-29 | I11: UNTESTED | J11: COMPANY_SCOPE_ONLY | K11: PUBLIC | L11: [Pilotpruefung uebernommen, nicht erneut vollvalidiert] Interaktive Pipeline; keine vollstaendige Extraktion/Phase-Verifikation erfolgt. | M11: INHERITED_NOT_RECHECKED | P11: OFFICIAL_ORGANISATION_OR_PROGRAMME_CLAIM_UNCHECKED | Q11: INHERITED_NOT_RECHECKED | R11: NO_AUTOMATIC_MISMATCH_DETECTED_NOT_PROOF | S11: SRC-PFIZER-PIPE
A12: SRC-INFEX-TEXT | B12: Infex: Pipeline- und Finanzierungsmitteilung 2026-05-12 | C12: OFFICIAL_WEB | D12: M01;M06;M07 | E12: https://www.infextx.com/infex-therapeutics-secures-4-3-million-funding-to-advance-anti-infective-pipeline-targeting-drug-resistant-infections/ | F12: WEB_TEXT | G12: CONTENT_READ | H12: 2026-10-29 | I12: UNTESTED | J12: COMPANY_AND_PROGRAM_SCOPE | K12: PUBLIC | L12: [Pilotpruefung uebernommen, nicht erneut vollvalidiert] Lesbarer Primaertext als Suchstart. M01 und M06 teilen denselben Abruf. Ereignisdatum 2026-05-12, kein Nachweis unveraenderten Status am 2026-10-29. | M12: INHERITED_NOT_RECHECKED | P12: PRESS_RELEASE | Q12: INHERITED_NOT_RECHECKED | R12: NO_AUTOMATIC_MISMATCH_DETECTED_NOT_PROOF | S12: SRC-INFEX-TEXT
A13: SRC-VIIV | B13: ViiV: Pipeline-Einstieg | C13: OFFICIAL_WEB | D13: M01 | E13: https://viivhcmedinfo.com/our-pipeline/ | F13: DYNAMIC_WEB | G13: CONTENT_READ | H13: 2026-10-29 | I13: UNTESTED | J13: NOT_VALIDATED | K13: PUBLIC | L13: [Pilotpruefung uebernommen, nicht erneut vollvalidiert] URL im Webtool nicht abrufbar. Als REVIEW-Quelle behalten; GSK-Seite bestaetigt HIV/JV-Kontext, nicht diesen technischen Zugang. | M13: V2_1_RISK_BASED_REVIEW | P13: OFFICIAL_ORGANISATION_OR_PROGRAMME_CLAIM_UNCHECKED | Q13: SCOPE_READ_THIS_REVISION | R13: NO_AUTOMATIC_MISMATCH_DETECTED_NOT_PROOF | S13: SRC-VIIV
... A22: SRC-HTGF-TECREGEN | B22: HTGF: TECregen Seed Financing | C22: OFFICIAL_WEB | D22: M06;M07 | E22: https://www.htgf.de/tecregen-seed-financing/ | F22: WEB_TEXT | G22: SEARCH_TEXT_READ | H22: 2026-10-29 | I22: UNTESTED | J22: SOURCE_MISMATCH_AUDIT | K22: PUBLIC | L22: [Pilotpruefung uebernommen, nicht erneut vollvalidiert] Primaermeldung betrifft TECregen/Thymusregeneration, nicht Centauri. Auditquelle, kein aktiver AMR-Rechercheauftrag. | M22: INHERITED_NOT_RECHECKED | P22: PRESS_RELEASE | Q22: INHERITED_NOT_RECHECKED | R22: NO_AUTOMATIC_MISMATCH_DETECTED_NOT_PROOF | S22: SRC-HTGF-TECREGEN
A23: SRC-NAME-SEARCH | B23: Namensbasierte Primaerquellensuche | C23: SEARCH_STRATEGY | D23: M01;M06;M07 | F23: WEB_SEARCH | G23: NOT_CHECKED | I23: UNTESTED | J23: DISCOVER_PRIMARY_SOURCE | K23: PUBLIC | L23: Kein URL erfunden. Exakten Organisationsnamen und Kontext verwenden; jede Organisation braucht einen eigenen Suchschluessel. Suchtreffer sind noch kein fachlicher Befund. | M23: INHERITED_NOT_RECHECKED | P23: NAME_SEARCH_HINT | Q23: INHERITED_NOT_RECHECKED | R23: NAME_ONLY | S23: SRC-NAME-SEARCH
A24: SRC-GLOBALDATA-202607 | B24: GlobalData / Nutzer-Snapshot 31.07.2026 | C24: LICENSED_SNAPSHOT | D24: M01 | E24: http://pharma.globaldata.com/ | F24: LICENSED_DATA | G24: NOT_CHECKED | I24: UNTESTED | J24: HISTORICAL_AUDIT_ONLY | K24: LICENSE_REVIEW_REQUIRED | L24: Herkunft aus gelieferten Radar-Tabellen. Keine automatische Zugriffsberechtigung, keine aktuelle Phase. Nicht als freien Live-Abruf einplanen. | M24: INHERITED_NOT_RECHECKED | P24: HISTORICAL_DATABASE_SNAPSHOT | Q24: INHERITED_NOT_RECHECKED | R24: HISTORICAL_LICENSED | S24: SRC-GLOBALDATA-202607
A25: SRC-DE_BMFTR_HEALTH | B25: BMFTR Gesundheitsforschung - Bekanntmachungen | C25: OFFICIAL_WEB | D25: M05 | E25: https://www.gesundheitsforschung-bmftr.de/de/bekanntmachungen-5786.php | F25: WEB_TEXT | G25: NOT_CHECKED | I25: UNTESTED | J25: FUNDING_ENTRY_ONLY | K25: PUBLIC | L25: Aus Nutzerdatei uebernommen; URL und aktueller Inhalt nicht in diesem Vollimport live verifiziert. | M25: INHERITED_NOT_RECHECKED | P25: OFFICIAL_ORGANISATION_OR_PROGRAMME_CLAIM_UNCHECKED | Q25: INHERITED_NOT_RECHECKED | R25: NO_AUTOMATIC_MISMATCH_DETECTED_NOT_PROOF | S25: SRC-DE_BMFTR_HEALTH
A26: SRC-DE_DFG | B26: DFG Förderprogramme | C26: OFFICIAL_WEB | D26: M05 | E26: https://www.dfg.de/de/foerderung/foerdermoeglichkeiten/programme | F26: WEB_TEXT | G26: NOT_CHECKED | I26: UNTESTED | J26: FUNDING_ENTRY_ONLY | K26: PUBLIC | L26: Aus Nutzerdatei uebernommen; URL und aktueller Inhalt nicht in diesem Vollimport live verifiziert. | M26: INHERITED_NOT_RECHECKED | P26: OFFICIAL_ORGANISATION_OR_PROGRAMME_CLAIM_UNCHECKED | Q26: INHERITED_NOT_RECHECKED | R26: NO_AUTOMATIC_MISMATCH_DETECTED_NOT_PROOF | S26: SRC-DE_DFG
A27: SRC-DE_DFG_CLINICAL | B27: DFG Klinische Studien | C27: OFFICIAL_WEB | D27: M05 | E27: https://www.dfg.de/de/foerderung/foerdermoeglichkeiten/programme/einzelfoerderung/klinische-studien | F27: WEB_TEXT | G27: NOT_CHECKED | I27: UNTESTED | J27: FUNDING_ENTRY_ONLY | K27: PUBLIC | L27: Aus Nutzerdatei uebernommen; URL und aktueller Inhalt nicht in diesem Vollimport live verifiziert. | M27: INHERITED_NOT_RECHECKED | P27: OFFICIAL_ORGANISATION_OR_PROGRAMME_CLAIM_UNCHECKED | Q27: INHERITED_NOT_RECHECKED | R27: NO_AUTOMATIC_MISMATCH_DETECTED_NOT_PROOF | S27: SRC-DE_DFG_CLINICAL
A28: SRC-DE_EKFS_CALLS | B28: EKFS Ausschreibungskalender | C28: OFFICIAL_WEB | D28: M05 | E28: https://ekfs.de/en/current-topics/funding-application-calender | F28: WEB_TEXT | G28: NOT_CHECKED | I28: UNTESTED | J28: FUNDING_ENTRY_ONLY | K28: PUBLIC | L28: Aus Nutzerdatei uebernommen; URL und aktueller Inhalt nicht in diesem Vollimport live verifiziert. | M28: INHERITED_NOT_RECHECKED | P28: OFFICIAL_ORGANISATION_OR_PROGRAMME_CLAIM_UNCHECKED | Q28: INHERITED_NOT_RECHECKED | R28: NO_AUTOMATIC_MISMATCH_DETECTED_NOT_PROOF | S28: SRC-DE_EKFS_CALLS
A29: SRC-DE_GO_BIO | B29: GO-Bio next | C29: OFFICIAL_WEB | D29: M05 | E29: https://www.foerderdatenbank.de/FDB/Content/DE/Foerderprogramm/Bund/BMBF/go-bio-next.html | F29: WEB_TEXT | G29: NOT_CHECKED | I29: UNTESTED | J29: FUNDING_ENTRY_ONLY | K29: PUBLIC | L29: Aus Nutzerdatei uebernommen; URL und aktueller Inhalt nicht in diesem Vollimport live verifiziert. | M29: INHERITED_NOT_RECHECKED | P29: OFFICIAL_ORGANISATION_OR_PROGRAMME_CLAIM_UNCHECKED | Q29: INHERITED_NOT_RECHECKED | R29: NO_AUTOMATIC_MISMATCH_DETECTED_NOT_PROOF | S29: SRC-DE_GO_BIO
A30: SRC-DE_KMU_BIOMED | B30: KMU-innovativ Biomedizin | C30: OFFICIAL_WEB | D30: M05 | E30: https://www.foerderdatenbank.de/FDB/Content/DE/Foerderprogramm/Bund/BMBF/biomedizin.html | F30: WEB_TEXT | G30: NOT_CHECKED | I30: UNTESTED | J30: FUNDING_ENTRY_ONLY | K30: PUBLIC | L30: Aus Nutzerdatei uebernommen; URL und aktueller Inhalt nicht in diesem Vollimport live verifiziert. | M30: INHERITED_NOT_RECHECKED | P30: OFFICIAL_ORGANISATION_OR_PROGRAMME_CLAIM_UNCHECKED | Q30: INHERITED_NOT_RECHECKED | R30: NO_AUTOMATIC_MISMATCH_DETECTED_NOT_PROOF | S30: SRC-DE_KMU_BIOMED
A31: SRC-DE_ZIM | B31: ZIM - Zentrales Innovationsprogramm Mittelstand | C31: OFFICIAL_WEB | D31: M05 | E31: https://www.zim.de/ | F31: WEB_TEXT | G31: NOT_CHECKED | I31: UNTESTED | J31: FUNDING_ENTRY_ONLY | K31: PUBLIC | L31: Aus Nutzerdatei uebernommen; URL und aktueller Inhalt nicht in diesem Vollimport live verifiziert. | M31: INHERITED_NOT_RECHECKED | P31: OFFICIAL_ORGANISATION_OR_PROGRAMME_CLAIM_UNCHECKED | Q31: INHERITED_NOT_RECHECKED | R31: NO_AUTOMATIC_MISMATCH_DETECTED_NOT_PROOF | S31: SRC-DE_ZIM
A32: SRC-DE_EXIST | B32: EXIST | C32: OFFICIAL_WEB | D32: M05 | E32: https://www.exist.de/ | F32: WEB_TEXT | G32: NOT_CHECKED | I32: UNTESTED | J32: FUNDING_ENTRY_ONLY | K32: PUBLIC | L32: Aus Nutzerdatei uebernommen; URL und aktueller Inhalt nicht in diesem Vollimport live verifiziert. | M32: INHERITED_NOT_RECHECKED | P32: OFFICIAL_ORGANISATION_OR_PROGRAMME_CLAIM_UNCHECKED | Q32: INHERITED_NOT_RECHECKED | R32: NO_AUTOMATIC_MISMATCH_DETECTED_NOT_PROOF | S32: SRC-DE_EXIST
A33: SRC-DE_VW_STIFTUNG | B33: VolkswagenStiftung - Förderangebote | C33: OFFICIAL_WEB | D33: M05 | E33: https://www.volkswagenstiftung.de/de/foerderung | F33: WEB_TEXT | G33: NOT_CHECKED | I33: UNTESTED | J33: FUNDING_ENTRY_ONLY | K33: PUBLIC | L33: Aus Nutzerdatei uebernommen; URL und aktueller Inhalt nicht in diesem Vollimport live verifiziert. | M33: INHERITED_NOT_RECHECKED | P33: OFFICIAL_ORGANISATION_OR_PROGRAMME_CLAIM_UNCHECKED | Q33: INHERITED_NOT_RECHECKED | R33: NO_AUTOMATIC_MISMATCH_DETECTED_NOT_PROOF | S33: SRC-DE_VW_STIFTUNG
A34: SRC-DE_DZIF_INTERNAL | B34: DZIF interne Projekt- und Transferförderung | C34: OFFICIAL_WEB | D34: M05 | E34: https://www.dzif.de/ | F34: PUBLIC_PLUS_INTERNAL | G34: NOT_CHECKED | I34: UNTESTED | J34: FUNDING_ENTRY_ONLY | K34: PUBLIC | L34: Oeffentlicher Einstieg reicht fuer interne Ausschreibungen nicht aus; internen Zugriff gesondert bereitstellen. | M34: INHERITED_NOT_RECHECKED | P34: OFFICIAL_ORGANISATION_OR_PROGRAMME_CLAIM_UNCHECKED | Q34: INHERITED_NOT_RECHECKED | R34: NO_AUTOMATIC_MISMATCH_DETECTED_NOT_PROOF | S34: SRC-DE_DZIF_INTERNAL
A35: SRC-DE_HELMHOLTZ_TRANSFER | B35: Helmholtz Innovations- und Transferprogramme | C35: OFFICIAL_WEB | D35: M05 | E35: https://www.helmholtz.de/transfer/innovations-und-foerderprogramme | F35: WEB_TEXT | G35: NOT_CHECKED | I35: UNTESTED | J35: FUNDING_ENTRY_ONLY | K35: PUBLIC | L35: Aus Nutzerdatei uebernommen; URL und aktueller Inhalt nicht in diesem Vollimport live verifiziert. | M35: INHERITED_NOT_RECHECKED | P35: OFFICIAL_ORGANISATION_OR_PROGRAMME_CLAIM_UNCHECKED | Q35: INHERITED_NOT_RECHECKED | R35: NO_AUTOMATIC_MISMATCH_DETECTED_NOT_PROOF | S35: SRC-DE_HELMHOLTZ_TRANSFER
... A44: SRC-GL_WELLCOME | B44: Wellcome Funding Schemes | C44: OFFICIAL_WEB | D44: M05 | E44: https://wellcome.org/research-funding/schemes | F44: WEB_TEXT | G44: NOT_CHECKED | I44: UNTESTED | J44: FUNDING_ENTRY_ONLY | K44: PUBLIC | L44: Aus Nutzerdatei uebernommen; URL und aktueller Inhalt nicht in diesem Vollimport live verifiziert. | M44: INHERITED_NOT_RECHECKED | P44: OFFICIAL_ORGANISATION_OR_PROGRAMME_CLAIM_UNCHECKED | Q44: INHERITED_NOT_RECHECKED | R44: NO_AUTOMATIC_MISMATCH_DETECTED_NOT_PROOF | S44: SRC-GL_WELLCOME
A45: SRC-GL_GHIT | B45: Global Health Innovative Technology Fund (GHIT) | C45: OFFICIAL_WEB | D45: M05 | E45: https://www.ghitfund.org/applyforfunding/opportunities | F45: WEB_TEXT | G45: CONTENT_READ | H45: 2026-10-29 | I45: UNTESTED | J45: FUNDING_ENTRY_ONLY | K45: PUBLIC | L45: Partnerschaftsanforderung am 29.10.2026 primaer geprueft; kein konkreter Call bewertet. | M45: INHERITED_NOT_RECHECKED | P45: OFFICIAL_ORGANISATION_OR_PROGRAMME_CLAIM_UNCHECKED | Q45: INHERITED_NOT_RECHECKED | R45: NO_AUTOMATIC_MISMATCH_DETECTED_NOT_PROOF | S45: SRC-GL_GHIT
A46: SRC-GL_GRANDCHALLENGES | B46: Grand Challenges - Funding | C46: OFFICIAL_WEB | D46: M05 | E46: https://gcgh.grandchallenges.org/ | F46: WEB_TEXT | G46: NOT_CHECKED | I46: UNTESTED | J46: FUNDING_ENTRY_ONLY | K46: PUBLIC | L46: Aus Nutzerdatei uebernommen; URL und aktueller Inhalt nicht in diesem Vollimport live verifiziert. | M46: INHERITED_NOT_RECHECKED | P46: OFFICIAL_ORGANISATION_OR_PROGRAMME_CLAIM_UNCHECKED | Q46: INHERITED_NOT_RECHECKED | R46: NO_AUTOMATIC_MISMATCH_DETECTED_NOT_PROOF | S46: SRC-GL_GRANDCHALLENGES
A47: SRC-GL_INCATE | B47: INCATE - Early Antibacterial Innovation | C47: OFFICIAL_WEB | D47: M05 | E47: https://www.incate.net/how-we-help/ | F47: WEB_TEXT | G47: NOT_CHECKED | I47: UNTESTED | J47: FUNDING_ENTRY_ONLY | K47: PUBLIC | L47: Aus Nutzerdatei uebernommen; URL und aktueller Inhalt nicht in diesem Vollimport live verifiziert. | M47: INHERITED_NOT_RECHECKED | P47: OFFICIAL_ORGANISATION_OR_PROGRAMME_CLAIM_UNCHECKED | Q47: INHERITED_NOT_RECHECKED | R47: NO_AUTOMATIC_MISMATCH_DETECTED_NOT_PROOF | S47: SRC-GL_INCATE
A48: SRC-GL_NOVO | B48: Novo Nordisk Foundation - Grant Calls | C48: OFFICIAL_WEB | D48: M05 | E48: https://novonordiskfonden.dk/en/grant/ | F48: WEB_TEXT | G48: NOT_CHECKED | I48: UNTESTED | J48: FUNDING_ENTRY_ONLY | K48: PUBLIC | L48: Aus Nutzerdatei uebernommen; URL und aktueller Inhalt nicht in diesem Vollimport live verifiziert. | M48: INHERITED_NOT_RECHECKED | P48: OFFICIAL_ORGANISATION_OR_PROGRAMME_CLAIM_UNCHECKED | Q48: INHERITED_NOT_RECHECKED | R48: NO_AUTOMATIC_MISMATCH_DETECTED_NOT_PROOF | S48: SRC-GL_NOVO
A49: SRC-GL_NIH_FOREIGN | B49: NIH - Foreign Grants / Eligibility | C49: OFFICIAL_WEB | D49: M05 | E49: https://grants.nih.gov/new-to-nih/information-for/foreign-grants | F49: WEB_TEXT | G49: NOT_CHECKED | I49: UNTESTED | J49: FUNDING_ENTRY_ONLY | K49: PUBLIC | L49: Aus Nutzerdatei uebernommen; URL und aktueller Inhalt nicht in diesem Vollimport live verifiziert. | M49: INHERITED_NOT_RECHECKED | P49: OFFICIAL_ORGANISATION_OR_PROGRAMME_CLAIM_UNCHECKED | Q49: INHERITED_NOT_RECHECKED | R49: NO_AUTOMATIC_MISMATCH_DETECTED_NOT_PROOF | S49: SRC-GL_NIH_FOREIGN
A50: SRC-REG_BW | B50: L-Bank Baden-Württemberg | C50: OFFICIAL_WEB | D50: M05 | E50: https://www.l-bank.de/ | F50: WEB_TEXT | G50: NOT_CHECKED | I50: UNTESTED | J50: FUNDING_ENTRY_ONLY | K50: PUBLIC | L50: Aus Nutzerdatei uebernommen; URL und aktueller Inhalt nicht in diesem Vollimport live verifiziert. | M50: INHERITED_NOT_RECHECKED | P50: OFFICIAL_ORGANISATION_OR_PROGRAMME_CLAIM_UNCHECKED | Q50: INHERITED_NOT_RECHECKED | R50: NO_AUTOMATIC_MISMATCH_DETECTED_NOT_PROOF | S50: SRC-REG_BW
A51: SRC-REG_BY | B51: Bayerische Forschungs- und Innovationsagentur | C51: OFFICIAL_WEB | D51: M05 | E51: https://www.forschung-innovation-bayern.de/service/foerderung-von-forschung-und-innovation/ | F51: WEB_TEXT | G51: NOT_CHECKED | I51: UNTESTED | J51: FUNDING_ENTRY_ONLY | K51: PUBLIC | L51: Aus Nutzerdatei uebernommen; URL und aktueller Inhalt nicht in diesem Vollimport live verifiziert. | M51: INHERITED_NOT_RECHECKED | P51: OFFICIAL_ORGANISATION_OR_PROGRAMME_CLAIM_UNCHECKED | Q51: INHERITED_NOT_RECHECKED | R51: NO_AUTOMATIC_MISMATCH_DETECTED_NOT_PROOF | S51: SRC-REG_BY
A52: SRC-REG_BE | B52: IBB Berlin - Förderungen | C52: OFFICIAL_WEB | D52: M05 | E52: https://www.ibb.de/de/foerderungen/foerderungen.html | F52: WEB_TEXT | G52: NOT_CHECKED | I52: UNTESTED | J52: FUNDING_ENTRY_ONLY | K52: PUBLIC | L52: Aus Nutzerdatei uebernommen; URL und aktueller Inhalt nicht in diesem Vollimport live verifiziert. | M52: INHERITED_NOT_RECHECKED | P52: OFFICIAL_ORGANISATION_OR_PROGRAMME_CLAIM_UNCHECKED | Q52: INHERITED_NOT_RECHECKED | R52: NO_AUTOMATIC_MISMATCH_DETECTED_NOT_PROOF | S52: SRC-REG_BE
A53: SRC-REG_BB | B53: ILB Brandenburg - Innovation / FuE | C53: OFFICIAL_WEB | D53: M05 | E53: https://www.ilb.de/de/existenzgruendung/existenzgruendung-foerderangebote-nach-foerderthemen/innovationen-forschung-entwicklung/ | F53: WEB_TEXT | G53: NOT_CHECKED | I53: UNTESTED | J53: FUNDING_ENTRY_ONLY | K53: PUBLIC | L53: Aus Nutzerdatei uebernommen; URL und aktueller Inhalt nicht in diesem Vollimport live verifiziert. | M53: INHERITED_NOT_RECHECKED | P53: OFFICIAL_ORGANISATION_OR_PROGRAMME_CLAIM_UNCHECKED | Q53: INHERITED_NOT_RECHECKED | R53: NO_AUTOMATIC_MISMATCH_DETECTED_NOT_PROOF | S53: SRC-REG_BB
A54: SRC-REG_HB | B54: Bremer Aufbau-Bank (BAB) | C54: OFFICIAL_WEB | D54: M05 | E54: https://www.bab-bremen.de/ | F54: WEB_TEXT | G54: NOT_CHECKED | I54: UNTESTED | J54: FUNDING_ENTRY_ONLY | K54: PUBLIC | L54: Aus Nutzerdatei uebernommen; URL und aktueller Inhalt nicht in diesem Vollimport live verifiziert. | M54: INHERITED_NOT_RECHECKED | P54: OFFICIAL_ORGANISATION_OR_PROGRAMME_CLAIM_UNCHECKED | Q54: INHERITED_NOT_RECHECKED | R54: NO_AUTOMATIC_MISMATCH_DETECTED_NOT_PROOF | S54: SRC-REG_HB
A55: SRC-REG_HH | B55: IFB Hamburg - Förderprogramme | C55: OFFICIAL_WEB | D55: M05 | E55: https://www.ifbhh.de/ | F55: WEB_TEXT | G55: NOT_CHECKED | I55: UNTESTED | J55: FUNDING_ENTRY_ONLY | K55: PUBLIC | L55: Aus Nutzerdatei uebernommen; URL und aktueller Inhalt nicht in diesem Vollimport live verifiziert. | M55: INHERITED_NOT_RECHECKED | P55: OFFICIAL_ORGANISATION_OR_PROGRAMME_CLAIM_UNCHECKED | Q55: INHERITED_NOT_RECHECKED | R55: NO_AUTOMATIC_MISMATCH_DETECTED_NOT_PROOF | S55: SRC-REG_HH
A56: SRC-REG_HE | B56: WIBank Hessen - Förderprogramme | C56: OFFICIAL_WEB | D56: M05 | E56: https://www.wibank.de/wibank/gruender-unternehmen/foerderprogramme | F56: WEB_TEXT | G56: NOT_CHECKED | I56: UNTESTED | J56: FUNDING_ENTRY_ONLY | K56: PUBLIC | L56: Aus Nutzerdatei uebernommen; URL und aktueller Inhalt nicht in diesem Vollimport live verifiziert. | M56: INHERITED_NOT_RECHECKED | P56: OFFICIAL_ORGANISATION_OR_PROGRAMME_CLAIM_UNCHECKED | Q56: INHERITED_NOT_RECHECKED | R56: NO_AUTOMATIC_MISMATCH_DETECTED_NOT_PROOF | S56: SRC-REG_HE
A57: SRC-REG_MV | B57: LFI M-V - Förderfinder | C57: OFFICIAL_WEB | D57: M05 | E57: https://www.lfi-mv.de/foerderfinder | F57: WEB_TEXT | G57: NOT_CHECKED | I57: UNTESTED | J57: FUNDING_ENTRY_ONLY | K57: PUBLIC | L57: Aus Nutzerdatei uebernommen; URL und aktueller Inhalt nicht in diesem Vollimport live verifiziert. | M57: INHERITED_NOT_RECHECKED | P57: OFFICIAL_ORGANISATION_OR_PROGRAMME_CLAIM_UNCHECKED | Q57: INHERITED_NOT_RECHECKED | R57: NO_AUTOMATIC_MISMATCH_DETECTED_NOT_PROOF | S57: SRC-REG_MV
... A66: SRC-REG_BY_RESEARCH | B66: Bayerische Forschungsstiftung / Förderung | C66: OFFICIAL_WEB | D66: M05 | E66: https://www.stmwk.bayern.de/wissenschaftler/forschung/foerderung.html | F66: WEB_TEXT | G66: NOT_CHECKED | I66: UNTESTED | J66: FUNDING_ENTRY_ONLY | K66: PUBLIC | L66: Aus Nutzerdatei uebernommen; URL und aktueller Inhalt nicht in diesem Vollimport live verifiziert. | M66: INHERITED_NOT_RECHECKED | P66: OFFICIAL_ORGANISATION_OR_PROGRAMME_CLAIM_UNCHECKED | Q66: INHERITED_NOT_RECHECKED | R66: NO_AUTOMATIC_MISMATCH_DETECTED_NOT_PROOF | S66: SRC-REG_BY_RESEARCH
A67: SRC-BY-STIFTUNG | B67: Bayerische Transformations- und Forschungsstiftung | C67: OFFICIAL_WEB | D67: M05 | E67: https://www.forschungsstiftung.de/foerderangebot/ | F67: WEB_TEXT | G67: CONTENT_READ | H67: 2026-10-29 | I67: UNTESTED | J67: FUNDING_ENTRY_ONLY | K67: PUBLIC | L67: Name und direkter Foerdereinstieg am 29.10.2026 geprueft; keine Call- oder Budgetvalidierung. | M67: INHERITED_NOT_RECHECKED | P67: OFFICIAL_ORGANISATION_OR_PROGRAMME_CLAIM_UNCHECKED | Q67: INHERITED_NOT_RECHECKED | R67: NO_AUTOMATIC_MISMATCH_DETECTED_NOT_PROOF | S67: SRC-BY-STIFTUNG
A68: SRC-BD-002 | B68: MSD / Merck & Co. / PARTNERING_PAGE | C68: OFFICIAL_WEB | D68: M06;M07;M01 | E68: https://www.msd.com/research/business-development-and-licensing/collaborate-with-us/ | F68: WEB_TEXT | G68: NOT_CHECKED | I68: UNTESTED | J68: PARTNERING_OR_INVESTMENT_ENTRY | K68: PUBLIC | L68: Aus Nutzerdatei uebernommen; URL und aktueller Inhalt nicht in diesem Vollimport live verifiziert. | M68: INHERITED_NOT_RECHECKED | P68: OFFICIAL_ORGANISATION_OR_PROGRAMME_CLAIM_UNCHECKED | Q68: INHERITED_NOT_RECHECKED | R68: NO_AUTOMATIC_MISMATCH_DETECTED_NOT_PROOF | S68: SRC-BD-002
A69: SRC-BD-003 | B69: Sanofi / PARTNERING_PAGE | C69: OFFICIAL_WEB | D69: M06;M07;M01 | E69: https://www.sanofi.com/en/partnering/partnering-focus-areas/vaccines | F69: WEB_TEXT | G69: NOT_CHECKED | I69: UNTESTED | J69: PARTNERING_OR_INVESTMENT_ENTRY | K69: PUBLIC | L69: Aus Nutzerdatei uebernommen; URL und aktueller Inhalt nicht in diesem Vollimport live verifiziert. | M69: INHERITED_NOT_RECHECKED | P69: OFFICIAL_ORGANISATION_OR_PROGRAMME_CLAIM_UNCHECKED | Q69: INHERITED_NOT_RECHECKED | R69: NO_AUTOMATIC_MISMATCH_DETECTED_NOT_PROOF | S69: SRC-BD-003
A70: SRC-BD-004 | B70: Pfizer / PARTNERING_PAGE | C70: OFFICIAL_WEB | D70: M06;M07 | E70: https://www.pfizer.com/about/partners/research-and-business-development-partnerships/?page=9 | F70: WEB_TEXT | G70: NOT_CHECKED | I70: UNTESTED | J70: PARTNERING_OR_INVESTMENT_ENTRY | K70: PUBLIC | L70: Aus Nutzerdatei uebernommen; URL und aktueller Inhalt nicht in diesem Vollimport live verifiziert. | M70: INHERITED_NOT_RECHECKED | P70: OFFICIAL_ORGANISATION_OR_PROGRAMME_CLAIM_UNCHECKED | Q70: INHERITED_NOT_RECHECKED | R70: NO_AUTOMATIC_MISMATCH_DETECTED_NOT_PROOF | S70: SRC-PFIZER-BD
A71: SRC-BD-005 | B71: Roche / Genentech / PARTNERING_PAGE | C71: OFFICIAL_WEB | D71: M06;M07;M01 | E71: https://www.roche.com/innovation/partnering/areas-of-interest/infectious-diseases | F71: WEB_TEXT | G71: NOT_CHECKED | I71: UNTESTED | J71: PARTNERING_OR_INVESTMENT_ENTRY | K71: PUBLIC | L71: Aus Nutzerdatei uebernommen; URL und aktueller Inhalt nicht in diesem Vollimport live verifiziert. | M71: INHERITED_NOT_RECHECKED | P71: OFFICIAL_ORGANISATION_OR_PROGRAMME_CLAIM_UNCHECKED | Q71: INHERITED_NOT_RECHECKED | R71: NO_AUTOMATIC_MISMATCH_DETECTED_NOT_PROOF | S71: SRC-BD-005
A72: SRC-BD-006 | B72: Shionogi / PARTNERING_PAGE | C72: OFFICIAL_WEB | D72: M06;M07;M01 | E72: https://www.shionogi.com/eu/en/innovation/strategic-partnering-in-europe/partnering-licensing-interests.html | F72: WEB_TEXT | G72: NOT_CHECKED | I72: UNTESTED | J72: PARTNERING_OR_INVESTMENT_ENTRY | K72: PUBLIC | L72: Aus Nutzerdatei uebernommen; URL und aktueller Inhalt nicht in diesem Vollimport live verifiziert. | M72: INHERITED_NOT_RECHECKED | P72: OFFICIAL_ORGANISATION_OR_PROGRAMME_CLAIM_UNCHECKED | Q72: INHERITED_NOT_RECHECKED | R72: NO_AUTOMATIC_MISMATCH_DETECTED_NOT_PROOF | S72: SRC-BD-006
A73: SRC-BD-007 | B73: Basilea Pharmaceutica / OFFICIAL_ACTIVITY | C73: OFFICIAL_ACTIVITY | D73: M06;M07 | E73: https://www.basilea.com/news/news/basilea-informiert-ueber-stand-seines-portfolios-und-gibt-ausblick-1 | F73: WEB_TEXT | G73: NOT_CHECKED | I73: UNTESTED | J73: HISTORICAL_SIGNAL_ONLY | K73: PUBLIC | L73: Aus Nutzerdatei uebernommen; URL und aktueller Inhalt nicht in diesem Vollimport live verifiziert. | M73: INHERITED_NOT_RECHECKED | P73: PRESS_RELEASE | Q73: INHERITED_NOT_RECHECKED | R73: NO_AUTOMATIC_MISMATCH_DETECTED_NOT_PROOF | S73: SRC-BD-007
A74: SRC-BD-008 | B74: Eli Lilly / OFFICIAL_ACTIVITY | C74: OFFICIAL_ACTIVITY | D74: M06;M07;M01 | E74: https://investor.lilly.com/node/54346 | F74: WEB_TEXT | G74: NOT_CHECKED | I74: UNTESTED | J74: HISTORICAL_SIGNAL_ONLY | K74: PUBLIC | L74: Aus Nutzerdatei uebernommen; URL und aktueller Inhalt nicht in diesem Vollimport live verifiziert. | M74: INHERITED_NOT_RECHECKED | P74: PRESS_RELEASE | Q74: INHERITED_NOT_RECHECKED | R74: NO_AUTOMATIC_MISMATCH_DETECTED_NOT_PROOF | S74: SRC-BD-008
A75: SRC-BD-009 | B75: Asahi Kasei / Veloxis / OFFICIAL_ACTIVITY | C75: OFFICIAL_ACTIVITY | D75: M06;M07 | E75: https://www.asahi-kasei.com/news/2026/e260420-2 | F75: WEB_TEXT | G75: NOT_CHECKED | I75: UNTESTED | J75: HISTORICAL_SIGNAL_ONLY | K75: PUBLIC | L75: Aus Nutzerdatei uebernommen; URL und aktueller Inhalt nicht in diesem Vollimport live verifiziert. | M75: INHERITED_NOT_RECHECKED | P75: PRESS_RELEASE | Q75: INHERITED_NOT_RECHECKED | R75: NO_AUTOMATIC_MISMATCH_DETECTED_NOT_PROOF | S75: SRC-BD-009
A76: SRC-BD-010 | B76: AstraZeneca / PIPELINE | C76: OFFICIAL_WEB | D76: M06;M07;M01 | E76: https://www.astrazeneca.com/our-therapy-areas/pipeline.html | F76: WEB_TEXT | G76: NOT_CHECKED | I76: UNTESTED | J76: PARTNERING_OR_INVESTMENT_ENTRY | K76: PUBLIC | L76: Aus Nutzerdatei uebernommen; URL und aktueller Inhalt nicht in diesem Vollimport live verifiziert. | M76: INHERITED_NOT_RECHECKED | P76: OFFICIAL_ORGANISATION_OR_PROGRAMME_CLAIM_UNCHECKED | Q76: INHERITED_NOT_RECHECKED | R76: NO_AUTOMATIC_MISMATCH_DETECTED_NOT_PROOF | S76: SRC-BD-010
A77: SRC-BD-011 | B77: BioNTech / FOCUS_PROFILE | C77: OFFICIAL_WEB | D77: M06;M07;M01 | E77: https://www.biontech.com/us/en/home/research-and-innovation/therapeutic-areas/infectious-diseases.html | F77: WEB_TEXT | G77: NOT_CHECKED | I77: UNTESTED | J77: PARTNERING_OR_INVESTMENT_ENTRY | K77: PUBLIC | L77: Aus Nutzerdatei uebernommen; URL und aktueller Inhalt nicht in diesem Vollimport live verifiziert. | M77: INHERITED_NOT_RECHECKED | P77: OFFICIAL_ORGANISATION_OR_PROGRAMME_CLAIM_UNCHECKED | Q77: INHERITED_NOT_RECHECKED | R77: NO_AUTOMATIC_MISMATCH_DETECTED_NOT_PROOF | S77: SRC-BD-011
A78: SRC-BD-012 | B78: Moderna / PIPELINE | C78: OFFICIAL_WEB | D78: M06;M07;M01;M02 | E78: https://www.modernatx.com/research/product-pipeline | F78: WEB_TEXT | G78: OFFICIAL_SEARCH_TEXT_REVIEWED | H78: 2026-10-29 | I78: UNTESTED | J78: PARTNERING_OR_INVESTMENT_ENTRY | K78: PUBLIC | L78: Preventive EBV/mononucleosis mRNA-1189 scope from official pipeline search text. Dynamic trial microsite did not render full content; no phase copied. | M78: V23_FLAGSHIP_SCOPE_REVIEW | P78: OFFICIAL_ORGANISATION_SOURCE | Q78: OFFICIAL_SEARCH_SCOPE_CHECKED | R78: OFFICIAL_DOMAIN_SCOPE_CHECKED | S78: SRC-BD-012
A79: SRC-BD-013 | B79: Bavarian Nordic / OFFICIAL_ACTIVITY | C79: OFFICIAL_ACTIVITY | D79: M06;M07;M01 | E79: https://www.bavarian-nordic.com/investor/news/news.aspx?news=7444 | F79: WEB_TEXT | G79: NOT_CHECKED | I79: UNTESTED | J79: HISTORICAL_SIGNAL_ONLY | K79: PUBLIC | L79: Aus Nutzerdatei uebernommen; URL und aktueller Inhalt nicht in diesem Vollimport live verifiziert. | M79: INHERITED_NOT_RECHECKED | P79: PRESS_RELEASE | Q79: INHERITED_NOT_RECHECKED | R79: NO_AUTOMATIC_MISMATCH_DETECTED_NOT_PROOF | S79: SRC-BD-013
A80: SRC-BD-014 | B80: Valneva / FOCUS_PROFILE | C80: OFFICIAL_WEB | D80: M06;M07;M01 | E80: https://valneva.com/faq/ | F80: WEB_TEXT | G80: NOT_CHECKED | I80: UNTESTED | J80: PARTNERING_OR_INVESTMENT_ENTRY | K80: PUBLIC | L80: Aus Nutzerdatei uebernommen; URL und aktueller Inhalt nicht in diesem Vollimport live verifiziert. | M80: INHERITED_NOT_RECHECKED | P80: OFFICIAL_ORGANISATION_OR_PROGRAMME_CLAIM_UNCHECKED | Q80: INHERITED_NOT_RECHECKED | R80: NO_AUTOMATIC_MISMATCH_DETECTED_NOT_PROOF | S80: SRC-BD-014
A81: SRC-BD-015 | B81: Gilead Sciences / OFFICIAL_ACTIVITY | C81: OFFICIAL_ACTIVITY | D81: M06;M07;M01 | E81: https://www.gilead.com/news/news-details/2026/gilead-accelerates-global-access-planning-for-investigational-once-yearly-lenacapavir-for-hiv-prevention | F81: WEB_TEXT | G81: NOT_CHECKED | I81: UNTESTED | J81: HISTORICAL_SIGNAL_ONLY | K81: PUBLIC | L81: Aus Nutzerdatei uebernommen; URL und aktueller Inhalt nicht in diesem Vollimport live verifiziert. | M81: INHERITED_NOT_RECHECKED | P81: PRESS_RELEASE | Q81: INHERITED_NOT_RECHECKED | R81: NO_AUTOMATIC_MISMATCH_DETECTED_NOT_PROOF | S81: SRC-BD-015
A82: SRC-BD-016 | B82: ViiV Healthcare / FOCUS_PROFILE | C82: OFFICIAL_WEB | D82: M06;M07;M01 | E82: https://viivhealthcare.com/de-de/hiv-forschung-und-innovation/ | F82: WEB_TEXT | G82: NOT_CHECKED | I82: UNTESTED | J82: PARTNERING_OR_INVESTMENT_ENTRY | K82: PUBLIC | L82: Aus Nutzerdatei uebernommen; URL und aktueller Inhalt nicht in diesem Vollimport live verifiziert. | M82: INHERITED_NOT_RECHECKED | P82: OFFICIAL_ORGANISATION_OR_PROGRAMME_CLAIM_UNCHECKED | Q82: INHERITED_NOT_RECHECKED | R82: NO_AUTOMATIC_MISMATCH_DETECTED_NOT_PROOF | S82: SRC-BD-016
A83: SRC-BD-017 | B83: Regeneron / OFFICIAL_ACTIVITY | C83: OFFICIAL_ACTIVITY | D83: M06;M07;M01 | E83: https://newsroom.regeneron.com/news-releases/news-release-details/regeneron-extends-agreement-barda-provide-additional-supply | F83: WEB_TEXT | G83: NOT_CHECKED | I83: UNTESTED | J83: HISTORICAL_SIGNAL_ONLY | K83: PUBLIC | L83: Aus Nutzerdatei uebernommen; URL und aktueller Inhalt nicht in diesem Vollimport live verifiziert. | M83: INHERITED_NOT_RECHECKED | P83: PRESS_RELEASE | Q83: INHERITED_NOT_RECHECKED | R83: NO_AUTOMATIC_MISMATCH_DETECTED_NOT_PROOF | S83: SRC-BD-017
A84: SRC-BD-018 | B84: Serum Institute of India / OFFICIAL_ACTIVITY | C84: OFFICIAL_ACTIVITY | D84: M06;M07;M01 | E84: https://www.seruminstitute.com/gates-medical-research-institute-and-the-serum-institute-of-india-reach-agreement.php | F84: WEB_TEXT | G84: NOT_CHECKED | I84: UNTESTED | J84: HISTORICAL_SIGNAL_ONLY | K84: PUBLIC | L84: Aus Nutzerdatei uebernommen; URL und aktueller Inhalt nicht in diesem Vollimport live verifiziert. | M84: INHERITED_NOT_RECHECKED | P84: OFFICIAL_ORGANISATION_OR_PROGRAMME_CLAIM_UNCHECKED | Q84: INHERITED_NOT_RECHECKED | R84: NO_AUTOMATIC_MISMATCH_DETECTED_NOT_PROOF | S84: SRC-BD-018
A85: SRC-BD-019 | B85: Novartis / FOCUS_PROFILE | C85: OFFICIAL_WEB | D85: M06;M07;M01 | E85: https://www.novartis.com/diseases/malaria | F85: WEB_TEXT | G85: NOT_CHECKED | I85: UNTESTED | J85: PARTNERING_OR_INVESTMENT_ENTRY | K85: PUBLIC | L85: Aus Nutzerdatei uebernommen; URL und aktueller Inhalt nicht in diesem Vollimport live verifiziert. | M85: INHERITED_NOT_RECHECKED | P85: OFFICIAL_ORGANISATION_OR_PROGRAMME_CLAIM_UNCHECKED | Q85: INHERITED_NOT_RECHECKED | R85: NO_AUTOMATIC_MISMATCH_DETECTED_NOT_PROOF | S85: SRC-BD-019
A86: SRC-BD-021 | B86: Takeda / FOCUS_PROFILE | C86: OFFICIAL_WEB | D86: M06;M07;M01 | E86: https://www.takeda.com/science/research-and-development/partnerships/iir/ | F86: WEB_TEXT | G86: NOT_CHECKED | I86: UNTESTED | J86: PARTNERING_OR_INVESTMENT_ENTRY | K86: PUBLIC | L86: Aus Nutzerdatei uebernommen; URL und aktueller Inhalt nicht in diesem Vollimport live verifiziert. | M86: INHERITED_NOT_RECHECKED | P86: OFFICIAL_ORGANISATION_OR_PROGRAMME_CLAIM_UNCHECKED | Q86: INHERITED_NOT_RECHECKED | R86: NO_AUTOMATIC_MISMATCH_DETECTED_NOT_PROOF | S86: SRC-BD-021
A87: SRC-BD-023 | B87: Clarametyx Biosciences / PIPELINE | C87: OFFICIAL_WEB | D87: M06;M07 | E87: https://clarametyx.com/pipeline-publications/ | F87: WEB_TEXT | G87: NOT_CHECKED | I87: UNTESTED | J87: PARTNERING_OR_INVESTMENT_ENTRY | K87: PUBLIC | L87: Aus Nutzerdatei uebernommen; URL und aktueller Inhalt nicht in diesem Vollimport live verifiziert. | M87: INHERITED_NOT_RECHECKED | P87: OFFICIAL_ORGANISATION_OR_PROGRAMME_CLAIM_UNCHECKED | Q87: INHERITED_NOT_RECHECKED | R87: NO_AUTOMATIC_MISMATCH_DETECTED_NOT_PROOF | S87: SRC-BD-023
A88: SRC-BD-024 | B88: Trellis Bioscience / INVESTOR_ACTIVITY | C88: OFFICIAL_WEB | D88: M06;M07;M01 | E88: https://www.newscienceventures.com/trellis-bioscience-raises-9-million-to-advance-clinical-development-of-calpurbatug-trl1068/ | F88: WEB_TEXT | G88: NOT_CHECKED | I88: UNTESTED | J88: PARTNERING_OR_INVESTMENT_ENTRY | K88: PUBLIC | L88: Aus Nutzerdatei uebernommen; URL und aktueller Inhalt nicht in diesem Vollimport live verifiziert. | M88: INHERITED_NOT_RECHECKED | P88: OFFICIAL_ORGANISATION_OR_PROGRAMME_CLAIM_UNCHECKED | Q88: INHERITED_NOT_RECHECKED | R88: MULTI_ENTITY_RELATION_REQUIRES_CONTEXT | S88: SRC-BD-024
A89: SRC-BD-026 | B89: BioVersys / OFFICIAL_ACTIVITY | C89: OFFICIAL_ACTIVITY | D89: M06;M07 | E89: https://ir.bioversys.com/news/bioversys-reports-half-year-2026-results-bv100-pivotal-riv-target-trial-actively-recruiting-alpibectir-phase-2bc-underway/b1979958-6896-4f23-aed5-0fb65e3d4b76 | F89: WEB_TEXT | G89: NOT_CHECKED | I89: UNTESTED | J89: HISTORICAL_SIGNAL_ONLY | K89: PUBLIC | L89: Aus Nutzerdatei uebernommen; URL und aktueller Inhalt nicht in diesem Vollimport live verifiziert. | M89: INHERITED_NOT_RECHECKED | P89: PRESS_RELEASE | Q89: INHERITED_NOT_RECHECKED | R89: NO_AUTOMATIC_MISMATCH_DETECTED_NOT_PROOF | S89: SRC-BD-026
A90: SRC-BD-027 | B90: Antabio / FOCUS_PROFILE | C90: OFFICIAL_WEB | D90: M06;M07 | E90: https://antabio.com/ | F90: WEB_TEXT | G90: NOT_CHECKED | I90: UNTESTED | J90: PARTNERING_OR_INVESTMENT_ENTRY | K90: PUBLIC | L90: Aus Nutzerdatei uebernommen; URL und aktueller Inhalt nicht in diesem Vollimport live verifiziert. | M90: INHERITED_NOT_RECHECKED | P90: OFFICIAL_ORGANISATION_OR_PROGRAMME_CLAIM_UNCHECKED | Q90: INHERITED_NOT_RECHECKED | R90: NO_AUTOMATIC_MISMATCH_DETECTED_NOT_PROOF | S90: SRC-BD-027
... A95: SRC-BD-033 | B95: Arcturus Therapeutics / OFFICIAL_ACTIVITY | C95: OFFICIAL_ACTIVITY | D95: M06;M07;M01 | E95: https://ir.arcturusrx.com/news-releases/news-release-details/arcturus-therapeutics-announces-second-quarter-2026-financial | F95: WEB_TEXT | G95: NOT_CHECKED | I95: UNTESTED | J95: HISTORICAL_SIGNAL_ONLY | K95: PUBLIC | L95: Aus Nutzerdatei uebernommen; URL und aktueller Inhalt nicht in diesem Vollimport live verifiziert. | M95: INHERITED_NOT_RECHECKED | P95: PRESS_RELEASE | Q95: INHERITED_NOT_RECHECKED | R95: NO_AUTOMATIC_MISMATCH_DETECTED_NOT_PROOF | S95: SRC-BD-033
A96: SRC-BD-034 | B96: Assembly Biosciences / PIPELINE | C96: OFFICIAL_WEB | D96: M06;M07;M01 | E96: https://www.assemblybio.com/pipeline/ | F96: WEB_TEXT | G96: CONTENT_READ | H96: 2026-10-29 | I96: UNTESTED | J96: PARTNERING_OR_INVESTMENT_ENTRY | K96: PUBLIC | L96: Aus Nutzerdatei uebernommen; URL und aktueller Inhalt nicht in diesem Vollimport live verifiziert. | M96: V2_1_RISK_BASED_REVIEW | P96: OFFICIAL_ORGANISATION_OR_PROGRAMME_CLAIM_UNCHECKED | Q96: SCOPE_READ_THIS_REVISION | R96: PUBLISHER_SCOPE_REVIEWED | S96: SRC-BD-034
A97: SRC-BD-035 | B97: Precision BioSciences / OFFICIAL_ACTIVITY | C97: OFFICIAL_ACTIVITY | D97: M06;M07;M01 | E97: https://investor.precisionbiosciences.com/news-releases/news-release-details/precision-biosciences-reports-second-quarter-2026-financial | F97: WEB_TEXT | G97: NOT_CHECKED | I97: UNTESTED | J97: HISTORICAL_SIGNAL_ONLY | K97: PUBLIC | L97: Aus Nutzerdatei uebernommen; URL und aktueller Inhalt nicht in diesem Vollimport live verifiziert. | M97: INHERITED_NOT_RECHECKED | P97: PRESS_RELEASE | Q97: INHERITED_NOT_RECHECKED | R97: NO_AUTOMATIC_MISMATCH_DETECTED_NOT_PROOF | S97: SRC-BD-035
A98: SRC-BD-036 | B98: Vaxxas / PARTNERING_PAGE | C98: OFFICIAL_WEB | D98: M06;M07;M01 | E98: https://vaxxas.com/about-vaxxas/ | F98: WEB_TEXT | G98: NOT_CHECKED | I98: UNTESTED | J98: PARTNERING_OR_INVESTMENT_ENTRY | K98: PUBLIC | L98: Aus Nutzerdatei uebernommen; URL und aktueller Inhalt nicht in diesem Vollimport live verifiziert. | M98: INHERITED_NOT_RECHECKED | P98: OFFICIAL_ORGANISATION_OR_PROGRAMME_CLAIM_UNCHECKED | Q98: INHERITED_NOT_RECHECKED | R98: NO_AUTOMATIC_MISMATCH_DETECTED_NOT_PROOF | S98: SRC-BD-036
A99: SRC-BD-037 | B99: Locus Biosciences / PIPELINE | C99: OFFICIAL_WEB | D99: M06;M07;M01 | E99: https://www.locus-bio.com/pipeline/ | F99: WEB_TEXT | G99: NOT_CHECKED | I99: UNTESTED | J99: PARTNERING_OR_INVESTMENT_ENTRY | K99: PUBLIC | L99: Aus Nutzerdatei uebernommen; URL und aktueller Inhalt nicht in diesem Vollimport live verifiziert. | M99: INHERITED_NOT_RECHECKED | P99: OFFICIAL_ORGANISATION_OR_PROGRAMME_CLAIM_UNCHECKED | Q99: INHERITED_NOT_RECHECKED | R99: NO_AUTOMATIC_MISMATCH_DETECTED_NOT_PROOF | S99: SRC-BD-037
A100: SRC-BD-038 | B100: Atea Pharmaceuticals / OFFICIAL_ACTIVITY | C100: OFFICIAL_ACTIVITY | D100: M06;M07;M01 | E100: https://ir.ateapharma.com/news-releases/news-release-details/atea-pharmaceuticals-reports-second-quarter-2026-financial | F100: WEB_TEXT | G100: NOT_CHECKED | I100: UNTESTED | J100: HISTORICAL_SIGNAL_ONLY | K100: PUBLIC | L100: Aus Nutzerdatei uebernommen; URL und aktueller Inhalt nicht in diesem Vollimport live verifiziert. | M100: INHERITED_NOT_RECHECKED | P100: PRESS_RELEASE | Q100: INHERITED_NOT_RECHECKED | R100: NO_AUTOMATIC_MISMATCH_DETECTED_NOT_PROOF | S100: SRC-BD-038
A101: SRC-BD-040 | B101: Kineticos AMR Accelerator Fund / INVESTMENT_MANDATE | C101: OFFICIAL_WEB | D101: M06;M07 | E101: https://www.kineticos.com/antimicrobial-resistance-accelerator-fund/ | F101: WEB_TEXT | G101: NOT_CHECKED | I101: UNTESTED | J101: PARTNERING_OR_INVESTMENT_ENTRY | K101: PUBLIC | L101: Aus Nutzerdatei uebernommen; URL und aktueller Inhalt nicht in diesem Vollimport live verifiziert. | M101: INHERITED_NOT_RECHECKED | P101: OFFICIAL_ORGANISATION_OR_PROGRAMME_CLAIM_UNCHECKED | Q101: INHERITED_NOT_RECHECKED | R101: NO_AUTOMATIC_MISMATCH_DETECTED_NOT_PROOF | S101: SRC-BD-040
A102: SRC-BD-041 | B102: Adjuvant Capital / INVESTMENT_MANDATE | C102: OFFICIAL_WEB | D102: M06;M07 | E102: https://adjuvantcapital.com/ | F102: WEB_TEXT | G102: NOT_CHECKED | I102: UNTESTED | J102: PARTNERING_OR_INVESTMENT_ENTRY | K102: PUBLIC | L102: Aus Nutzerdatei uebernommen; URL und aktueller Inhalt nicht in diesem Vollimport live verifiziert. | M102: INHERITED_NOT_RECHECKED | P102: OFFICIAL_ORGANISATION_OR_PROGRAMME_CLAIM_UNCHECKED | Q102: INHERITED_NOT_RECHECKED | R102: NO_AUTOMATIC_MISMATCH_DETECTED_NOT_PROOF | S102: SRC-BD-041
A103: SRC-BD-042 | B103: Forbion / INVESTMENT_MANDATE | C103: OFFICIAL_WEB | D103: M06;M07 | E103: https://forbion.com/strategies/ | F103: WEB_TEXT | G103: NOT_CHECKED | I103: UNTESTED | J103: PARTNERING_OR_INVESTMENT_ENTRY | K103: PUBLIC | L103: Aus Nutzerdatei uebernommen; URL und aktueller Inhalt nicht in diesem Vollimport live verifiziert. | M103: INHERITED_NOT_RECHECKED | P103: OFFICIAL_ORGANISATION_OR_PROGRAMME_CLAIM_UNCHECKED | Q103: INHERITED_NOT_RECHECKED | R103: NO_AUTOMATIC_MISMATCH_DETECTED_NOT_PROOF | S103: SRC-BD-042
A104: SRC-BD-043 | B104: Novo Holdings / OFFICIAL_ACTIVITY | C104: OFFICIAL_ACTIVITY | D104: M06;M07 | E104: https://novoholdings.dk/news/novo-holdings-backs-bactolife-s-euro30-million-series-b-alongside-new-and-existing-investors- | F104: WEB_TEXT | G104: NOT_CHECKED | I104: UNTESTED | J104: HISTORICAL_SIGNAL_ONLY | K104: PUBLIC | L104: Aus Nutzerdatei uebernommen; URL und aktueller Inhalt nicht in diesem Vollimport live verifiziert. | M104: INHERITED_NOT_RECHECKED | P104: PRESS_RELEASE | Q104: INHERITED_NOT_RECHECKED | R104: NO_AUTOMATIC_MISMATCH_DETECTED_NOT_PROOF | S104: SRC-BD-043
A105: SRC-BD-044 | B105: Sanofi Ventures / INVESTMENT_MANDATE | C105: OFFICIAL_WEB | D105: M06;M07 | E105: https://www.sanofiventures.com/approach/ | F105: WEB_TEXT | G105: NOT_CHECKED | I105: UNTESTED | J105: PARTNERING_OR_INVESTMENT_ENTRY | K105: PUBLIC | L105: Aus Nutzerdatei uebernommen; URL und aktueller Inhalt nicht in diesem Vollimport live verifiziert. | M105: INHERITED_NOT_RECHECKED | P105: OFFICIAL_ORGANISATION_OR_PROGRAMME_CLAIM_UNCHECKED | Q105: INHERITED_NOT_RECHECKED | R105: NO_AUTOMATIC_MISMATCH_DETECTED_NOT_PROOF | S105: SRC-BD-044
A106: SRC-BD-045 | B106: High-Tech Gruenderfonds (HTGF) / OFFICIAL_ACTIVITY | C106: OFFICIAL_ACTIVITY | D106: M06;M07 | E106: https://www.htgf.de/en/revier-therapeutics-seed/ | F106: WEB_TEXT | G106: NOT_CHECKED | I106: UNTESTED | J106: HISTORICAL_SIGNAL_ONLY | K106: PUBLIC | L106: Aus Nutzerdatei uebernommen; URL und aktueller Inhalt nicht in diesem Vollimport live verifiziert. | M106: INHERITED_NOT_RECHECKED | P106: OFFICIAL_ORGANISATION_OR_PROGRAMME_CLAIM_UNCHECKED | Q106: INHERITED_NOT_RECHECKED | R106: NO_AUTOMATIC_MISMATCH_DETECTED_NOT_PROOF | S106: SRC-BD-045
A107: SRC-BD-046 | B107: Sofinnova Partners / INVESTMENT_MANDATE | C107: OFFICIAL_WEB | D107: M06;M07 | E107: https://sofinnovapartners.com/strategy/capital | F107: WEB_TEXT | G107: NOT_CHECKED | I107: UNTESTED | J107: PARTNERING_OR_INVESTMENT_ENTRY | K107: PUBLIC | L107: Aus Nutzerdatei uebernommen; URL und aktueller Inhalt nicht in diesem Vollimport live verifiziert. | M107: INHERITED_NOT_RECHECKED | P107: OFFICIAL_ORGANISATION_OR_PROGRAMME_CLAIM_UNCHECKED | Q107: INHERITED_NOT_RECHECKED | R107: NO_AUTOMATIC_MISMATCH_DETECTED_NOT_PROOF | S107: SRC-BD-046
A108: SRC-BD-051 | B108: SR One / INVESTOR_PORTFOLIO | C108: OFFICIAL_WEB | D108: M06;M07 | E108: https://www.srone.com/portfolio | F108: WEB_TEXT | G108: NOT_CHECKED | I108: UNTESTED | J108: PARTNERING_OR_INVESTMENT_ENTRY | K108: PUBLIC | L108: Aus Nutzerdatei uebernommen; URL und aktueller Inhalt nicht in diesem Vollimport live verifiziert. | M108: INHERITED_NOT_RECHECKED | P108: OFFICIAL_ORGANISATION_OR_PROGRAMME_CLAIM_UNCHECKED | Q108: INHERITED_NOT_RECHECKED | R108: NO_AUTOMATIC_MISMATCH_DETECTED_NOT_PROOF | S108: SRC-BD-051
... A110: SRC-BD-053 | B110: F-Prime Capital / INVESTOR_PORTFOLIO | C110: OFFICIAL_WEB | D110: M06;M07 | E110: https://www.fprimecapital.com/portfolio/life-sciences/ | F110: WEB_TEXT | G110: NOT_CHECKED | I110: UNTESTED | J110: PARTNERING_OR_INVESTMENT_ENTRY | K110: PUBLIC | L110: Aus Nutzerdatei uebernommen; URL und aktueller Inhalt nicht in diesem Vollimport live verifiziert. | M110: INHERITED_NOT_RECHECKED | P110: OFFICIAL_ORGANISATION_OR_PROGRAMME_CLAIM_UNCHECKED | Q110: INHERITED_NOT_RECHECKED | R110: NO_AUTOMATIC_MISMATCH_DETECTED_NOT_PROOF | S110: SRC-BD-053
A111: SRC-CENTAURI-2022 | B111: Centauri / Series A 2022 | C111: OFFICIAL_WEB | D111: M06;M07 | E111: https://www.centauritherapeutics.com/centauri-therapeutics-closes-24m-series-a-investment-round/ | F111: WEB_TEXT | G111: CONTENT_READ | H111: 2026-10-29 | I111: UNTESTED | J111: HISTORICAL_PORTFOLIO_ONLY | K111: PUBLIC | L111: Artikeltext nennt 16.02.2022; Seitenkopf weicht ab. Historischer Beteiligungsnachweis, kein aktuelles Investmentmandat. | M111: INHERITED_NOT_RECHECKED | P111: PRESS_RELEASE | Q111: INHERITED_NOT_RECHECKED | R111: NO_AUTOMATIC_MISMATCH_DETECTED_NOT_PROOF | S111: SRC-CENTAURI-2022
A112: SRC-BD-055 | B112: EQT Life Sciences / INVESTMENT_MANDATE | C112: OFFICIAL_WEB | D112: M06;M07 | E112: https://eqtgroup.com/private-capital/eqt-life-sciences | F112: WEB_TEXT | G112: NOT_CHECKED | I112: UNTESTED | J112: PARTNERING_OR_INVESTMENT_ENTRY | K112: PUBLIC | L112: Aus Nutzerdatei uebernommen; URL und aktueller Inhalt nicht in diesem Vollimport live verifiziert. | M112: INHERITED_NOT_RECHECKED | P112: OFFICIAL_ORGANISATION_OR_PROGRAMME_CLAIM_UNCHECKED | Q112: INHERITED_NOT_RECHECKED | R112: NO_AUTOMATIC_MISMATCH_DETECTED_NOT_PROOF | S112: SRC-BD-055
A113: SRC-BD-057 | B113: KHAN Technology Transfer Fund II / INVESTMENT_MANDATE | C113: OFFICIAL_WEB | D113: M06;M07 | E113: https://khanu.de/ | F113: WEB_TEXT | G113: NOT_CHECKED | I113: UNTESTED | J113: PARTNERING_OR_INVESTMENT_ENTRY | K113: PUBLIC | L113: Aus Nutzerdatei uebernommen; URL und aktueller Inhalt nicht in diesem Vollimport live verifiziert. | M113: INHERITED_NOT_RECHECKED | P113: OFFICIAL_ORGANISATION_OR_PROGRAMME_CLAIM_UNCHECKED | Q113: INHERITED_NOT_RECHECKED | R113: NO_AUTOMATIC_MISMATCH_DETECTED_NOT_PROOF | S113: SRC-BD-057
A114: SRC-RAD-1fb244a155 | B114: BEAM Alliance | Cross-company RX/DX pipeline | C114: INDUSTRY_DIRECTORY | D114: M01;M03;M06 | E114: https://beam-alliance.eu/pipeline/ | F114: WEB_TEXT | G114: CONTENT_READ | H114: 2026-10-29 | I114: UNTESTED | J114: SECTOR_ASSOCIATION_ONLY | K114: PUBLIC | L114: Industry consortium directory across many developers; NOT Bioversys-specific primary evidence. Verify each asset at developer or study-register level. | M114: V2_1_RISK_BASED_REVIEW | P114: INDUSTRY_DIRECTORY | Q114: SCOPE_READ_THIS_REVISION | R114: MULTI_ENTITY_DIRECTORY | S114: SRC-RAD-1fb244a155
A115: SRC-RAD-b7ad624d28 | B115: Armata Pharmaceuticals Inc / Referenzquelle | C115: OFFICIAL_WEB | D115: M01 | E115: https://www.armata.com/ | F115: WEB_TEXT | G115: NOT_CHECKED | I115: UNTESTED | J115: COMPANY_SCOPE_ONLY | K115: PUBLIC | L115: Aus Nutzerdatei uebernommen; URL und aktueller Inhalt nicht in diesem Vollimport live verifiziert. | M115: INHERITED_NOT_RECHECKED | P115: OFFICIAL_ORGANISATION_OR_PROGRAMME_CLAIM_UNCHECKED | Q115: INHERITED_NOT_RECHECKED | R115: NO_AUTOMATIC_MISMATCH_DETECTED_NOT_PROOF | S115: SRC-RAD-b7ad624d28
A116: SRC-RAD-6f35534e04 | B116: Seres Therapeutics Inc / Referenzquelle | C116: OFFICIAL_WEB | D116: M01 | E116: https://www.serestherapeutics.com/our-programs/ | F116: WEB_TEXT | G116: NOT_CHECKED | I116: UNTESTED | J116: COMPANY_SCOPE_ONLY | K116: PUBLIC | L116: Aus Nutzerdatei uebernommen; URL und aktueller Inhalt nicht in diesem Vollimport live verifiziert. | M116: INHERITED_NOT_RECHECKED | P116: OFFICIAL_ORGANISATION_OR_PROGRAMME_CLAIM_UNCHECKED | Q116: INHERITED_NOT_RECHECKED | R116: NO_AUTOMATIC_MISMATCH_DETECTED_NOT_PROOF | S116: SRC-RAD-6f35534e04
A117: SRC-RAD-c2abdf37fd | B117: Clarametyx Biosciences Inc / Referenzquelle | C117: OFFICIAL_WEB | D117: M01 | E117: https://clarametyx.com/ | F117: WEB_TEXT | G117: NOT_CHECKED | I117: UNTESTED | J117: COMPANY_SCOPE_ONLY | K117: PUBLIC | L117: Aus Nutzerdatei uebernommen; URL und aktueller Inhalt nicht in diesem Vollimport live verifiziert. | M117: INHERITED_NOT_RECHECKED | P117: OFFICIAL_ORGANISATION_OR_PROGRAMME_CLAIM_UNCHECKED | Q117: INHERITED_NOT_RECHECKED | R117: NO_AUTOMATIC_MISMATCH_DETECTED_NOT_PROOF | S117: SRC-RAD-c2abdf37fd
A118: SRC-RAD-d19726318a | B118: Vedanta Biosciences Inc / Referenzquelle | C118: OFFICIAL_WEB | D118: M01 | E118: https://www.vedantabio.com/pipeline-programs/pipeline/ | F118: WEB_TEXT | G118: NOT_CHECKED | I118: UNTESTED | J118: COMPANY_SCOPE_ONLY | K118: PUBLIC | L118: Aus Nutzerdatei uebernommen; URL und aktueller Inhalt nicht in diesem Vollimport live verifiziert. | M118: INHERITED_NOT_RECHECKED | P118: OFFICIAL_ORGANISATION_OR_PROGRAMME_CLAIM_UNCHECKED | Q118: INHERITED_NOT_RECHECKED | R118: NO_AUTOMATIC_MISMATCH_DETECTED_NOT_PROOF | S118: SRC-RAD-d19726318a
A119: SRC-RAD-d614ffa198 | B119: QIAGEN / Referenzquelle | C119: OFFICIAL_WEB | D119: M01 | E119: https://www.qiagen.com/de/products/diagnostics-and-clinical-research/infectious-disease/qiastat-dx-syndromic-testing/qiastat-dx | F119: WEB_TEXT | G119: NOT_CHECKED | I119: UNTESTED | J119: COMPANY_SCOPE_ONLY | K119: PUBLIC | L119: Aus Nutzerdatei uebernommen; URL und aktueller Inhalt nicht in diesem Vollimport live verifiziert. | M119: INHERITED_NOT_RECHECKED | P119: OFFICIAL_ORGANISATION_OR_PROGRAMME_CLAIM_UNCHECKED | Q119: INHERITED_NOT_RECHECKED | R119: NO_AUTOMATIC_MISMATCH_DETECTED_NOT_PROOF | S119: SRC-RAD-d614ffa198
A120: SRC-RAD-1786dd6b66 | B120: Roche Diagnostics / Referenzquelle | C120: OFFICIAL_WEB | D120: M01 | E120: https://diagnostics.roche.com/global/en/products/product-category/health-topic/infectious-diseases.html | F120: WEB_TEXT | G120: NOT_CHECKED | I120: UNTESTED | J120: COMPANY_SCOPE_ONLY | K120: PUBLIC | L120: Aus Nutzerdatei uebernommen; URL und aktueller Inhalt nicht in diesem Vollimport live verifiziert. | M120: INHERITED_NOT_RECHECKED | P120: OFFICIAL_ORGANISATION_OR_PROGRAMME_CLAIM_UNCHECKED | Q120: INHERITED_NOT_RECHECKED | R120: NO_AUTOMATIC_MISMATCH_DETECTED_NOT_PROOF | S120: SRC-RAD-1786dd6b66
A121: SRC-RAD-71fc0abe40 | B121: Becton, Dickinson and Company / Referenzquelle | C121: OFFICIAL_WEB | D121: M01 | E121: https://emea.bd.com/advancing-diagnostics/for-clinicians/ | F121: WEB_TEXT | G121: NOT_CHECKED | I121: UNTESTED | J121: COMPANY_SCOPE_ONLY | K121: PUBLIC | L121: Aus Nutzerdatei uebernommen; URL und aktueller Inhalt nicht in diesem Vollimport live verifiziert. | M121: INHERITED_NOT_RECHECKED | P121: OFFICIAL_ORGANISATION_OR_PROGRAMME_CLAIM_UNCHECKED | Q121: INHERITED_NOT_RECHECKED | R121: NO_AUTOMATIC_MISMATCH_DETECTED_NOT_PROOF | S121: SRC-RAD-71fc0abe40
A122: SRC-RAD-b6e19f6da9 | B122: Cepheid / Referenzquelle | C122: OFFICIAL_WEB | D122: M01 | E122: https://www.cepheid.com/ | F122: WEB_TEXT | G122: NOT_CHECKED | I122: UNTESTED | J122: COMPANY_SCOPE_ONLY | K122: PUBLIC | L122: Aus Nutzerdatei uebernommen; URL und aktueller Inhalt nicht in diesem Vollimport live verifiziert. | M122: INHERITED_NOT_RECHECKED | P122: OFFICIAL_ORGANISATION_OR_PROGRAMME_CLAIM_UNCHECKED | Q122: INHERITED_NOT_RECHECKED | R122: NO_AUTOMATIC_MISMATCH_DETECTED_NOT_PROOF | S122: SRC-RAD-b6e19f6da9
A123: SRC-RAD-11cd893e09 | B123: bioMerieux / Referenzquelle | C123: OFFICIAL_WEB | D123: M01 | E123: https://www.biomerieux.com/ | F123: WEB_TEXT | G123: NOT_CHECKED | I123: UNTESTED | J123: COMPANY_SCOPE_ONLY | K123: PUBLIC | L123: Aus Nutzerdatei uebernommen; URL und aktueller Inhalt nicht in diesem Vollimport live verifiziert. | M123: INHERITED_NOT_RECHECKED | P123: OFFICIAL_ORGANISATION_OR_PROGRAMME_CLAIM_UNCHECKED | Q123: INHERITED_NOT_RECHECKED | R123: NO_AUTOMATIC_MISMATCH_DETECTED_NOT_PROOF | S123: SRC-RAD-11cd893e09
A124: SRC-RAD-99e967cfbf | B124: Atara Biotherapeutics / Referenzquelle | C124: OFFICIAL_WEB | D124: M01 | E124: https://investors.atarabio.com/news-events/press-releases | F124: WEB_TEXT | G124: NOT_CHECKED | I124: UNTESTED | J124: COMPANY_SCOPE_ONLY | K124: PUBLIC | L124: Aus Nutzerdatei uebernommen; URL und aktueller Inhalt nicht in diesem Vollimport live verifiziert. | M124: INHERITED_NOT_RECHECKED | P124: PRESS_RELEASE | Q124: INHERITED_NOT_RECHECKED | R124: NO_AUTOMATIC_MISMATCH_DETECTED_NOT_PROOF | S124: SRC-RAD-99e967cfbf
A125: SRC-CENTAURI | B125: Centauri Therapeutics | C125: OFFICIAL_WEB | D125: M01;M06;M07 | E125: https://www.centauritherapeutics.com/ | F125: WEB_TEXT | G125: CONTENT_READ | H125: 2026-10-29 | I125: UNTESTED | J125: COMPANY_AND_TECHNOLOGY_SCOPE | K125: PUBLIC | L125: Alphamer-Technologie nutzt vorhandene Antikoerper; nicht pauschal als verabreichter mAb klassifizieren. Identitaet Centauri Therapeutics / Limited abgeglichen. | M125: INHERITED_NOT_RECHECKED | P125: OFFICIAL_ORGANISATION_OR_PROGRAMME_CLAIM_UNCHECKED | Q125: INHERITED_NOT_RECHECKED | R125: NO_AUTOMATIC_MISMATCH_DETECTED_NOT_PROOF | S125: SRC-CENTAURI
A126: SRC-RAD-b1e50ef2f0 | B126: MaaT Pharma / Referenzquelle | C126: OFFICIAL_WEB | D126: M01 | E126: https://www.maatpharma.com/pipeline/ | F126: WEB_TEXT | G126: NOT_CHECKED | I126: UNTESTED | J126: COMPANY_SCOPE_ONLY | K126: PUBLIC | L126: Aus Nutzerdatei uebernommen; URL und aktueller Inhalt nicht in diesem Vollimport live verifiziert. | M126: INHERITED_NOT_RECHECKED | P126: OFFICIAL_ORGANISATION_OR_PROGRAMME_CLAIM_UNCHECKED | Q126: INHERITED_NOT_RECHECKED | R126: NO_AUTOMATIC_MISMATCH_DETECTED_NOT_PROOF | S126: SRC-RAD-b1e50ef2f0
A127: SRC-RAD-9142305dd4 | B127: Excision BioTherapeutics / Referenzquelle | C127: OFFICIAL_WEB | D127: M01 | E127: https://excisionbiotherapeutics.com/pipeline | F127: WEB_TEXT | G127: CONTENT_READ | H127: 2026-10-29 | I127: UNTESTED | J127: COMPANY_SCOPE_ONLY | K127: PUBLIC | L127: Aus Nutzerdatei uebernommen; URL und aktueller Inhalt nicht in diesem Vollimport live verifiziert. | M127: V2_1_RISK_BASED_REVIEW | P127: OFFICIAL_ORGANISATION_OR_PROGRAMME_CLAIM_UNCHECKED | Q127: SCOPE_READ_THIS_REVISION | R127: PUBLISHER_SCOPE_REVIEWED | S127: SRC-RAD-9142305dd4
A128: SRC-RAD-dd4d6ddb44 | B128: BEAM Alliance | Member directory | C128: INDUSTRY_DIRECTORY | D128: M01;M06 | E128: https://beam-alliance.eu/members/ | F128: WEB_TEXT | G128: NOT_CHECKED | I128: UNTESTED | J128: SECTOR_ASSOCIATION_ONLY | K128: PUBLIC | L128: Aus Nutzerdatei uebernommen; URL und aktueller Inhalt nicht in diesem Vollimport live verifiziert. | M128: INHERITED_NOT_RECHECKED | P128: INDUSTRY_DIRECTORY | Q128: INHERITED_NOT_RECHECKED | R128: MULTI_ENTITY_DIRECTORY | S128: SRC-RAD-dd4d6ddb44
A129: SRC-INPUT-DZIF_RA | B129: DZIF | C129: PUBLIC_REFERENCE | D129: M01 | E129: https://www.dzif.de/en/research-areas | F129: WEB_TEXT | G129: NOT_CHECKED | I129: UNTESTED | J129: DISCOVERY_REFERENCE | K129: PUBLIC | L129: Confirms names of DZIF research units. | M129: INHERITED_NOT_RECHECKED | P129: OFFICIAL_ORGANISATION_OR_PROGRAMME_CLAIM_UNCHECKED | Q129: INHERITED_NOT_RECHECKED | R129: NO_AUTOMATIC_MISMATCH_DETECTED_NOT_PROOF | S129: SRC-INPUT-DZIF_RA
...

Sheet MATCH_ANCHORS
A1: anchor_id | B1: entity_ids | C1: asset_id | D1: asset_name | E1: anchor_scope | F1: pathogen_tags | G1: indication_tags | H1: modality_tags | I1: target_tags | J1: moa_tags | K1: population_tags | L1: purpose_tags | M1: source_id | N1: evidence_url | O1: scope_reviewed_on | P1: verification_status | Q1: caution
A2: ANCH-RESPX | B2: CMP-fa8243cafa7 | C2: AST-RESPX-INFEX702 | D2: RESP-X / INFEX702 | E2: ASSET_SCOPE | F2: P_AERUGINOSA | G2: NCFB | H2: ANTIBODY | I2: PCRV | J2: ANTIVIRULENCE | K2: UNKNOWN | L2: TREATMENT | M2: SRC-INFEX-IMAGE | N2: https://www.infextx.com/infex-therapeutics-presents-new-phase-iia-data-for-resp-x-at-ers-congress-2026-providing-further-evidence-on-exploratory-efficacy-endpoints-supporting-progression-to-later-stage-development/ | O2: 2026-10-29 | P2: SCOPE_REVIEWED_NOT_CURRENT_STATUS | Q2: Same pathogen/target as PANTIPA; NCFB is not acute HAP/VAP. No current clinical-stage claim in master.
A3: ANCH-GREMUBAMAB | B3: CMP-85e7acc8115 | C3: AST-GREMUBAMAB-MEDI3902 | D3: gremubamab / MEDI3902 | E3: ASSET_SCOPE | F3: P_AERUGINOSA | G3: NCFB | H3: BISPECIFIC | I3: PCRV;PSL | J3: ANTIVIRULENCE | K3: UNKNOWN | L3: TREATMENT | M3: SRC-V21-GREAT2 | N3: https://www.hra.nhs.uk/planning-and-improving-research/application-summaries/research-summaries/gremubamab-eradication-trial-great-2/ | O3: 2026-10-29 | P3: SCOPE_REVIEWED_NOT_CURRENT_STATUS | Q3: Target/MoA identity additionally supported by PMID 30107283 (2018/2019), https://pubmed.ncbi.nlm.nih.gov/30107283/ . GREAT-2: academic sponsor, not automatically a currently active AZ corporate phase.
A4: ANCH-APPA02 | B4: CMP-3a0fa1b3462 | C4: AST-APPA02 | D4: AP-PA02 | E4: ASSET_SCOPE | F4: P_AERUGINOSA | G4: NCFB;CF | H4: PHAGE | I4: UNKNOWN | J4: BACTERIAL_LYSIS | K4: UNKNOWN | L4: TREATMENT | M4: SRC-ARMATA | N4: https://www.armatapharma.com/pipeline/ap-pa02/ | O4: 2026-10-29 | P4: SCOPE_REVIEWED_NOT_CURRENT_STATUS | Q4: Pathogen-related alternative; NCFB/CF does not establish HAP/VAP efficacy.
A5: ANCH-VIIV | B5: CMP-5ad19a5f747 | E5: PORTFOLIO_SCOPE | F5: HIV | G5: HIV_TREATMENT;HIV_PREVENTION | H5: SMALL_MOLECULE;ANTIBODY | I5: UNKNOWN | J5: UNKNOWN | K5: UNKNOWN | L5: TREATMENT;PREVENTION | M5: SRC-VIIV | N5: https://viivhcmedinfo.com/our-pipeline/ | O5: 2026-10-29 | P5: SCOPE_REVIEWED_NOT_CURRENT_STATUS | Q5: Identity/routing evidence only. Phase, current activity, clinical equivalence and rights require live verification.
A6: ANCH-ASSEMBLY | B6: CMP-37b3da7d795 | E6: PORTFOLIO_SCOPE | F6: HBV;HDV;HSV | G6: CHRONIC_HBV;CHRONIC_HDV;HSV_INFECTION | H6: SMALL_MOLECULE | I6: UNKNOWN | J6: UNKNOWN | K6: UNKNOWN | L6: TREATMENT | M6: SRC-BD-034 | N6: https://www.assemblybio.com/pipeline/ | O6: 2026-10-29 | P6: SCOPE_REVIEWED_NOT_CURRENT_STATUS | Q6: Identity/routing evidence only. Phase, current activity, clinical equivalence and rights require live verification.
A7: ANCH-VIR | B7: CMP-601bca434c7 | E7: PORTFOLIO_SCOPE | F7: HDV;HIV | G7: CHRONIC_HDV;HIV_CURE | H7: ANTIBODY;RNA | I7: UNKNOWN | J7: UNKNOWN | K7: UNKNOWN | L7: TREATMENT | M7: SRC-V21-VIR | N7: https://www.vir.bio/pipeline/ | O7: 2026-10-29 | P7: SCOPE_REVIEWED_NOT_CURRENT_STATUS | Q7: Identity/routing evidence only. Phase, current activity, clinical equivalence and rights require live verification.
A8: ANCH-TB | B8: ENT-V2-TB_ALLIANCE | E8: PORTFOLIO_SCOPE | F8: M_TUBERCULOSIS | G8: TB | H8: SMALL_MOLECULE | I8: UNKNOWN | J8: UNKNOWN | K8: UNKNOWN | L8: TREATMENT | M8: SRC-V2-TB_ALLIANCE | N8: https://www.tballiance.org/our-pipeline-portfolio/ | O8: 2026-10-29 | P8: SCOPE_REVIEWED_NOT_CURRENT_STATUS | Q8: Identity/routing evidence only. Phase, current activity, clinical equivalence and rights require live verification.
A9: ANCH-DNDI | B9: CMP-6dcf8867166 | E9: PORTFOLIO_SCOPE | F9: LEISHMANIA;T_CRUZI;T_BRUCEI;HCV;HIV;CRYPTOCOCCUS | G9: LEISHMANIASIS;CHAGAS;SLEEPING_SICKNESS;CHRONIC_HCV;HIV_TREATMENT;CRYPTOCOCCAL_MENINGITIS | H9: SMALL_MOLECULE | I9: UNKNOWN | J9: UNKNOWN | K9: UNKNOWN | L9: TREATMENT | M9: SRC-V21-DNDI_PORTFOLIO | N9: https://dndi.org/research-development/portfolio/ | O9: 2026-10-29 | P9: SCOPE_REVIEWED_NOT_CURRENT_STATUS | Q9: Identity/routing evidence only. Phase, current activity, clinical equivalence and rights require live verification.
A10: ANCH-MMV | B10: ENT-V2-MMV | E10: PORTFOLIO_SCOPE | F10: P_FALCIPARUM;P_VIVAX | G10: MALARIA | H10: SMALL_MOLECULE | I10: UNKNOWN | J10: UNKNOWN | K10: UNKNOWN | L10: TREATMENT | M10: SRC-V2-PDP_ALLIANCE | N10: https://gardp.org/dndi-gardp-and-mmv-join-forces-to-accelerate-drug-development-for-patients-in-greatest-need/ | O10: 2026-10-29 | P10: SCOPE_REVIEWED_NOT_CURRENT_STATUS | Q10: Malaria organisational mission corroborated by existing PDP alliance source, not own portfolio contents; MMV site access blocked. Specific projects remain unverified.
A11: ANCH-FERRING | B11: CMP-1c39dd558a2 | E11: PORTFOLIO_SCOPE | F11: C_DIFFICILE | G11: RECURRENT_CDI | H11: MICROBIOME | I11: UNKNOWN | J11: MICROBIOTA_RESTORATION | K11: UNKNOWN | L11: PREVENTION;TREATMENT | M11: SRC-FERRING | N11: https://www.ferring.com/science-innovation/research-and-development/product-pipeline/ | O11: 2026-10-29 | P11: SCOPE_REVIEWED_NOT_CURRENT_STATUS | Q11: Identity/routing evidence only. Phase, current activity, clinical equivalence and rights require live verification.
A12: ANCH-EXCISION | B12: CMP-c2df97c26fd | C12: AST-EBT101 | D12: EBT-101 | E12: ASSET_SCOPE | F12: HIV | G12: HIV_CURE | H12: GENE_EDITING | I12: VIRAL_GENOME | J12: GENE_EDITING | K12: UNKNOWN | L12: TREATMENT | M12: SRC-RAD-9142305dd4 | N12: https://excisionbiotherapeutics.com/pipeline | O12: 2026-10-29 | P12: SCOPE_REVIEWED_NOT_CURRENT_STATUS | Q12: Identity/routing evidence only. Phase, current activity, clinical equivalence and rights require live verification.
A13: ANCH-AICURIS | B13: CMP-0c4fb4ab435 | C13: AST-PRITELIVIR | D13: pritelivir | E13: ASSET_SCOPE | F13: HSV | G13: HSV_INFECTION | H13: SMALL_MOLECULE | I13: HELICASE_PRIMASE | J13: ANTIVIRAL | K13: IMMUNOCOMPROMISED | L13: TREATMENT | M13: SRC-V2-AICURIS | N13: https://www.aicuris.com/pipeline-products/ | O13: 2026-10-29 | P13: SCOPE_REVIEWED_NOT_CURRENT_STATUS | Q13: Identity/routing evidence only. Phase, current activity, clinical equivalence and rights require live verification.
A14: ANCH-OLOROFIM | B14: CMP-b3350328f73;CMP-e1f2b6c9f07 | C14: AST-OLOROFIM | D14: olorofim | E14: ASSET_SCOPE | F14: ASPERGILLUS | G14: INVASIVE_ASPERGILLOSIS | H14: SMALL_MOLECULE | I14: UNKNOWN | J14: UNKNOWN | K14: IMMUNOCOMPROMISED | L14: TREATMENT | M14: SRC-V2-F2G_SHIONOGI | N14: https://www.shionogi.com/global/en/news/2026/10/e20261021_3.html | O14: 2026-10-29 | P14: SCOPE_REVIEWED_NOT_CURRENT_STATUS | Q14: Identity/routing evidence only. Phase, current activity, clinical equivalence and rights require live verification.
A15: ANCH-EBVALLO | B15: ENT-V2-PIERRE_FABRE | C15: AST-TABELECLEUCEL | D15: tabelecleucel / Ebvallo | E15: ASSET_SCOPE | F15: EBV | G15: EBV_PTLD | H15: CELL_THERAPY | I15: EBV_ANTIGENS | J15: T_CELL_CYTOTOXICITY | K15: HSCT;SOLID_ORGAN_TRANSPLANT;IMMUNOCOMPROMISED | L15: TREATMENT | M15: SRC-V2-EBVALLO | N15: https://www.ema.europa.eu/de/medicines/human/EPAR/ebvallo | O15: 2026-10-29 | P15: SCOPE_REVIEWED_NOT_CURRENT_STATUS | Q15: Identity/routing evidence only. Phase, current activity, clinical equivalence and rights require live verification.
A16: ANCH-SEQIRUS | B16: CMP-155bfcfe459 | E16: PORTFOLIO_SCOPE | F16: INFLUENZA | G16: PANDEMIC_PREVENTION | H16: VACCINE | I16: UNKNOWN | J16: UNKNOWN | K16: UNKNOWN | L16: PREVENTION | M16: SRC-BD-020 | N16: https://www.cslseqirus.us/partnering | O16: 2026-10-29 | P16: SCOPE_REVIEWED_NOT_CURRENT_STATUS | Q16: Identity/routing evidence only. Phase, current activity, clinical equivalence and rights require live verification.
A17: ANCH-V22-AR105 | B17: CMP-3fd58dd38dd | C17: AST-AR105 | D17: AR-105 / Aerucin | E17: ASSET_SCOPE | F17: P_AERUGINOSA | G17: HAP;VAP | H17: ANTIBODY | I17: UNKNOWN | J17: ANTIVIRULENCE | K17: UNKNOWN | L17: TREATMENT | M17: SRC-V22-ARIDIS | N17: https://www.aridispharma.com/product-overview-2/ | O17: 2026-10-29 | P17: SCOPE_REVIEWED_NOT_CURRENT_STATUS | Q17: Anti-alginate mAb; not anti-PcrV. Live rights/availability check needed.
A18: ANCH-V22-AR101 | B18: CMP-3fd58dd38dd | C18: AST-AR101 | D18: AR-101 / Aerumab | E18: ASSET_SCOPE | F18: P_AERUGINOSA | G18: HAP;VAP | H18: ANTIBODY | I18: UNKNOWN | J18: ANTIVIRULENCE | K18: UNKNOWN | L18: TREATMENT | M18: SRC-V22-ARIDIS | N18: https://www.aridispharma.com/product-overview-2/ | O18: 2026-10-29 | P18: SCOPE_REVIEWED_NOT_CURRENT_STATUS | Q18: Anti-LPS mAb; same pathogen/indication but not anti-PcrV.
A19: ANCH-V22-SCY247 | B19: ENT-V22-SCYNEXIS | C19: AST-SCY247 | D19: SCY-247 | E19: ASSET_SCOPE | F19: CANDIDA;ASPERGILLUS;C_AURIS | G19: INVASIVE_CANDIDIASIS;INVASIVE_ASPERGILLOSIS | H19: SMALL_MOLECULE | I19: UNKNOWN | J19: UNKNOWN | K19: IMMUNOCOMPROMISED | L19: TREATMENT | M19: SRC-V22-SCYNEXIS | N19: https://www.scynexis.com/our-pipeline/ | O19: 2026-10-29 | P19: SCOPE_REVIEWED_NOT_CURRENT_STATUS | Q19: Invasive fungal infection programme; clinical/indication scope needs live check.
A20: ANCH-V22-R21 | B20: CMP-fbe85e38ed1 | C20: AST-R21-MATRIXM | D20: R21 / Matrix-M | E20: ASSET_SCOPE | F20: P_FALCIPARUM | G20: MALARIA | H20: VACCINE | I20: UNKNOWN | J20: UNKNOWN | K20: UNKNOWN | L20: PREVENTION | M20: SRC-V22-NOVAVAX | N20: https://www.novavax.com/products-pipeline/pipeline | O20: 2026-10-29 | P20: SCOPE_REVIEWED_NOT_CURRENT_STATUS | Q20: Partnered product with Serum Institute; approved/prequalified in territories. Not an early pipeline candidate.
A21: ANCH-V22-CANSINO-TB | B21: CMP-add35b11171 | D21: Inhaled TB vaccine | E21: PORTFOLIO_SCOPE | F21: M_TUBERCULOSIS | G21: TB | H21: VACCINE | I21: UNKNOWN | J21: UNKNOWN | K21: UNKNOWN | L21: PREVENTION | M21: SRC-V22-CANSINO | N21: https://www.cansinotech.com/PipelineAndStrategy | O21: 2026-10-29 | P21: SCOPE_REVIEWED_NOT_CURRENT_STATUS | Q21: Portfolio search anchor, phase cannot be inferred.
A22: ANCH-V22-ALIGOS-HBV | B22: CMP-4146497d3c7 | C22: AST-PEVIFOSCORVIR | D22: pevifoscorvir sodium | E22: ASSET_SCOPE | F22: HBV | G22: CHRONIC_HBV | H22: SMALL_MOLECULE | I22: UNKNOWN | J22: UNKNOWN | K22: UNKNOWN | L22: TREATMENT | M22: SRC-V22-ALIGOS | N22: https://aligos.com/science/scientific-overview/ | O22: 2026-10-29 | P22: SCOPE_REVIEWED_NOT_CURRENT_STATUS | Q22: CAM-E HBV drug; trials and current phase live verified separately.
A23: ANCH-V22-BRII-HBV | B23: CMP-bebf092fda0 | C23: AST-BRII179 | D23: BRII-179 | E23: ASSET_SCOPE | F23: HBV | G23: CHRONIC_HBV | H23: VACCINE | I23: UNKNOWN | J23: UNKNOWN | K23: UNKNOWN | L23: TREATMENT | M23: SRC-V22-BRII | N23: https://briibio.com/en/media/press-release/20261029/ | O23: 2026-10-29 | P23: SCOPE_REVIEWED_NOT_CURRENT_STATUS | Q23: Therapeutic priming/immunotherapy; not prophylactic hepatitis vaccine.
A24: ANCH-V22-MARBURG | B24: ENT-V22-SABIN_VACCINE_INSTITUTE | C24: AST-SABIN-MARBURG | D24: Sabin cAd3 Marburg vaccine | E24: ASSET_SCOPE | F24: MARBURG | G24: PANDEMIC_PREVENTION | H24: VACCINE | I24: UNKNOWN | J24: UNKNOWN | K24: UNKNOWN | L24: PREVENTION | M24: SRC-V22-SABIN | N24: https://sabin.org/vaccine-research-and-development/ | O24: 2026-10-29 | P24: SCOPE_REVIEWED_NOT_CURRENT_STATUS | Q24: Nonprofit vaccine developer; current study registration must be refreshed.
A25: ANCH-V22-SUDAN | B25: ENT-V22-SABIN_VACCINE_INSTITUTE | C25: AST-SABIN-SUDAN | D25: Sabin cAd3 Sudan Ebola vaccine | E25: ASSET_SCOPE | F25: SUDAN_EBOLA | G25: PANDEMIC_PREVENTION | H25: VACCINE | I25: UNKNOWN | J25: UNKNOWN | K25: UNKNOWN | L25: PREVENTION | M25: SRC-V22-SABIN | N25: https://sabin.org/vaccine-research-and-development/ | O25: 2026-10-29 | P25: SCOPE_REVIEWED_NOT_CURRENT_STATUS | Q25: Sudan species distinct from Zaire Ebola vaccine.
A26: ANCH-V22-VENATORX | B26: ENT-V22-VENATORX_PHARMACEUTICALS | C26: AST-CEFEPIME-TANIBORBACTAM | D26: cefepime-taniborbactam | E26: ASSET_SCOPE | F26: K_PNEUMONIAE;E_COLI | G26: HAP;VAP;UTI | H26: SMALL_MOLECULE | I26: UNKNOWN | J26: UNKNOWN | K26: UNKNOWN | L26: TREATMENT | M26: SRC-V22-VENATORX | N26: https://accesstomedicinefoundation.org/company/venatorx-pharmaceuticals-inc/amrb | O26: 2026-10-29 | P26: SCOPE_REVIEWED_NOT_CURRENT_STATUS | Q26: Evidence is independent 2026 benchmark rather than developer primary; status, rights and regulator need verification.
A27: ANCH-V23-OPC167832 | B27: CMP-c1c503fce47 | C27: AST-OPC167832 | D27: Quabodepistat / OPC-167832 | E27: ASSET_SCOPE | F27: M_TUBERCULOSIS | G27: TB | H27: SMALL_MOLECULE | I27: DPRE1 | J27: CELL_WALL_INHIBITION | K27: UNKNOWN | L27: TREATMENT | M27: SRC-V23-OTSUKA | N27: https://www.otsuka.co.jp/en/research-and-development/pipeline/ | O27: 2026-10-29 | P27: SCOPE_REVIEWED_NOT_CURRENT_STATUS | Q27: Scope only; current status, rights and clinical comparability require a fresh check.
A28: ANCH-V23-HY133 | B28: CMP-02e13c78d23 | C28: AST-HY133 | D28: HY-133 | E28: ASSET_SCOPE | F28: S_AUREUS | G28: NASAL_DECOLONIZATION | H28: ENDOLYSIN | I28: PEPTIDOGLYCAN | J28: BACTERIAL_LYSIS | K28: UNKNOWN | L28: DECOLONIZATION | M28: SRC-V23-HYPHARM | N28: https://hypharm.de/phagenlysin-wirkstoff-hy-133-start-der-klinischen-phase-i-first-in-human-studie-zur-eliminierung-von-staphylococcus-aureus-im-nasenmikrobiom/ | O28: 2026-10-29 | P28: SCOPE_REVIEWED_NOT_CURRENT_STATUS | Q28: DZIF own project in HY-133 benchmark. Recombinant endolysin, not live phage; exclude own asset from competitor ranking when identified in intake.
A29: ANCH-V23-MRNA1189 | B29: CMP-24531a6b01f | C29: AST-MRNA1189 | D29: mRNA-1189 | E29: ASSET_SCOPE | F29: EBV | G29: INFECTIOUS_MONONUCLEOSIS | H29: MRNA_VACCINE | I29: EBV_ANTIGENS | J29: IMMUNIZATION | K29: UNKNOWN | L29: PREVENTION | M29: SRC-BD-012 | N29: https://www.modernatx.com/research/product-pipeline | O29: 2026-10-29 | P29: SCOPE_REVIEWED_NOT_CURRENT_STATUS | Q29: Preventive EBV vaccine programme, not treatment of EBV-positive PTLD. Clinical registry follow-up required.
A30: ANCH-V23-AR301 | B30: CMP-3fd58dd38dd | C30: AST-AR301 | D30: AR-301 | E30: ASSET_SCOPE | F30: S_AUREUS | G30: VAP;HAP | H30: ANTIBODY | I30: ALPHA_TOXIN | J30: ANTIVIRULENCE | K30: ICU | L30: TREATMENT | M30: SRC-V23-AR301 | N30: https://www.aridispharma.com/ar-301/ | O30: 2026-10-29 | P30: SCOPE_REVIEWED_NOT_CURRENT_STATUS | Q30: Scope only; current status, rights and clinical comparability require a fresh check.
A31: ANCH-V23-HECOLIN | B31: CMP-9d444f16979 | C31: AST-HECOLIN | D31: Hecolin | E31: ASSET_SCOPE | F31: HEV | G31: ACUTE_HEV | H31: VACCINE | I31: HEV_ORF2 | J31: IMMUNIZATION | K31: UNKNOWN | L31: PREVENTION | M31: SRC-V23-INNOVAX | N31: https://www.xiameninnovax.com/products/ | O31: 2026-10-29 | P31: SCOPE_REVIEWED_NOT_CURRENT_STATUS | Q31: HEV prevention vaccine, not a therapeutic antibody or treatment of chronic HEV. Authorization is jurisdiction-specific.
A32: ANCH-V23-CHADOXMERS | B32: CMP-50fc87fe9bd | C32: AST-CHADOX1-MERS | D32: ChAdOx1 MERS | E32: ASSET_SCOPE | F32: MERS_COV | G32: MERS | H32: VIRAL_VECTOR_VACCINE | I32: MERS_SPIKE | J32: IMMUNIZATION | K32: UNKNOWN | L32: PREVENTION | M32: SRC-V23-OXFORD_MERS | N32: https://www.ox.ac.uk/news/2023-09-18-oxford-and-liverpool-scientists-launch-new-vaccine-trial-middle-east-respiratory | O32: 2026-10-29 | P32: SCOPE_REVIEWED_NOT_CURRENT_STATUS | Q32: Official 2023 programme scope. Current trial activity and rights not verified by this reference.
A33: ANCH-V23-EMODEPSIDE | B33: CMP-6dcf8867166 | C33: AST-EMODEPSIDE | D33: Emodepside | E33: ASSET_SCOPE | F33: O_VOLVULUS | G33: ONCHOCERCIASIS | H33: SMALL_MOLECULE | I33: UNKNOWN | J33: ANTHELMINTHIC | K33: UNKNOWN | L33: TREATMENT | M33: SRC-V23-DNDI_FILARIA | N33: https://dndi.org/research-development/portfolio/emodepside/ | O33: 2026-10-29 | P33: SCOPE_REVIEWED_NOT_CURRENT_STATUS | Q33: Clinical alternative for onchocerciasis, distinct from anti-Wolbachia mechanism of CorA. DNDi also collaborates with CorA; asset and organization roles differ.
... A35: ANCH-V23-BULEVIRTIDE | B35: CMP-384891abbee | C35: AST-BULEVIRTIDE | D35: Bulevirtide / Hepcludex | E35: ASSET_SCOPE | F35: HDV | G35: CHRONIC_HDV | H35: PEPTIDE | I35: NTCP | J35: ENTRY_INHIBITION | K35: UNKNOWN | L35: TREATMENT | M35: SRC-V23-HEPCLUDEX | N35: https://www.ema.europa.eu/en/medicines/human/EPAR/hepcludex | O35: 2026-10-29 | P35: SCOPE_REVIEWED_NOT_CURRENT_STATUS | Q35: Approved reference and own project for Hepcludex benchmark. Exclude this asset, not all other Gilead programmes, from self-comparison.

Sheet QUERY_TEMPLATES
A1: query_id | B1: module_id | C1: query_type | D1: template | E1: required_inputs | F1: source_strategy | G1: max_results | H1: status | I1: adapter_status | J1: quality_rule | K1: source_ids | L1: topic_gate | M1: purpose_gate
A2: M01_ENTITY | B2: M01 | C2: ENTITY | D2: "{entity_name}" ({pathogen_query} OR {indication_query}) (pipeline OR trial OR discontinued OR licensing) | E2: entity_name;pathogen_query|indication_query | F2: PRIMARY_SOURCE_FIRST | G2: 20 | H2: ACTIVE | I2: PLANNING_TEMPLATE_NOT_LIVE_TESTED | J2: Entwicklerseite zuerst; keine Modalitaets-UND-Schranke bei identischem Pathogen.
A3: M01_DISCOVERY | B3: M01 | C3: DISCOVERY | D3: ({pathogen_query} OR {indication_query}) (therapeutic OR vaccine OR phage OR endolysin OR antibody OR microbiome) (pipeline OR clinical trial OR research) | E3: pathogen_query|indication_query | F3: PRIMARY_SOURCE_FIRST | G3: 20 | H3: ACTIVE | I3: PLANNING_TEMPLATE_NOT_LIVE_TESTED | J3: Open discovery independent of all company names and match anchors. Query is a research plan, not a completed search.
A4: M01_ACADEMIC_DISCOVERY | B4: M01 | C4: DISCOVERY | D4: ({pathogen_query} OR {indication_query}) (preclinical OR academic OR university OR investigator initiated OR consortium) (therapy OR vaccine OR diagnostic) | E4: pathogen_query|indication_query | F4: INDEPENDENT_ACADEMIC_DISCOVERY | G4: 20 | H4: ACTIVE | I4: PLANNING_TEMPLATE_NOT_LIVE_TESTED | J4: Independent academic/early discovery; no company whitelist, no benchmark expectations loaded; distinguish own projects and clinical purposes. | K4: SRC-V2-PUBMED;SRC-V2-EPMC;SRC-V21-CORDIS;SRC-V21-DRKS;SRC-V21-DZIF_CTU;SRC-V23-DZIF_FLAGSHIP | L4: ANY | M4: ANY
A5: M02_REGISTRY | B5: M02 | C5: REGISTRY | D5: ({pathogen_query} OR {indication_query}) | E5: pathogen_query|indication_query | F5: PRIMARY_SOURCE_FIRST | G5: 20 | H5: ACTIVE | I5: PLANNING_TEMPLATE_NOT_LIVE_TESTED | J5: Erste Suche modalitaetsbreit; zweite Detailabfrage nach Asset/Aliases. Alle Seiten/totalCount pruefen.
A6: M02_ASSET | B6: M02 | C6: REGISTRY | D6: "{asset_name}" | E6: asset_name | F6: PRIMARY_SOURCE_FIRST | G6: 20 | H6: ACTIVE | I6: PLANNING_TEMPLATE_NOT_LIVE_TESTED | J6: Bekannte Register-ID direkt nachladen; sonst exakter Assetname plus Aliases.
A7: M03_LITERATURE | B7: M03 | C7: LITERATURE | D7: ({pathogen_query} OR {indication_query}) AND ({target_query} OR {modality_query}) | E7: pathogen_query|indication_query;target_query|modality_query | F7: PRIMARY_SOURCE_FIRST | G7: 20 | H7: ACTIVE | I7: PLANNING_TEMPLATE_NOT_LIVE_TESTED | J7: Zeitraum separat; PubMed/EuropePMC Syntaxadapter. Fehlende OR-Gruppe nicht als leeren Query senden.
A8: M03_DISCOVERY | B8: M03 | C8: DISCOVERY | D8: ({pathogen_query} OR {indication_query}) (novel target OR mechanism OR preclinical OR platform) | E8: pathogen_query|indication_query | F8: PRIMARY_SOURCE_FIRST | G8: 20 | H8: ACTIVE | I8: PLANNING_TEMPLATE_NOT_LIVE_TESTED | J8: Discovery unabhaengig vom bekannten Target; Review/Originalarbeit/Preprint trennen.
A9: M04_GUIDANCE | B9: M04 | C9: GUIDANCE | D9: ({modality_query} OR {indication_query}) (guideline OR guidance OR assessment) {jurisdiction_query} | E9: modality_query|indication_query | F9: PRIMARY_SOURCE_FIRST | G9: 20 | H9: ACTIVE | I9: PLANNING_TEMPLATE_NOT_LIVE_TESTED | J9: Draft/Final, Version, effective date und Arzneimittel/IVD-Klassifikation speichern.
A10: M05_SOURCE | B10: M05 | C10: FUNDING | D10: "{record_name}" ({pathogen_query} OR {modality_query} OR {topic_query}) call funding | E10: record_name;pathogen_query|modality_query|topic_query | F10: PRIMARY_SOURCE_FIRST | G10: 20 | H10: ACTIVE | I10: PLANNING_TEMPLATE_NOT_LIVE_TESTED | J10: Programmroute zuerst; offener Call erst nach primaer belegter Frist/Eligibility.
A11: M05_DISCOVERY | B11: M05 | C11: DISCOVERY | D11: ({pathogen_query} OR {modality_query}) (call for proposals OR funding opportunity) {applicant_query} | E11: pathogen_query|modality_query | F11: PRIMARY_SOURCE_FIRST | G11: 20 | H11: ACTIVE | I11: PLANNING_TEMPLATE_NOT_LIVE_TESTED | J11: Neue Foerderinstrumente separat suchen; Rechts-/Institutionskontext nicht raten.
A12: M06_ENTITY | B12: M06 | C12: ENTITY | D12: "{entity_name}" ({pathogen_query} OR {modality_query}) (partnering OR collaboration OR licensing) | E12: entity_name;pathogen_query|modality_query | F12: PRIMARY_SOURCE_FIRST | G12: 20 | H12: ACTIVE | I12: PLANNING_TEMPLATE_NOT_LIVE_TESTED | J12: Partnerrolle pruefen: Lizenznehmer, PDP, Investor und CDMO nicht gleichsetzen.
